Workbook

Sheet Data
B1: No | C1: Nama Perusahaan | D1: Tahun | E1: Kas | F1: Aktiva Lancar | G1: Total Aset | H1: Hutang Lancar | I1: Total Hutang | J1: Saldo Laba | K1: Total Ekuitas | L1: Pendapatan | M1: EBIT | N1: Laba Bersih | O1: Persentase Kepemilikan Terbesar | P1: Keterangan | Q1: Jumlah Komisaris Independen | R1: Jumlah Dewan Komisaris | S1: Jumlah Dewan Direksi | T1: Jumlah Dewan Komisaris dan Dewan Direksi | U1: Persentase Kepemilikan oleh Komisaris dan Direksi | V1: BoC Education [Bachelor + (2 x Master) + (2 x MBA) + (3 x PhD)] | W1: TMT Education (Dewan Komisaris) | X1: TMT Education (Dewan Direksi) [Bachelor + (2 x Master) + (2 x MBA) + (3 x PhD)] | Y1: Keterangan Data
A2: Asuransi Jiwa | B2: 1 | C2: Asuransi Jiwa Bersama Bumiputera 1912 | D2: 2014 | E2: 0 | F2: 0 | G2: 0 | H2: 0 | I2: 0 | J2: 0 | K2: 0 | L2: 0 | M2: 0 | N2: 0 | O2: 0 | P2: 0 | Q2: 0 | R2: 0 | T2: 0 | U2: 0 | V2: 0 | W2: =V2 -> 0 | X2: 0 | Y2: Website Tidak Dapat Diakses
D3: 2015 | E3: 0 | F3: 0 | G3: 0 | H3: 0 | I3: 0 | J3: 0 | K3: 0 | L3: 0 | M3: 0 | N3: 0 | O3: 0 | P3: 0 | Q3: 0 | R3: 0 | T3: 0 | U3: 0 | V3: 0 | W3: =V3 -> 0 | X3: 0
D4: 2016 | E4: 0 | F4: 0 | G4: 0 | H4: 0 | I4: 0 | J4: 0 | K4: 0 | L4: 0 | M4: 0 | N4: 0 | O4: 0 | P4: 0 | Q4: 0 | R4: 0 | T4: 0 | U4: 0 | V4: 0 | W4: =V4 -> 0 | X4: 0
D5: 2017 | E5: 0 | F5: 0 | G5: 0 | H5: 0 | I5: 0 | J5: 0 | K5: 0 | L5: 0 | M5: 0 | N5: 0 | O5: 0 | P5: 0 | Q5: 0 | R5: 0 | T5: 0 | U5: 0 | V5: 0 | W5: =V5 -> 0 | X5: 0
D6: 2018 | E6: 0 | F6: 0 | G6: 0 | H6: 0 | I6: 0 | J6: 0 | K6: 0 | L6: 0 | M6: 0 | N6: 0 | O6: 0 | P6: 0 | Q6: 0 | R6: 0 | T6: 0 | U6: 0 | V6: 0 | W6: =V6 -> 0 | X6: 0
D7: 2019 | E7: 0 | F7: 0 | G7: 0 | H7: 0 | I7: 0 | J7: 0 | K7: 0 | L7: 0 | M7: 0 | N7: 0 | O7: 0 | P7: 0 | Q7: 0 | R7: 0 | T7: 0 | U7: 0 | V7: 0 | W7: =V7 -> 0 | X7: 0
D8: 2020 | E8: 0 | F8: 0 | G8: 0 | H8: 0 | I8: 0 | J8: 0 | K8: 0 | L8: 0 | M8: 0 | N8: 0 | O8: 0 | P8: 0 | Q8: 0 | R8: 0 | T8: 0 | U8: 0 | V8: 0 | W8: =V8 -> 0 | X8: 0
D9: 2021 | E9: 0 | F9: 0 | G9: 0 | H9: 0 | I9: 0 | J9: 0 | K9: 0 | L9: 0 | M9: 0 | N9: 0 | O9: 0 | P9: 0 | Q9: 0 | R9: 0 | T9: 0 | U9: 0 | V9: 0 | W9: =V9 -> 0 | X9: 0
D10: 2022 | E10: 0 | F10: 0 | G10: 0 | H10: 0 | I10: 0 | J10: 0 | K10: 0 | L10: 0 | M10: 0 | N10: 0 | O10: 0 | P10: 0 | Q10: 0 | R10: 0 | T10: 0 | U10: 0 | V10: 0 | W10: =V10 -> 0 | X10: 0
D11: 2023 | E11: 0 | F11: 0 | G11: 0 | H11: 0 | I11: 0 | J11: 0 | K11: 0 | L11: 0 | M11: 0 | N11: 0 | O11: 0 | P11: 0 | Q11: 0 | R11: 0 | T11: 0 | U11: 0 | V11: 0 | W11: =V11 -> 0 | X11: 0
D12: 2024 | E12: 0 | F12: 0 | G12: 0 | H12: 0 | I12: 0 | J12: 0 | K12: 0 | L12: 0 | M12: 0 | N12: 0 | O12: 0 | P12: 0 | Q12: 0 | R12: 0 | T12: 0 | U12: 0 | V12: 0 | W12: =V12 -> 0 | X12: 0
B13: 2 | C13: PT AIA Financial | D13: 2014 | E13: 0 | F13: 0 | G13: 0 | H13: 0 | I13: 0 | J13: 0 | K13: 0 | L13: =11948691*1000000 -> 11948691000000 | M13: 0 | N13: 0 | O13: 0 | P13: 0 | Q13: 0 | R13: 0 | T13: 0 | U13: 0 | V13: 0 | W13: =V13 -> 0
D14: 2015 | E14: =322334*1000000 -> 322334000000 | F14: =(1650409-423263-273144-2863)*1000000 -> 951139000000 | G14: =31860954*1000000 -> 31860954000000 | H14: =1833519*1000000 -> 1833519000000 | I14: =25291701*1000000 -> 25291701000000 | J14: =5786895*1000000 -> 5786895000000 | K14: =6569253*1000000 -> 6569253000000 | L14: =8985907*1000000 -> 8985907000000 | M14: =1649123*1000000 -> 1649123000000 | N14: =848437*1000000 -> 848437000000 | O14: 0.8 | P14: AIA International Limited | Q14: 2 | R14: 4 | S14: 5 | T14: =S14+R14 -> 9 | U14: 0 | V14: 0 | W14: 0 | X14: 0
D15: 2016 | E15: =383884*1000000 -> 383884000000 | F15: =(1714053-378107-214642-2511)*1000000 -> 1118793000000 | G15: =35767906*1000000 -> 35767906000000 | H15: =2103474*1000000 -> 2103474000000 | I15: =28001542*1000000 -> 28001542000000 | J15: =6850440*1000000 -> 6850440000000 | K15: =7766364*1000000 -> 7766364000000 | L15: =13264521*1000000 -> 13264521000000 | M15: =1034240*1000000 -> 1034240000000 | N15: =1197111*1000000 -> 1197111000000 | O15: 0.8 | P15: AIA International Limited | Q15: 2 | R15: 4 | S15: 5 | T15: =S15+R15 -> 9 | U15: 0 | V15: 0 | W15: 0 | X15: 0
D16: 2017 | E16: =461296*1000000 -> 461296000000 | F16: =(2647963-1137872-205000-15613-2158)*1000000 -> 1287320000000 | G16: =44937292*1000000 -> 44937292000000 | H16: =3116639*1000000 -> 3116639000000 | I16: =34375378*1000000 -> 34375378000000 | J16: =7239986*1000000 -> 7239986000000 | K16: =10561914*1000000 -> 10561914000000 | L16: =15523134*1000000 -> 15523134000000 | M16: =542068*1000000 -> 542068000000 | N16: =1562417*1000000 -> 1562417000000 | O16: 0.95 | P16: AIA International Limited | Q16: 2 | R16: 4 | S16: 5 | T16: =S16+R16 -> 9 | U16: 0 | V16: 0 | W16: 0 | X16: 0
D17: 2018 | E17: =718593*1000000 -> 718593000000 | F17: =(3478638-1737464-222358-7146-1858)*1000000 -> 1509812000000 | G17: =46562563*1000000 -> 46562563000000 | H17: =3329580*1000000 -> 3329580000000 | I17: =35535336*1000000 -> 35535336000000 | J17: =8566661*1000000 -> 8566661000000 | K17: =11027227*1000000 -> 11027227000000 | L17: =12786352*1000000 -> 12786352000000 | M17: =2150147*1000000 -> 2150147000000 | N17: =1065313*1000000 -> 1065313000000 | O17: 0.95 | P17: AIA International Limited | Q17: 2 | R17: 4 | S17: 5 | T17: =S17+R17 -> 9 | U17: 0 | V17: 0 | W17: 0 | X17: 0
D18: 2019 | E18: =1028736*1000000 -> 1028736000000 | F18: =(5436824-3135551-275043-4811-1597)*1000000 -> 2019822000000 | G18: =50043024*1000000 -> 50043024000000 | H18: =3399335*1000000 -> 3399335000000 | I18: =38172435*1000000 -> 38172435000000 | J18: =7904525*1000000 -> 7904525000000 | K18: =11870589*1000000 -> 11870589000000 | L18: =15545577*1000000 -> 15545577000000 | M18: =449893*1000000 -> 449893000000 | N18: =2104310*1000000 -> 2104310000000 | O18: 0.9499 | P18: AIA International Limited | Q18: 2 | R18: 4 | S18: 4 | T18: =S18+R18 -> 8 | U18: 0 | V18: 0 | W18: 0 | X18: 0
D19: 2020 | E19: =1275183*1000000 -> 1275183000000 | F19: =(7128145-4572994-363789-454-1336)*1000000 -> 2189572000000 | G19: =53134780*1000000 -> 53134780000000 | H19: =3640926*1000000 -> 3640926000000 | I19: =41373205*1000000 -> 41373205000000 | J19: =7057134*1000000 -> 7057134000000 | K19: =11761575*1000000 -> 11761575000000 | L19: =15658951*1000000 -> 15658951000000 | M19: =718592*1000000 -> 718592000000 | N19: =(-410562)*1000000 -> -410562000000 | O19: 0.9499 | P19: AIA International Limited | Q19: 2 | R19: 4 | S19: 4 | T19: =S19+R19 -> 8 | U19: 0 | V19: 0 | W19: 0 | X19: 0
D20: 2021 | E20: =1225179*1000000 -> 1225179000000 | F20: =(5404009-2571985-498366-384-1074)*1000000 -> 2332200000000 | G20: =52330016*1000000 -> 52330016000000 | H20: =3465695*1000000 -> 3465695000000 | I20: =40473683*1000000 -> 40473683000000 | J20: =6523045*1000000 -> 6523045000000 | K20: =11856333*1000000 -> 11856333000000 | L20: =15671921*1000000 -> 15671921000000 | M20: =1143810*1000000 -> 1143810000000 | N20: =-586757*1000000 -> -586757000000 | O20: 0.9499 | P20: AIA International Limited | Q20: 1 | R20: 3 | S20: 4 | T20: =S20+R20 -> 7 | U20: 0 | V20: 0 | W20: 0 | X20: 0
D21: 2022 | E21: =1379712*1000000 -> 1379712000000 | F21: =(5171825-2010624-605983-376-905)*1000000 -> 2553937000000 | G21: =44912325*1000000 -> 44912325000000 | H21: =3771309*1000000 -> 3771309000000 | I21: =36682436*1000000 -> 36682436000000 | J21: =5603024*1000000 -> 5603024000000 | K21: =8229889*1000000 -> 8229889000000 | L21: =11948182*1000000 -> 11948182000000 | M21: =2655031*1000000 -> 2655031000000 | N21: =-785208*1000000 -> -785208000000 | O21: 0.9499 | P21: AIA International Limited | Q21: 1 | R21: 3 | S21: 4 | T21: =S21+R21 -> 7 | U21: 0 | V21: 0 | W21: 0 | X21: 0
D22: 2023 | E22: =841975*1000000 -> 841975000000 | F22: =(4935701-1917920-799475-802)*1000000 -> 2217504000000 | G22: =41785302*1000000 -> 41785302000000 | H22: =3324784*1000000 -> 3324784000000 | I22: =33736676*1000000 -> 33736676000000 | J22: =6019271*1000000 -> 6019271000000 | K22: =8048626*1000000 -> 8048626000000 | L22: =12931853*1000000 -> 12931853000000 | M22: =1674911*1000000 -> 1674911000000 | N22: =876769*1000000 -> 876769000000 | O22: 0.9499 | P22: AIA International Limited | Q22: 2 | R22: 4 | S22: 5 | T22: =S22+R22 -> 9 | U22: 0 | V22: 0 | W22: 0 | X22: 0
D23: 2024 | E23: =1063869*1000000 -> 1063869000000 | F23: =(5779370-2783963-760527-699)*1000000 -> 2234181000000 | G23: =39899482*1000000 -> 39899482000000 | H23: =2965577*1000000 -> 2965577000000 | I23: =30987181*1000000 -> 30987181000000 | J23: =7306046*1000000 -> 7306046000000 | K23: =8912301*1000000 -> 8912301000000 | L23: =10095098*1000000 -> 10095098000000 | M23: =1789193*1000000 -> 1789193000000 | N23: =1419919*1000000 -> 1419919000000 | O23: 0.9499 | P23: AIA International Limited | Q23: 1 | R23: 3 | S23: 5 | T23: =S23+R23 -> 8 | U23: 0 | V23: 0 | W23: 0 | X23: 0
B24: 3 | C24: PT Asuransi Allianz Life Indonesia | D24: 2014 | E24: 0 | F24: 0 | G24: 0 | H24: 0 | I24: 0 | J24: 0 | K24: 0 | L24: =12354658*1000000 -> 12354658000000 | M24: 0 | N24: 0 | O24: 0 | P24: 0 | Q24: 0 | R24: 0 | T24: 0 | U24: 0 | W24: =V24 -> 0
D25: 2015 | E25: =459323*1000000 -> 459323000000 | F25: =(459323+26775+202537)*1000000 -> 688635000000 | G25: =27635118*1000000 -> 27635118000000 | H25: =(114268+204780+18994+18963+308951)*1000000 -> 665956000000 | I25: =22909265*1000000 -> 22909265000000 | J25: =3103856*1000000 -> 3103856000000 | K25: =4355995*1000000 -> 4355995000000 | L25: =8593467*1000000 -> 8593467000000 | M25: =903774*1000000 -> 903774000000 | N25: =806099*1000000 -> 806099000000 | O25: 0.9976 | P25: Allianz Asia Pacific & Africa GmbH | Q25: 2 | R25: 3 | S25: 4 | T25: =R25+S25 -> 7 | U25: 0 | V25: 0 | W25: =V25 -> 0 | X25: 0
D26: 2016 | E26: =541939*1000000 -> 541939000000 | F26: =(541939+29637+365907)*1000000 -> 937483000000 | G26: =30294789*1000000 -> 30294789000000 | H26: =(111313+264934+97766+479554)*1000000 -> 953567000000 | I26: =24436046*1000000 -> 24436046000000 | J26: =3996502*1000000 -> 3996502000000 | K26: =5381290*1000000 -> 5381290000000 | L26: =11372680*1000000 -> 11372680000000 | M26: =905890*1000000 -> 905890000000 | N26: =899890*1000000 -> 899890000000 | O26: 0.9976 | P26: Allianz Asia Pacific & Africa GmbH | Q26: 2 | R26: 3 | S26: 4 | T26: =R26+S26 -> 7 | U26: 0 | V26: 0 | W26: =V26 -> 0 | X26: 0
D27: 2017 | E27: =400675*1000000 -> 400675000000 | F27: =(400675+10953+750970)*1000000 -> 1162598000000 | G27: =35751863*1000000 -> 35751863000000 | H27: =(111504+364624+29852+738671)*1000000 -> 1244651000000 | I27: =27527468*1000000 -> 27527468000000 | J27: =4311634*1000000 -> 4311634000000 | K27: =6030989*1000000 -> 6030989000000 | L27: =13302120*1000000 -> 13302120000000 | M27: =329564*1000000 -> 329564000000 | N27: =649699*1000000 -> 649699000000 | O27: 0.9976 | P27: Allianz Asia Pacific & Africa GmbH | Q27: 2 | R27: 4 | S27: 5 | T27: =R27+S27 -> 9 | U27: 0 | V27: 0 | W27: =V27 -> 0 | X27: 0
D28: 2018 | E28: =445074*1000000 -> 445074000000 | F28: =(445074+8503+985111)*1000000 -> 1438688000000 | G28: =35266933*1000000 -> 35266933000000 | H28: =(123243+422315+186769+73+847856)*1000000 -> 1580256000000 | I28: =27304202*1000000 -> 27304202000000 | J28: =4737672*1000000 -> 4737672000000 | K28: =5768100*1000000 -> 5768100000000 | L28: =10531156*1000000 -> 10531156000000 | M28: =899975*1000000 -> 899975000000 | N28: =137111*1000000 -> 137111000000 | O28: 0.9976 | P28: Allianz Asia Pacific & Africa GmbH | Q28: 2 | R28: 3 | S28: 6 | T28: =R28+S28 -> 9 | U28: 0 | V28: 0 | W28: =V28 -> 0 | X28: 0
D29: 2019 | E29: =593701*1000000 -> 593701000000 | F29: =(593701+586967+794491)*1000000 -> 1975159000000 | G29: =38345233*1000000 -> 38345233000000 | H29: =(50269+421228+177272+70491+572518)*1000000 -> 1291778000000 | I29: =29736010*1000000 -> 29736010000000 | J29: =5161928*1000000 -> 5161928000000 | K29: =6511324*1000000 -> 6511324000000 | L29: =15153459*1000000 -> 15153459000000 | M29: =1526889*1000000 -> 1526889000000 | N29: =1493224*1000000 -> 1493224000000 | O29: 0.9976 | P29: Allianz Asia Pacific & Africa GmbH | Q29: 2 | R29: 3 | S29: 6 | T29: =R29+S29 -> 9 | U29: 0 | V29: 0 | W29: =V29 -> 0 | X29: 0
D30: 2020 | E30: =757656*1000000 -> 757656000000 | F30: =(757656+912739+874268)*1000000 -> 2544663000000 | G30: =41166712*1000000 -> 41166712000000 | H30: =(50367+650691+134806+97681+509680)*1000000 -> 1443225000000 | I30: =31830554*1000000 -> 31830554000000 | J30: =5998414*1000000 -> 5998414000000 | K30: =7090980*1000000 -> 7090980000000 | L30: =18812789*1000000 -> 18812789000000 | M30: =1691295*1000000 -> 1691295000000 | N30: =1129656*1000000 -> 1129656000000 | O30: 0.9976 | P30: Allianz Asia Pacific & Africa GmbH | Q30: 2 | R30: 3 | S30: 6 | T30: =R30+S30 -> 9 | U30: 0 | V30: =3+(2*1)+(2*0)+(3*1) -> 8 | W30: =V30 -> 8 | X30: =6+(2*4) -> 14
D31: 2021 | E31: =781493*1000000 -> 781493000000 | F31: =(781493+1075393+994241)*1000000 -> 2851127000000 | G31: =42808931*1000000 -> 42808931000000 | H31: =(87103+679306+83026+1367+689159)*1000000 -> 1539961000000 | I31: =33849131*1000000 -> 33849131000000 | J31: =5949541*1000000 -> 5949541000000 | K31: =6945025*1000000 -> 6945025000000 | L31: =20725660*1000000 -> 20725660000000 | M31: =561475*1000000 -> 561475000000 | N31: =404045*1000000 -> 404045000000 | O31: 0.9976 | P31: Allianz Asia Pacific & Africa GmbH | Q31: 2 | R31: 4 | S31: 5 | T31: =R31+S31 -> 9 | U31: 0 | V31: =4+(2*1)+(2*0)+(3*1) -> 9 | W31: =V31 -> 9 | X31: =5+(2*3) -> 11
D32: 2022 | E32: =917912*1000000 -> 917912000000 | F32: =(917912+1432787+1061310)*1000000 -> 3412009000000 | G32: =41194961*1000000 -> 41194961000000 | H32: =(54342+607177+117687+2986+1539088)*1000000 -> 2321280000000 | I32: =32037270*1000000 -> 32037270000000 | J32: =6757463*1000000 -> 6757463000000 | K32: =7208812*1000000 -> 7208812000000 | L32: =14203983*1000000 -> 14203983000000 | M32: =597200*1000000 -> 597200000000 | N32: =107318*1000000 -> 107318000000 | O32: 0.9976 | P32: Allianz Asia Pacific & Africa GmbH | Q32: 2 | R32: 3 | S32: 4 | T32: =R32+S32 -> 7 | U32: 0 | V32: =3+(2*1)+(3*1) -> 8 | W32: =V32 -> 8 | X32: =4+(2*2) -> 8
D33: 2023 | E33: =1253189*1000000 -> 1253189000000 | F33: =(1253189+1054946+1251808)*1000000 -> 3559943000000 | G33: =40147448*1000000 -> 40147448000000 | H33: =(50113+742554+60377+193361+1535406)*1000000 -> 2581811000000 | I33: =31712785*1000000 -> 31712785000000 | J33: =6154142*1000000 -> 6154142000000 | K33: =6640072*1000000 -> 6640072000000 | L33: =17375945*1000000 -> 17375945000000 | M33: =372376*1000000 -> 372376000000 | N33: =481260*1000000 -> 481260000000 | O33: 0.9976 | P33: Allianz Asia Pacific & Africa GmbH | Q33: 2 | R33: 4 | S33: 4 | T33: =R33+S33 -> 8 | U33: 0 | V33: =3+(2*1)+(3*1) -> 8 | W33: =V33 -> 8 | X33: =4+(2*2)+(2*1) -> 10
D34: 2024 | E34: =1400159*1000000 -> 1400159000000 | F34: =(1400159+565832+619462)*1000000 -> 2585453000000 | G34: =39131978*1000000 -> 39131978000000 | H34: =(74394+717562+214968+7499+1720606)*1000000 -> 2735029000000 | I34: =30372565*1000000 -> 30372565000000 | J34: =6934793*1000000 -> 6934793000000 | K34: =7301939*1000000 -> 7301939000000 | L34: =18185132*1000000 -> 18185132000000 | M34: =1242464*1000000 -> 1242464000000 | N34: =961867*1000000 -> 961867000000 | O34: 0.9976 | P34: Allianz Asia Pacific & Africa GmbH | Q34: 2 | R34: 4 | S34: 3 | T34: =R34+S34 -> 7 | U34: 0 | V34: =3+(2*1)+(3*1) -> 8 | W34: =V34 -> 8 | X34: =2+(2*1)+(2*1) -> 6
B35: 4 | C35: PT Asuransi Allianz Life Syariah Indonesia | D35: 2014 | E35: 0 | F35: 0 | G35: 0 | H35: 0 | I35: 0 | J35: 0 | K35: 0 | L35: 0 | M35: 0 | N35: 0 | O35: 0 | P35: 0 | Q35: 0 | R35: 0 | T35: 0 | U35: 0 | V35: 0 | W35: 0 | X35: 0
D36: 2015 | E36: 0 | F36: 0 | G36: 0 | H36: 0 | I36: 0 | J36: 0 | K36: 0 | L36: 0 | M36: 0 | N36: 0 | O36: 0 | P36: 0 | Q36: 0 | R36: 0 | T36: 0 | U36: 0 | V36: 0 | W36: 0 | X36: 0
D37: 2016 | E37: 0 | F37: 0 | G37: 0 | H37: 0 | I37: 0 | J37: 0 | K37: 0 | L37: 0 | M37: 0 | N37: 0 | O37: 0 | P37: 0 | Q37: 0 | R37: 0 | T37: 0 | U37: 0 | V37: 0 | W37: 0 | X37: 0
D38: 2017 | E38: 0 | F38: 0 | G38: 0 | H38: 0 | I38: 0 | J38: 0 | K38: 0 | L38: 0 | M38: 0 | N38: 0 | O38: 0 | P38: 0 | Q38: 0 | R38: 0 | T38: 0 | U38: 0 | V38: 0 | W38: 0 | X38: 0
D39: 2018 | E39: 0 | F39: 0 | G39: 0 | H39: 0 | I39: 0 | J39: 0 | K39: 0 | L39: 0 | M39: 0 | N39: 0 | O39: 0 | P39: 0 | Q39: 0 | R39: 0 | T39: 0 | U39: 0 | V39: 0 | W39: 0 | X39: 0
D40: 2019 | E40: 0 | F40: 0 | G40: 0 | H40: 0 | I40: 0 | J40: 0 | K40: 0 | L40: 0 | M40: 0 | N40: 0 | O40: 0 | P40: 0 | Q40: 0 | R40: 0 | T40: 0 | U40: 0 | V40: 0 | W40: 0 | X40: 0
D41: 2020 | E41: 0 | F41: 0 | G41: 0 | H41: 0 | I41: 0 | J41: 0 | K41: 0 | L41: 0 | M41: 0 | N41: 0 | O41: 0 | P41: 0 | Q41: 0 | R41: 0 | T41: 0 | U41: 0 | V41: 0 | W41: 0 | X41: 0
D42: 2021 | E42: 0 | F42: 0 | G42: 0 | H42: 0 | I42: 0 | J42: 0 | K42: 0 | L42: 0 | M42: 0 | N42: 0 | O42: 0 | P42: 0 | Q42: 0 | R42: 0 | T42: 0 | U42: 0 | V42: 0 | W42: 0 | X42: 0
D43: 2022 | E43: =172936*1000000 -> 172936000000 | F43: =(172936+178309+38650+20813)*1000000 -> 410708000000 | G43: =4337827*1000000 -> 4337827000000 | H43: =(7536+508644)*1000000 -> 516180000000 | I43: =891833*1000000 -> 891833000000 | J43: =-184*1000000 -> -184000000 | K43: =(100000+1426413-29114+184)*1000000 -> 1497483000000 | L43: =1070003*1000000 -> 1070003000000 | M43: =382608*1000000 -> 382608000000 | N43: =382661*1000000 -> 382661000000 | O43: 0 | P43: 0 | Q43: 0 | R43: 0 | T43: 0 | U43: 0 | V43: 0 | W43: 0 | X43: 0
D44: 2023 | E44: =206081*1000000 -> 206081000000 | F44: =(206081+125610+267394+13404)*1000000 -> 612489000000 | G44: =3620310*1000000 -> 3620310000000 | H44: =(45570+175470+211743)*1000000 -> 432783000000 | I44: =867595*1000000 -> 867595000000 | J44: =-22950*1000000 -> -22950000000 | K44: =(100000+838900-3726+22950)*1000000 -> 958124000000 | L44: =1217667*1000000 -> 1217667000000 | M44: =221160*1000000 -> 221160000000 | N44: =232895*1000000 -> 232895000000 | O44: 0.9999 | P44: PT Asuransi Allianz Life Indonesia | Q44: 2 | R44: 3 | S44: 3 | T44: =S44+R44 -> 6 | U44: 0 | V44: 0 | W44: 0 | X44: 0
D45: 2024 | E45: =160128*1000000 -> 160128000000 | F45: =(160128+46432+65350+20442)*1000000 -> 292352000000 | G45: =3339322*1000000 -> 3339322000000 | H45: =(36644+334134)*1000000 -> 370778000000 | I45: =913660*1000000 -> 913660000000 | J45: =65665*1000000 -> 65665000000 | K45: =(100000+808430-5907+65665)*1000000 -> 968188000000 | L45: =1130418*1000000 -> 1130418000000 | M45: =69939*1000000 -> 69939000000 | N45: =58584*1000000 -> 58584000000 | O45: 0.99 | P45: PT Asuransi Allianz Life Indonesia | Q45: 2 | R45: 3 | S45: 3 | T45: =S45+R45 -> 6 | U45: 0 | V45: 0 | W45: 0 | X45: 0
B46: 5 | C46: PT Asuransi BRI Life | D46: 2014 | E46: 0 | F46: 0 | G46: 0 | H46: 0 | I46: 0 | J46: 0 | K46: 0 | L46: 0 | M46: 0 | N46: 0 | O46: 0 | P46: 0 | Q46: 0 | R46: 0 | S46: 0 | T46: 0 | U46: 0 | V46: 0 | W46: 0 | X46: 0
D47: 2015 | E47: =31270004*1000 -> 31270004000 | F47: =(31270004+77490113+45534291+259061313+7743719+13551301+33711049)*1000 -> 468361790000 | G47: =4933308738*1000 -> 4933308738000 | H47: =(34595124+7506146+55379253+1025192+32338508+81747961)*1000 -> 212592184000 | I47: =3608103108*1000 -> 3608103108000 | J47: =(612198897+567512452)*1000 -> 1179711349000 | K47: =4933308738*1000 -> 4933308738000 | L47: 0 | M47: 0 | N47: 0 | O47: 0 | P47: 0 | Q47: 0 | R47: 0 | S47: 0 | T47: 0 | U47: 0 | V47: 0 | W47: 0 | X47: 0
D48: 2016 | E48: =47737525*1000 -> 47737525000 | F48: =(47737535+26372725+53428744+231858058+6175234+12572361+13315384)*1000 -> 391460041000 | G48: =6176329027*1000 -> 6176329027000 | H48: =(10800635+7379785+1164024+1685837+48804757+62931273)*1000 -> 132766311000 | I48: =4512591084*1000 -> 4512591084000 | J48: =(612198897+781533993)*1000 -> 1393732890000 | K48: =6176329027*1000 -> 6176329027000 | L48: =3542155857*1000 -> 3542155857000 | M48: =205478355*1000 -> 205478355000 | N48: =331486312*1000 -> 331486312000 | O48: 0 | P48: 0 | Q48: 0 | R48: 0 | S48: 0 | T48: 0 | U48: 0 | V48: 0 | W48: 0 | X48: 0
D49: 2017 | E49: =51803533*1000 -> 51803533000 | F49: =(51803533+20464954+64353745+269187118+7213610+55814574+14868375)*1000 -> 483705909000 | G49: =8162691116*1000 -> 8162691116000 | H49: =(20665270+14209189+1155193+1042740+50202928+82905755)*1000 -> 170181075000 | I49: =5984418466*1000 -> 5984418466000 | J49: =(794117206+891417232)*1000 -> 1685534438000 | K49: =2104006591*1000 -> 2104006591000 | L49: =4403365381*1000 -> 4403365381000 | M49: =355529117*1000 -> 355529117000 | N49: =538226085*1000 -> 538226085000 | O49: 0.91 | P49: PT Bank Rakyat Indonesia | Q49: 3 | R49: 5 | S49: 6 | T49: =SUM(R49:S49) -> 11 | U49: 0 | V49: =5+(2*4) -> 13 | W49: =V49 -> 13 | X49: =6+(2*4)+(3*1) -> 17
D50: 2018 | E50: =61423379*1000 -> 61423379000 | F50: =(61423379+29031114+77407721+311731510+5113655+69301022+10037283)*1000 -> 564045684000 | G50: =9356504263*1000 -> 9356504263000 | H50: =(31530041+8801561+71869450+1119625+29546320+219912207)*1000 -> 362779204000 | I50: =7033564683*1000 -> 7033564683000 | J50: =(958227519+1163594728)*1000 -> 2121822247000 | K50: =2231804990*1000 -> 2231804990000 | L50: =4872269263*1000 -> 4872269263000 | M50: =784108783*1000 -> 784108783000 | N50: =291908712*1000 -> 291908712000 | O50: 0.91 | P50: PT Bank Rakyat Indonesia | Q50: 2 | R50: 5 | S50: 6 | T50: =SUM(R50:S50) -> 11 | U50: 0 | V50: =5+(2*4) -> 13 | W50: =V50 -> 13 | X50: =6+(2*5) -> 16
D51: 2019 | E51: =68265*1000000 -> 68265000000 | F51: =(68265+42754+83633+247698+9216+38704+16436)*1000000 -> 506706000000 | G51: =11084971*1000000 -> 11084971000000 | H51: =(37557+15699+22200+1016+70306+175303)*1000000 -> 322081000000 | I51: =8407279*1000000 -> 8407279000000 | J51: =(1438546+886463)*1000000 -> 2325009000000 | K51: =2563929*1000000 -> 2563929000000 | L51: =5671048*1000000 -> 5671048000000 | M51: =336198*1000000 -> 336198000000 | N51: =452204*1000000 -> 452204000000 | O51: 0.9101 | P51: PT Bank Rakyat Indonesia | Q51: 3 | R51: 6 | S51: 6 | T51: =SUM(R51:S51) -> 12 | U51: 0 | V51: =6+(2*5) -> 16 | W51: =V51 -> 16 | X51: =6+(2*5) -> 16
D52: 2020 | E52: =95700*1000000 -> 95700000000 | F52: =(95700+49055+93216+333507+11770+128853+11039)*1000000 -> 723140000000 | G52: =13044264*1000000 -> 13044264000000 | H52: =(21171+1730+2826+990+45871+182754)*1000000 -> 255342000000 | I52: =10081934*1000000 -> 10081934000000 | J52: =(1761813+625586)*1000000 -> 2387399000000 | K52: =2794003*1000000 -> 2794003000000 | L52: =6379851*1000000 -> 6379851000000 | M52: =53150*1000000 -> 53150000000 | N52: =230074*1000000 -> 230074000000 | O52: 0.9101 | P52: PT Bank Rakyat Indonesia | Q52: 2 | R52: 4 | S52: 4 | T52: =SUM(R52:S52) -> 8 | U52: 0 | V52: =4+(2*4) -> 12 | W52: =V52 -> 12 | X52: =4+(2*3) -> 10
D53: 2021 | E53: =79576*1000000 -> 79576000000 | F53: =(79576+50250+97444+443441+40888+121624+15238)*1000000 -> 848461000000 | G53: =18260736*1000000 -> 18260736000000 | H53: =(49991+535+4980+1214+80034+809405)*1000000 -> 946159000000 | I53: =11381796*1000000 -> 11381796000000 | J53: =(1761813+775625)*1000000 -> 2537438000000 | K53: =6683102*1000000 -> 6683102000000 | L53: =7264440*1000000 -> 7264440000000 | M53: =130173*1000000 -> 130173000000 | N53: =39099*1000000 -> 39099000000 | O53: 0.6383 | P53: PT Bank Rakyat Indonesia | Q53: 4 | R53: 6 | S53: 8 | T53: =SUM(R53:S53) -> 14 | U53: 0 | V53: =6+(2*4) -> 14 | W53: =V53 -> 14 | X53: =8+(2*6) -> 20
D54: 2022 | E54: =65266*1000000 -> 65266000000 | F54: =(65266+85330+148528+808664+26750+81336+23992)*1000000 -> 1239866000000 | G54: =21494817*1000000 -> 21494817000000 | H54: =(361051+345+10662+1104+131183+73534)*1000000 -> 577879000000 | I54: =13552263*1000000 -> 13552263000000 | J54: =(1761813+1089871)*1000000 -> 2851684000000 | K54: =7706566*1000000 -> 7706566000000 | L54: =9141344*1000000 -> 9141344000000 | M54: =385371*1000000 -> 385371000000 | N54: =283472*1000000 -> 283472000000 | O54: 0.5902 | P54: PT Bank Rakyat Indonesia | Q54: 3 | R54: 5 | S54: 5 | T54: =SUM(R54:S54) -> 10 | U54: 0 | V54: =5+(2*3) -> 11 | W54: =V54 -> 11 | X54: =5+(2*3) -> 11
D55: 2023 | E55: =66255*1000000 -> 66255000000 | F55: =(66255+79543+189806+324161+5847+135720+29940)*1000000 -> 831272000000 | G55: =23552167*1000000 -> 23552167000000 | H55: =(39484+1139+4803+1002+176528+95578)*1000000 -> 318534000000 | I55: =14172581*1000000 -> 14172581000000 | J55: =(1761813+1624979)*1000000 -> 3386792000000 | K55: =9111525*1000000 -> 9111525000000 | L55: =9194450*1000000 -> 9194450000000 | M55: =618387*1000000 -> 618387000000 | N55: =634959*1000000 -> 634959000000 | O55: 0.5477 | P55: PT Bank Rakyat Indonesia | Q55: 3 | R55: 5 | S55: 5 | T55: =SUM(R55:S55) -> 10 | U55: 0 | V55: =5+(2*3)+(3*1) -> 14 | W55: =V55 -> 14 | X55: =5+(2*4) -> 13
D56: 2024 | E56: 0 | F56: 0 | G56: 0 | H56: 0 | I56: 0 | J56: 0 | K56: 0 | L56: 0 | M56: 0 | N56: 0 | O56: 0 | P56: 0 | Q56: 0 | R56: 0 | S56: 0 | T56: 0 | U56: 0 | V56: 0 | W56: 0 | X56: 0
B57: 6 | C57: PT Asuransi Ciputra Indonesia | D57: 2014 | E57: 0 | F57: 0 | G57: 0 | H57: 0 | I57: 0 | J57: 0 | K57: 0 | L57: 0 | M57: 0 | N57: 0 | O57: 0 | P57: 0 | Q57: 0 | R57: 0 | T57: 0 | U57: 0 | W57: =V57 -> 0
D58: 2015 | E58: 0 | F58: 0 | G58: 0 | H58: 0 | I58: 0 | J58: 0 | K58: 0 | L58: 0 | M58: 0 | N58: 0 | O58: 0 | P58: 0 | Q58: 0 | R58: 0 | T58: 0 | U58: 0 | W58: =V58 -> 0
D59: 2016 | E59: =7117*1000000 -> 7117000000 | F59: =(8507-9-1382)*1000000 -> 7116000000 | G59: =98507*1000000 -> 98507000000 | H59: =3417*1000000 -> 3417000000 | I59: =3417*1000000 -> 3417000000 | J59: =-4909*1000000 -> -4909000000 | K59: =95091*1000000 -> 95091000000 | L59: =3041*1000000 -> 3041000000 | M59: =-4909*1000000 -> -4909000000 | N59: =-4909*1000000 -> -4909000000 | O59: 0 | P59: 0 | Q59: 0 | R59: 0 | T59: 0 | U59: 0 | W59: =V59 -> 0
D60: 2017 | E60: =5273*1000000 -> 5273000000 | F60: =(16686-3395-5091)*1000000 -> 8200000000 | G60: =116479*1000000 -> 116479000000 | H60: =7335*1000000 -> 7335000000 | I60: =11160*1000000 -> 11160000000 | J60: =(-25649)*1000000 -> -25649000000 | K60: =105319*1000000 -> 105319000000 | L60: =13468*1000000 -> 13468000000 | M60: =-20740*1000000 -> -20740000000 | N60: =-19772*1000000 -> -19772000000 | O60: 0.6 | P60: PT Ciputra Internasional | Q60: 2 | R60: 4 | S60: 3 | T60: 7 | U60: 0 | V60: =4+(2*1)+(2*3) -> 12 | W60: =V60 -> 12 | X60: =3+(2*2) -> 7
D61: 2018 | E61: =9389*1000000 -> 9389000000 | F61: =(33970-4086-7331)*1000000 -> 22553000000 | G61: =152680*1000000 -> 152680000000 | H61: =15989*1000000 -> 15989000000 | I61: =50492*1000000 -> 50492000000 | J61: =-76064*1000000 -> -76064000000 | K61: =102188*1000000 -> 102188000000 | L61: =59888*1000000 -> 59888000000 | M61: =-50414*1000000 -> -50414000000 | N61: =-43131*1000000 -> -43131000000 | O61: 0.6 | P61: PT Ciputra Internasional | Q61: 2 | R61: 4 | S61: 3 | T61: 7 | U61: 0 | V61: =4+(2*1)+(2*3) -> 12 | W61: =V61 -> 12 | X61: =3+(2*2) -> 7
D62: 2019 | E62: =9265*1000000 -> 9265000000 | F62: =(44980-1188-9522)*1000000 -> 34270000000 | G62: =214472*1000000 -> 214472000000 | H62: =14816*1000000 -> 14816000000 | I62: =87535*1000000 -> 87535000000 | J62: =-119946*1000000 -> -119946000000 | K62: =126937*1000000 -> 126937000000 | L62: =104287*1000000 -> 104287000000 | M62: =-43882*1000000 -> -43882000000 | N62: =-45250*1000000 -> -45250000000 | O62: 0.6 | P62: PT Ciputra Internasional | Q62: 2 | R62: 4 | S62: 3 | T62: 7 | U62: 0 | V62: =4+(2*1)+(2*3) -> 12 | W62: =V62 -> 12 | X62: =3+(2*2) -> 7
D63: 2020 | E63: =24303*1000000 -> 24303000000 | F63: =(68459-1680-9470)*1000000 -> 57309000000 | G63: =278255*1000000 -> 278255000000 | H63: =14810*1000000 -> 14810000000 | I63: =138272*1000000 -> 138272000000 | J63: =-172440*1000000 -> -172440000000 | K63: =139982*1000000 -> 139982000000 | L63: =110130*1000000 -> 110130000000 | M63: =-52425*1000000 -> -52425000000 | N63: =-36955*1000000 -> -36955000000 | O63: 0.6 | P63: PT Ciputra Internasional | Q63: 2 | R63: 4 | S63: 3 | T63: 7 | U63: 0 | V63: =4+(2*1)+(2*3) -> 12 | W63: =V63 -> 12 | X63: =3+(2*2) -> 7
D64: 2021 | E64: =33236*1000000 -> 33236000000 | F64: =(111713-2859-7544)*1000000 -> 101310000000 | G64: =384372*1000000 -> 384372000000 | H64: =33110*1000000 -> 33110000000 | I64: =252304*1000000 -> 252304000000 | J64: =-222576*1000000 -> -222576000000 | K64: =132068*1000000 -> 132068000000 | L64: =244885*1000000 -> 244885000000 | M64: =-50077*1000000 -> -50077000000 | N64: =-52914*1000000 -> -52914000000 | O64: 0.6 | P64: PT Ciputra Internasional | Q64: 2 | R64: 4 | S64: 3 | T64: 7 | U64: 0 | V64: =4+(2*1)+(2*3) -> 12 | W64: =V64 -> 12 | X64: =3+(2*2) -> 7
D65: 2022 | E65: =29813*1000000 -> 29813000000 | F65: =(105275-2276-4916)*1000000 -> 98083000000 | G65: =517439*1000000 -> 517439000000 | H65: =40437*1000000 -> 40437000000 | I65: =359910*1000000 -> 359910000000 | J65: =-217970*1000000 -> -217970000000 | K65: =157529*1000000 -> 157529000000 | L65: =334681*1000000 -> 334681000000 | M65: =4803*1000000 -> 4803000000 | N65: =460*1000000 -> 460000000 | O65: 0.6 | P65: PT Ciputra Internasional | Q65: 2 | R65: 4 | S65: 3 | T65: 7 | U65: 0 | V65: =4+(2*1)+(2*3) -> 12 | W65: =V65 -> 12 | X65: =3+(2*2) -> 7
D66: 2023 | E66: =39592*1000000 -> 39592000000 | F66: =(166451-2872-6699)*1000000 -> 156880000000 | G66: =714057*1000000 -> 714057000000 | H66: =58468*1000000 -> 58468000000 | I66: =548082*1000000 -> 548082000000 | J66: =-204285*1000000 -> -204285000000 | K66: =165975*1000000 -> 165975000000 | L66: =467731*1000000 -> 467731000000 | M66: =14009*1000000 -> 14009000000 | N66: =8447*1000000 -> 8447000000 | O66: 0.6 | P66: PT Ciputra Internasional | Q66: 2 | R66: 4 | S66: 3 | T66: 7 | U66: 0 | V66: =4+(2*1)+(2*3) -> 12 | W66: =V66 -> 12 | X66: =3+(2*2) -> 7
D67: 2024 | E67: =42438*1000000 -> 42438000000 | F67: =(180662-7520-5902)*1000000 -> 167240000000 | G67: =997332*1000000 -> 997332000000 | H67: =70006*1000000 -> 70006000000 | I67: =796246*1000000 -> 796246000000 | J67: =-164910*1000000 -> -164910000000 | K67: =201086*1000000 -> 201086000000 | L67: =587025*1000000 -> 587025000000 | M67: =39668*1000000 -> 39668000000 | N67: =35110*1000000 -> 35110000000 | O67: 0.6 | P67: PT Ciputra Internasional | Q67: 2 | R67: 3 | S67: 3 | T67: 6 | U67: 0 | V67: =3+(2*2) -> 7 | W67: =3+(2*2) -> 7 | X67: =3+(2*2) -> 7
B68: 7 | C68: PT Asuransi Jiwa Astra | D68: 2014 | E68: 0 | F68: 0 | G68: 0 | H68: 0 | I68: 0 | J68: 0 | K68: 0 | L68: =613328*1000000 -> 613328000000 | M68: 0 | N68: 0 | O68: 0 | P68: 0 | Q68: 0 | R68: 0 | T68: 0 | U68: 0 | V68: 0 | W68: =V68 -> 0 | X68: 0
D69: 2015 | E69: =187589*1000000 -> 187589000000 | F69: =(642650-318280-75938)*1000000 -> 248432000000 | G69: =1899837*1000000 -> 1899837000000 | H69: =323188*1000000 -> 323188000000 | I69: =1364281*1000000 -> 1364281000000 | J69: =-325409*1000000 -> -325409000000 | K69: =535556*1000000 -> 535556000000 | L69: =1310956*1000000 -> 1310956000000 | M69: =-178757*1000000 -> -178757000000 | N69: =-177698*1000000 -> -177698000000 | O69: 0.5 | P69: Aviva International Holding dan PT Astra International | Q69: 2 | R69: 4 | S69: 6 | T69: =R69+S69 -> 10 | U69: 0 | V69: 0 | W69: =V69 -> 0 | X69: 0
D70: 2016 | E70: =584373*1000000 -> 584373000000 | F70: =(1007870-285037-68295)*1000000 -> 654538000000 | G70: =3802688*1000000 -> 3802688000000 | H70: =406803*1000000 -> 406803000000 | I70: =2965233*1000000 -> 2965233000000 | J70: =-601347*1000000 -> -601347000000 | K70: =837455*1000000 -> 837455000000 | L70: =2981581*1000000 -> 2981581000000 | M70: =-270279*1000000 -> -270279000000 | N70: =-268101*1000000 -> -268101000000 | O70: 0.5 | P70: Aviva International Holding dan PT Astra International | Q70: 2 | R70: 4 | S70: 5 | T70: =R70+S70 -> 9 | U70: 0 | V70: 0 | W70: =V70 -> 0 | X70: 0
D71: 2017 | E71: =589034*1000000 -> 589034000000 | F71: =(992884-256361-51436)*1000000 -> 685087000000 | G71: =4315435*1000000 -> 4315435000000 | H71: =364804*1000000 -> 364804000000 | I71: =3703552*1000000 -> 3703552000000 | J71: =-829401*1000000 -> -829401000000 | K71: =611883*1000000 -> 611883000000 | L71: =3796659*1000000 -> 3796659000000 | M71: =-238633*1000000 -> -238633000000 | N71: =-255572*1000000 -> -255572000000 | O71: 0.5 | P71: Aviva International Holding dan PT Astra International | Q71: 2 | R71: 4 | S71: 4 | T71: =R71+S71 -> 8 | U71: 0 | V71: 0 | W71: =V71 -> 0 | X71: 0
D72: 2018 | E72: =805555*1000000 -> 805555000000 | F72: =(1257516-247254-53193)*1000000 -> 957069000000 | G72: =5004717*1000000 -> 5004717000000 | H72: =381609*1000000 -> 381609000000 | I72: =4569886*1000000 -> 4569886000000 | J72: =-996164*1000000 -> -996164000000 | K72: =434830*1000000 -> 434830000000 | L72: =3611633*1000000 -> 3611633000000 | M72: =-171898*1000000 -> -171898000000 | N72: =-177053*1000000 -> -177053000000 | O72: 0.5 | P72: Aviva International Holding dan PT Astra International | Q72: 2 | R72: 4 | S72: 4 | T72: =R72+S72 -> 8 | U72: 0 | V72: 0 | W72: =V72 -> 0 | X72: 0
D73: 2019 | E73: =601357*1000000 -> 601357000000 | F73: =(1112969-247719-48991)*1000000 -> 816259000000 | G73: =5901298*1000000 -> 5901298000000 | H73: =397846*1000000 -> 397846000000 | I73: =5043700*1000000 -> 5043700000000 | J73: =-1078931*1000000 -> -1078931000000 | K73: =857598*1000000 -> 857598000000 | L73: =3346426*1000000 -> 3346426000000 | M73: =-85388*1000000 -> -85388000000 | N73: =-77232*1000000 -> -77232000000 | O73: 0.5 | P73: Aviva International Holding dan PT Astra International | Q73: 2 | R73: 4 | S73: 6 | T73: =R73+S73 -> 10 | U73: 0 | V73: 0 | W73: =V73 -> 0 | X73: 0
D74: 2020 | E74: =588417*1000000 -> 588417000000 | F74: =(1141065-309351-44975)*1000000 -> 786739000000 | G74: =6587066*1000000 -> 6587066000000 | H74: =582749*1000000 -> 582749000000 | I74: =5746720*1000000 -> 5746720000000 | J74: =-1110095*1000000 -> -1110095000000 | K74: =840112*1000000 -> 840112000000 | L74: =3645793*1000000 -> 3645793000000 | M74: =-32278*1000000 -> -32278000000 | N74: =-16497*1000000 -> -16497000000 | O74: 0.4999 | P74: PT Astra International dan PT Sedaya Multi Investama | Q74: 2 | R74: 4 | S74: 4 | T74: =R74+S74 -> 8 | U74: 0 | V74: 0 | W74: =V74 -> 0 | X74: 0
D75: 2021 | E75: =453748*1000000 -> 453748000000 | F75: =(1047115-242581-28401)*1000000 -> 776133000000 | G75: =7092935*1000000 -> 7092935000000 | H75: =386504*1000000 -> 386504000000 | I75: =6266517*1000000 -> 6266517000000 | J75: =-1112228*1000000 -> -1112228000000 | K75: =826251*1000000 -> 826251000000 | L75: =5769733*1000000 -> 5769733000000 | M75: =-20542*1000000 -> -20542000000 | N75: =-13860*1000000 -> -13860000000 | O75: 0.4999 | P75: PT Astra International dan PT Sedaya Multi Investama | Q75: 2 | R75: 4 | S75: 4 | T75: =R75+S75 -> 8 | U75: 0 | V75: 0 | W75: =V75 -> 0 | X75: 0
D76: 2022 | E76: =554809*1000000 -> 554809000000 | F76: =(1303496-390829-23546)*1000000 -> 889121000000 | G76: =7345755*1000000 -> 7345755000000 | H76: =673005*1000000 -> 673005000000 | I76: =6661879*1000000 -> 6661879000000 | J76: =-1245204*1000000 -> -1245204000000 | K76: =683137*1000000 -> 683137000000 | L76: =5918222*1000000 -> 5918222000000 | M76: =-132881*1000000 -> -132881000000 | N76: =-143113*1000000 -> -143113000000 | O76: 0.4999 | P76: PT Astra International dan PT Sedaya Multi Investama | Q76: 2 | R76: 4 | S76: 5 | T76: =R76+S76 -> 9 | U76: 0 | V76: =4+(2*2)+(2*1) -> 10 | W76: =V76 -> 10 | X76: =5+(2*2)+(2*1) -> 11
D77: 2023 | E77: =347200*1000000 -> 347200000000 | F77: =(1180449-520755-17148)*1000000 -> 642546000000 | G77: =7501061*1000000 -> 7501061000000 | H77: =840770*1000000 -> 840770000000 | I77: =6800327*1000000 -> 6800327000000 | J77: =-1230033*1000000 -> -1230033000000 | K77: =699090*1000000 -> 699090000000 | L77: =6350888*1000000 -> 6350888000000 | M77: =1174*1000000 -> 1174000000 | N77: =15952*1000000 -> 15952000000 | O77: 0.4999 | P77: PT Astra International dan PT Sedaya Multi Investama | Q77: 2 | R77: 4 | S77: 5 | T77: =R77+S77 -> 9 | U77: 0 | V77: 0 | W77: =V77 -> 0 | X77: 0
D78: 2024 | E78: =295483*1000000 -> 295483000000 | F78: =(744665-158615-20046)*1000000 -> 566004000000 | G78: =6806055*1000000 -> 6806055000000 | H78: =701500*1000000 -> 701500000000 | I78: =6056599*1000000 -> 6056599000000 | J78: =-1167798*1000000 -> -1167798000000 | K78: =748206*1000000 -> 748206000000 | L78: =5855479*1000000 -> 5855479000000 | M78: =61283*1000000 -> 61283000000 | N78: =49115*1000000 -> 49115000000 | O78: 0.4999 | P78: PT Astra International dan PT Sedaya Multi Investama | Q78: 2 | R78: 4 | S78: 5 | T78: =R78+S78 -> 9 | U78: 0 | V78: 0 | W78: =V78 -> 0 | X78: 0
B79: 8 | C79: PT Asuransi Jiwa BCA | D79: 2014 | E79: 0 | F79: 0 | G79: 0 | H79: 0 | I79: 0 | J79: 0 | K79: 0 | L79: =17340*1000000 -> 17340000000 | M79: 0 | N79: 0 | O79: 0 | P79: 0 | Q79: 0 | R79: 0 | T79: 0 | U79: 0 | V79: 0 | W79: 0 | X79: 0
D80: 2015 | E80: =10832*1000000 -> 10832000000 | F80: =(78282-43592-7624-8516)*1000000 -> 18550000000 | G80: =281282*1000000 -> 281282000000 | H80: =15519*1000000 -> 15519000000 | I80: =52698*1000000 -> 52698000000 | J80: =-31416*1000000 -> -31416000000 | K80: =228584*1000000 -> 228584000000 | L80: =108628*1000000 -> 108628000000 | M80: =-41004*1000000 -> -41004000000 | N80: =-27031*1000000 -> -27031000000 | O80: 0.9999 | P80: PT BCA Sekuritas | Q80: 2 | R80: 4 | T80: 8 | U80: 0 | V80: 0 | W80: 0 | X80: 0
D81: 2016 | E81: =9355*1000000 -> 9355000000 | F81: =(121639-59065-5251-7727)*1000000 -> 49596000000 | G81: =385447*1000000 -> 385447000000 | H81: =44397*1000000 -> 44397000000 | I81: =181020*1000000 -> 181020000000 | J81: =-54891*1000000 -> -54891000000 | K81: =204426*1000000 -> 204426000000 | L81: =289387*1000000 -> 289387000000 | M81: =-37138*1000000 -> -37138000000 | N81: =-24158*1000000 -> -24158000000 | O81: 0.9999 | P81: PT BCA Sekuritas | Q81: 1 | R81: 3 | T81: 7 | U81: 0 | V81: 0 | W81: 0 | X81: 0
D82: 2017 | E82: =9023*1000000 -> 9023000000 | F82: =(151743-57503-8093)*1000000 -> 86147000000 | G82: =842122*1000000 -> 842122000000 | H82: =96254*1000000 -> 96254000000 | I82: =375260*1000000 -> 375260000000 | J82: =-98219*1000000 -> -98219000000 | K82: =466862*1000000 -> 466862000000 | L82: =445563*1000000 -> 445563000000 | M82: =-58814*1000000 -> -58814000000 | N82: =-37565*1000000 -> -37565000000 | O82: 0.9 | P82: PT BCA Sekuritas | Q82: 0 | R82: 4 | T82: 7 | U82: 0 | V82: 0 | W82: 0 | X82: 0
D83: 2018 | E83: =2165*1000000 -> 2165000000 | F83: =(80317-20217-3466)*1000000 -> 56634000000 | G83: =902876*1000000 -> 902876000000 | H83: =62173*1000000 -> 62173000000 | I83: =514818*1000000 -> 514818000000 | J83: =-166505*1000000 -> -166505000000 | K83: =388058*1000000 -> 388058000000 | L83: =585605*1000000 -> 585605000000 | M83: =-25377*1000000 -> -25377000000 | N83: =-78803*1000000 -> -78803000000 | O83: 0.9 | P83: PT BCA Sekuritas | Q83: 0 | R83: 4 | T83: 7 | U83: 0 | V83: 0 | W83: 0 | X83: 0
D84: 2019 | E84: =5650*1000000 -> 5650000000 | F84: =(111186-18737-6693)*1000000 -> 85756000000 | G84: =1154689*1000000 -> 1154689000000 | H84: =76452*1000000 -> 76452000000 | I84: =753776*1000000 -> 753776000000 | J84: =-169045*1000000 -> -169045000000 | K84: =400913*1000000 -> 400913000000 | L84: =800269*1000000 -> 800269000000 | M84: =-3158*1000000 -> -3158000000 | N84: =12855*1000000 -> 12855000000 | O84: 0.9 | P84: PT BCA Sekuritas | Q84: 0 | R84: 4 | T84: 7 | U84: 0 | V84: 0 | W84: 0 | X84: 0
D85: 2020 | E85: =13881*1000000 -> 13881000000 | F85: =(179911-36903-8086)*1000000 -> 134922000000 | G85: =1467896*1000000 -> 1467896000000 | H85: =89869*1000000 -> 89869000000 | I85: =975453*1000000 -> 975453000000 | J85: =-99137*1000000 -> -99137000000 | K85: =492443*1000000 -> 492443000000 | L85: =991129*1000000 -> 991129000000 | M85: =69848*1000000 -> 69848000000 | N85: =91530*1000000 -> 91530000000 | O85: 0.9 | P85: PT BCA Sekuritas | Q85: 0 | R85: 4 | T85: 8 | U85: 0 | V85: 0 | W85: 0 | X85: 0
D86: 2021 | E86: =2873*1000000 -> 2873000000 | F86: =(408826-70546-18011)*1000000 -> 320269000000 | G86: =1930213*1000000 -> 1930213000000 | H86: =84761*1000000 -> 84761000000 | I86: =1397617*1000000 -> 1397617000000 | J86: =-61258*1000000 -> -61258000000 | K86: =532596*1000000 -> 532596000000 | L86: =1316137*1000000 -> 1316137000000 | M86: =17594*1000000 -> 17594000000 | N86: =40152*1000000 -> 40152000000 | O86: 0.9 | P86: PT BCA Sekuritas | Q86: 2 | R86: 4 | T86: 9 | U86: 0 | V86: 0 | W86: 0 | X86: 0
D87: 2022 | E87: =7230*1000000 -> 7230000000 | F87: =(306869-63245-15644)*1000000 -> 227980000000 | G87: =2347921*1000000 -> 2347921000000 | H87: =117537*1000000 -> 117537000000 | I87: =1688561*1000000 -> 1688561000000 | J87: =-2661*1000000 -> -2661000000 | K87: =659360*1000000 -> 659360000000 | L87: =1382687*1000000 -> 1382687000000 | M87: =54204*1000000 -> 54204000000 | N87: =51764*1000000 -> 51764000000 | O87: 0.9 | P87: PT BCA Sekuritas | Q87: 2 | R87: 4 | T87: 8 | U87: 0 | V87: 0 | W87: 0 | X87: 0
D88: 2023 | E88: =3676*1000000 -> 3676000000 | F88: =(352759-93495-15477)*1000000 -> 243787000000 | G88: =2878724*1000000 -> 2878724000000 | H88: =132809*1000000 -> 132809000000 | I88: =2148138*1000000 -> 2148138000000 | J88: =76793*1000000 -> 76793000000 | K88: =730586*1000000 -> 730586000000 | L88: =1576409*1000000 -> 1576409000000 | M88: =69991*1000000 -> 69991000000 | N88: =71227*1000000 -> 71227000000 | O88: 0.9 | P88: PT BCA Sekuritas | Q88: 2 | R88: 4 | T88: 8 | U88: 0 | V88: 0 | W88: 0 | X88: 0
D89: 2024 | E89: =2728*1000000 -> 2728000000 | F89: =(334411-92892-15578)*1000000 -> 225941000000 | G89: =3339666*1000000 -> 3339666000000 | H89: =97813*1000000 -> 97813000000 | I89: =2525508*1000000 -> 2525508000000 | J89: =170342*1000000 -> 170342000000 | K89: =814158*1000000 -> 814158000000 | L89: =1481484*1000000 -> 1481484000000 | M89: =90398*1000000 -> 90398000000 | N89: =83571*1000000 -> 83571000000 | O89: 0.9 | P89: PT BCA Sekuritas | Q89: 2 | R89: 4 | T89: 8 | U89: 0 | V89: 0 | W89: 0 | X89: 0
B90: 9 | C90: PT Asuransi Jiwa Central Asia Raya | D90: 2014 | E90: 0 | F90: 0 | G90: 0 | H90: 0 | I90: 0 | J90: 0 | K90: 0 | L90: =1111447*1000000 -> 1111447000000 | M90: 0 | N90: 0 | O90: 0 | P90: 0 | Q90: 0 | R90: 0 | T90: 0 | U90: 0 | W90: =V90 -> 0
D91: 2015 | E91: =9150*1000000 -> 9150000000 | F91: =176774*1000000 -> 176774000000 | G91: =4598462*1000000 -> 4598462000000 | H91: =(10450+15847+2039+33708)*1000000 -> 62044000000 | I91: =2852326*1000000 -> 2852326000000 | J91: =664287*1000000 -> 664287000000 | K91: =1729967*1000000 -> 1729967000000 | L91: =1157281*1000000 -> 1157281000000 | M91: =50463*1000000 -> 50463000000 | N91: =-187450*1000000 -> -187450000000 | O91: 0.9999 | P91: PT Asuransi Central Asia | Q91: 2 | R91: 4 | T91: 6 | U91: =0.00001 -> 1e-05 | V91: 0 | W91: 0 | X91: 0
D92: 2016 | E92: =99955*1000000 -> 99955000000 | F92: =(9995+31616+27408+25381+14880+14880+21185)*1000000 -> 145345000000 | G92: =5298273*1000000 -> 5298273000000 | H92: =374125*1000000 -> 374125000000 | I92: =3397124*1000000 -> 3397124000000 | J92: =853948*1000000 -> 853948000000 | K92: =1901149*1000000 -> 1901149000000 | L92: =1932573*1000000 -> 1932573000000 | M92: =222436*1000000 -> 222436000000 | N92: =201331*1000000 -> 201331000000 | O92: 0.99 | P92: PT Asuransi Central Asia | Q92: 2 | R92: 4 | T92: 7 | U92: =0.00001 -> 1e-05 | V92: 0 | W92: 0 | X92: 0
D93: 2017 | E93: =19011*1000000 -> 19011000000 | F93: =(19011+46933+31668+22628+7034+24585)*1000000 -> 151859000000 | G93: =5618666*1000000 -> 5618666000000 | H93: =403817*1000000 -> 403817000000 | I93: =4348556*1000000 -> 4348556000000 | J93: =1098328*1000000 -> 1098328000000 | K93: =1270110*1000000 -> 1270110000000 | L93: =2584123*1000000 -> 2584123000000 | M93: =285079*1000000 -> 285079000000 | N93: =-590339*1000000 -> -590339000000 | O93: 0.99 | P93: PT Asuransi Central Asia | Q93: 2 | R93: 4 | T93: 7 | U93: =0.00001 -> 1e-05 | V93: 0 | W93: 0 | X93: 0
D94: 2018 | E94: =14894*1000000 -> 14894000000 | F94: =(14894+33021+30709+25017+7034+27263)*1000000 -> 137938000000 | G94: =6696353*1000000 -> 6696353000000 | H94: =446855*1000000 -> 446855000000 | I94: =5300406*1000000 -> 5300406000000 | J94: =1164789*1000000 -> 1164789000000 | K94: =6696353*1000000 -> 6696353000000 | L94: =2626306*1000000 -> 2626306000000 | M94: =116022*1000000 -> 116022000000 | N94: =175397*1000000 -> 175397000000 | O94: 0.99 | P94: PT Asuransi Central Asia | Q94: 2 | R94: 4 | T94: 7 | U94: =0.00001 -> 1e-05 | V94: 0 | W94: 0 | X94: 0
D95: 2019 | E95: =13047*1000000 -> 13047000000 | F95: =(13047+22984+33663+26021+7034+27263)*1000000 -> 130012000000 | G95: =8158087*1000000 -> 8158087000000 | H95: =410765*1000000 -> 410765000000 | I95: =6383523*1000000 -> 6383523000000 | J95: =1347007*1000000 -> 1347007000000 | K95: =8158087*1000000 -> 8158087000000 | L95: =3015912*1000000 -> 3015912000000 | M95: =199761*1000000 -> 199761000000 | N95: =396160*1000000 -> 396160000000 | O95: 0.99 | P95: PT Asuransi Central Asia | Q95: 2 | R95: 4 | T95: 8 | U95: =0.00001 -> 1e-05 | V95: 0 | W95: 0 | X95: 0
D96: 2020 | E96: =17657*1000000 -> 17657000000 | F96: =(259309-42948-11604-62924)*1000000 -> 141833000000 | G96: =8569933*1000000 -> 8569933000000 | H96: =418551*1000000 -> 418551000000 | I96: =6749524*1000000 -> 6749524000000 | J96: =1562189*1000000 -> 1562189000000 | K96: =1820409*1000000 -> 1820409000000 | L96: =2727108*1000000 -> 2727108000000 | M96: =239948*1000000 -> 239948000000 | N96: =70612*1000000 -> 70612000000 | O96: 0.99 | P96: PT Asuransi Central Asia | Q96: 2 | R96: 4 | T96: 8 | U96: =0.00001 -> 1e-05 | V96: 0 | W96: 0 | X96: 0
D97: 2021 | E97: =12463*1000000 -> 12463000000 | F97: =(277746-31994-7385-65172)*1000000 -> 173195000000 | G97: =10111397*1000000 -> 10111397000000 | H97: =389107*1000000 -> 389107000000 | I97: =7169272*1000000 -> 7169272000000 | J97: =1710831*1000000 -> 1710831000000 | K97: =2942125*1000000 -> 2942125000000 | L97: =2794098*1000000 -> 2794098000000 | M97: =181449*1000000 -> 181449000000 | N97: =1154523*1000000 -> 1154523000000 | O97: 0.99 | P97: PT Asuransi Central Asia | Q97: 2 | R97: 3 | T97: 6 | U97: =0.00001 -> 1e-05 | V97: 0 | W97: 0 | X97: 0
D98: 2022 | E98: =31388*1000000 -> 31388000000 | F98: =(304682-20532-5619-60331)*1000000 -> 218200000000 | G98: =10357588*1000000 -> 10357588000000 | H98: =384877*1000000 -> 384877000000 | I98: =7279861*1000000 -> 7279861000000 | J98: =1889815*1000000 -> 1889815000000 | K98: =3077726*1000000 -> 3077726000000 | L98: =2587182*1000000 -> 2587182000000 | M98: =202189*1000000 -> 202189000000 | N98: =158806*1000000 -> 158806000000 | O98: 0.99 | P98: PT Asuransi Central Asia | Q98: 2 | R98: 3 | T98: 7 | U98: =0.00001 -> 1e-05 | V98: 0 | W98: 0 | X98: 0
D99: 2023 | E99: =14432*1000000 -> 14432000000 | F99: =(418686-22136-4442-55442)*1000000 -> 336666000000 | G99: =11033985*1000000 -> 11033985000000 | H99: =515004*1000000 -> 515004000000 | I99: =7874976*1000000 -> 7874976000000 | J99: =2067551*1000000 -> 2067551000000 | K99: =3159009*1000000 -> 3159009000000 | L99: =2996848*1000000 -> 2996848000000 | M99: =204143*1000000 -> 204143000000 | N99: =107690*1000000 -> 107690000000 | O99: 0.99 | P99: PT Asuransi Central Asia | Q99: 2 | R99: 3 | T99: 6 | U99: =0.00001 -> 1e-05 | V99: 0 | W99: 0 | X99: 0
D100: 2024 | E100: =65375*1000000 -> 65375000000 | F100: =(571434-31716-13827-56899)*1000000 -> 468992000000 | G100: =11181540*1000000 -> 11181540000000 | H100: =403540*1000000 -> 403540000000 | I100: =7771730*1000000 -> 7771730000000 | J100: =2276380*1000000 -> 2276380000000 | K100: =3409810*1000000 -> 3409810000000 | L100: =2435099*1000000 -> 2435099000000 | M100: =235293*1000000 -> 235293000000 | N100: =277265*1000000 -> 277265000000 | O100: 0.99 | P100: PT Asuransi Central Asia | Q100: 2 | R100: 3 | T100: 7 | U100: =0.00001 -> 1e-05 | V100: 0 | W100: 0 | X100: 0
...

Sheet Current Ratio
A1: Sub Sektor | B1: No | C1: Nama Perusahaan | D1: Tahun | E1: Aktiva Lancar | F1: Hutang Lancar | G1: Current Ratio
A2: Asuransi Jiwa | B2: 1 | C2: Asuransi Jiwa Bersama Bumiputera 1912 | D2: 2014 | E2: =Data!F2 -> 0 | F2: =Data!H2 -> 0 | G2: =IFERROR(E2/F2,0) -> 0
D3: 2015 | E3: =Data!F3 -> 0 | F3: =Data!H3 -> 0 | G3: =IFERROR(E3/F3,0) -> 0
D4: 2016 | E4: =Data!F4 -> 0 | F4: =Data!H4 -> 0 | G4: =IFERROR(E4/F4,0) -> 0
D5: 2017 | E5: =Data!F5 -> 0 | F5: =Data!H5 -> 0 | G5: =IFERROR(E5/F5,0) -> 0
D6: 2018 | E6: =Data!F6 -> 0 | F6: =Data!H6 -> 0 | G6: =IFERROR(E6/F6,0) -> 0
D7: 2019 | E7: =Data!F7 -> 0 | F7: =Data!H7 -> 0 | G7: =IFERROR(E7/F7,0) -> 0
D8: 2020 | E8: =Data!F8 -> 0 | F8: =Data!H8 -> 0 | G8: =IFERROR(E8/F8,0) -> 0
D9: 2021 | E9: =Data!F9 -> 0 | F9: =Data!H9 -> 0 | G9: =IFERROR(E9/F9,0) -> 0
D10: 2022 | E10: =Data!F10 -> 0 | F10: =Data!H10 -> 0 | G10: =IFERROR(E10/F10,0) -> 0
D11: 2023 | E11: =Data!F11 -> 0 | F11: =Data!H11 -> 0 | G11: =IFERROR(E11/F11,0) -> 0
D12: 2024 | E12: =Data!F12 -> 0 | F12: =Data!H12 -> 0 | G12: =IFERROR(E12/F12,0) -> 0
B13: 2 | C13: PT AIA Financial | D13: 2014 | E13: =Data!F13 -> 0 | F13: =Data!H13 -> 0 | G13: =IFERROR(E13/F13,0) -> 0
D14: 2015 | E14: =Data!F14 -> 951139000000 | F14: =Data!H14 -> 1833519000000 | G14: =IFERROR(E14/F14,0) -> 0.51875056
D15: 2016 | E15: =Data!F15 -> 1118793000000 | F15: =Data!H15 -> 2103474000000 | G15: =IFERROR(E15/F15,0) -> 0.53187869
D16: 2017 | E16: =Data!F16 -> 1287320000000 | F16: =Data!H16 -> 3116639000000 | G16: =IFERROR(E16/F16,0) -> 0.41304752
D17: 2018 | E17: =Data!F17 -> 1509812000000 | F17: =Data!H17 -> 3329580000000 | G17: =IFERROR(E17/F17,0) -> 0.45345419
D18: 2019 | E18: =Data!F18 -> 2019822000000 | F18: =Data!H18 -> 3399335000000 | G18: =IFERROR(E18/F18,0) -> 0.59418151
D19: 2020 | E19: =Data!F19 -> 2189572000000 | F19: =Data!H19 -> 3640926000000 | G19: =IFERROR(E19/F19,0) -> 0.60137778
D20: 2021 | E20: =Data!F20 -> 2332200000000 | F20: =Data!H20 -> 3465695000000 | G20: =IFERROR(E20/F20,0) -> 0.67293862
D21: 2022 | E21: =Data!F21 -> 2553937000000 | F21: =Data!H21 -> 3771309000000 | G21: =IFERROR(E21/F21,0) -> 0.67720174
D22: 2023 | E22: =Data!F22 -> 2217504000000 | F22: =Data!H22 -> 3324784000000 | G22: =IFERROR(E22/F22,0) -> 0.66696182
D23: 2024 | E23: =Data!F23 -> 2234181000000 | F23: =Data!H23 -> 2965577000000 | G23: =IFERROR(E23/F23,0) -> 0.75337143
B24: 3 | C24: PT Asuransi Allianz Life Indonesia | D24: 2014 | E24: =Data!F24 -> 0 | F24: =Data!H24 -> 0 | G24: =IFERROR(E24/F24,0) -> 0
D25: 2015 | E25: =Data!F25 -> 688635000000 | F25: =Data!H25 -> 665956000000 | G25: =IFERROR(E25/F25,0) -> 1.0340548
D26: 2016 | E26: =Data!F26 -> 937483000000 | F26: =Data!H26 -> 953567000000 | G26: =IFERROR(E26/F26,0) -> 0.98313281
D27: 2017 | E27: =Data!F27 -> 1162598000000 | F27: =Data!H27 -> 1244651000000 | G27: =IFERROR(E27/F27,0) -> 0.9340755
D28: 2018 | E28: =Data!F28 -> 1438688000000 | F28: =Data!H28 -> 1580256000000 | G28: =IFERROR(E28/F28,0) -> 0.91041452
D29: 2019 | E29: =Data!F29 -> 1975159000000 | F29: =Data!H29 -> 1291778000000 | G29: =IFERROR(E29/F29,0) -> 1.5290236
D30: 2020 | E30: =Data!F30 -> 2544663000000 | F30: =Data!H30 -> 1443225000000 | G30: =IFERROR(E30/F30,0) -> 1.7631783
D31: 2021 | E31: =Data!F31 -> 2851127000000 | F31: =Data!H31 -> 1539961000000 | G31: =IFERROR(E31/F31,0) -> 1.8514281
D32: 2022 | E32: =Data!F32 -> 3412009000000 | F32: =Data!H32 -> 2321280000000 | G32: =IFERROR(E32/F32,0) -> 1.4698826
D33: 2023 | E33: =Data!F33 -> 3559943000000 | F33: =Data!H33 -> 2581811000000 | G33: =IFERROR(E33/F33,0) -> 1.378855
D34: 2024 | E34: =Data!F34 -> 2585453000000 | F34: =Data!H34 -> 2735029000000 | G34: =IFERROR(E34/F34,0) -> 0.945311
B35: 4 | C35: PT Asuransi Allianz Life Syariah Indonesia | D35: 2014 | E35: =Data!F35 -> 0 | F35: =Data!H35 -> 0 | G35: =IFERROR(E35/F35,0) -> 0
D36: 2015 | E36: =Data!F36 -> 0 | F36: =Data!H36 -> 0 | G36: =IFERROR(E36/F36,0) -> 0
D37: 2016 | E37: =Data!F37 -> 0 | F37: =Data!H37 -> 0 | G37: =IFERROR(E37/F37,0) -> 0
D38: 2017 | E38: =Data!F38 -> 0 | F38: =Data!H38 -> 0 | G38: =IFERROR(E38/F38,0) -> 0
D39: 2018 | E39: =Data!F39 -> 0 | F39: =Data!H39 -> 0 | G39: =IFERROR(E39/F39,0) -> 0
D40: 2019 | E40: =Data!F40 -> 0 | F40: =Data!H40 -> 0 | G40: =IFERROR(E40/F40,0) -> 0
D41: 2020 | E41: =Data!F41 -> 0 | F41: =Data!H41 -> 0 | G41: =IFERROR(E41/F41,0) -> 0
D42: 2021 | E42: =Data!F42 -> 0 | F42: =Data!H42 -> 0 | G42: =IFERROR(E42/F42,0) -> 0
D43: 2022 | E43: =Data!F43 -> 410708000000 | F43: =Data!H43 -> 516180000000 | G43: =IFERROR(E43/F43,0) -> 0.79566818
D44: 2023 | E44: =Data!F44 -> 612489000000 | F44: =Data!H44 -> 432783000000 | G44: =IFERROR(E44/F44,0) -> 1.4152335
D45: 2024 | E45: =Data!F45 -> 292352000000 | F45: =Data!H45 -> 370778000000 | G45: =IFERROR(E45/F45,0) -> 0.7884826
B46: 5 | C46: PT Asuransi BRI Life | D46: 2014 | E46: =Data!F46 -> 0 | F46: =Data!H46 -> 0 | G46: =IFERROR(E46/F46,0) -> 0
D47: 2015 | E47: =Data!F47 -> 468361790000 | F47: =Data!H47 -> 212592184000 | G47: =IFERROR(E47/F47,0) -> 2.2030998
D48: 2016 | E48: =Data!F48 -> 391460041000 | F48: =Data!H48 -> 132766311000 | G48: =IFERROR(E48/F48,0) -> 2.9484893
D49: 2017 | E49: =Data!F49 -> 483705909000 | F49: =Data!H49 -> 170181075000 | G49: =IFERROR(E49/F49,0) -> 2.8423014
D50: 2018 | E50: =Data!F50 -> 564045684000 | F50: =Data!H50 -> 362779204000 | G50: =IFERROR(E50/F50,0) -> 1.5547906
D51: 2019 | E51: =Data!F51 -> 506706000000 | F51: =Data!H51 -> 322081000000 | G51: =IFERROR(E51/F51,0) -> 1.5732254
D52: 2020 | E52: =Data!F52 -> 723140000000 | F52: =Data!H52 -> 255342000000 | G52: =IFERROR(E52/F52,0) -> 2.8320449
D53: 2021 | E53: =Data!F53 -> 848461000000 | F53: =Data!H53 -> 946159000000 | G53: =IFERROR(E53/F53,0) -> 0.89674251
D54: 2022 | E54: =Data!F54 -> 1239866000000 | F54: =Data!H54 -> 577879000000 | G54: =IFERROR(E54/F54,0) -> 2.145546
D55: 2023 | E55: =Data!F55 -> 831272000000 | F55: =Data!H55 -> 318534000000 | G55: =IFERROR(E55/F55,0) -> 2.6096806
D56: 2024 | E56: =Data!F56 -> 0 | F56: =Data!H56 -> 0 | G56: =IFERROR(E56/F56,0) -> 0
B57: 6 | C57: PT Asuransi Ciputra Indonesia | D57: 2014 | E57: =Data!F57 -> 0 | F57: =Data!H57 -> 0 | G57: =IFERROR(E57/F57,0) -> 0
D58: 2015 | E58: =Data!F58 -> 0 | F58: =Data!H58 -> 0 | G58: =IFERROR(E58/F58,0) -> 0
D59: 2016 | E59: =Data!F59 -> 7116000000 | F59: =Data!H59 -> 3417000000 | G59: =IFERROR(E59/F59,0) -> 2.0825285
D60: 2017 | E60: =Data!F60 -> 8200000000 | F60: =Data!H60 -> 7335000000 | G60: =IFERROR(E60/F60,0) -> 1.1179277
D61: 2018 | E61: =Data!F61 -> 22553000000 | F61: =Data!H61 -> 15989000000 | G61: =IFERROR(E61/F61,0) -> 1.4105322
D62: 2019 | E62: =Data!F62 -> 34270000000 | F62: =Data!H62 -> 14816000000 | G62: =IFERROR(E62/F62,0) -> 2.31304
D63: 2020 | E63: =Data!F63 -> 57309000000 | F63: =Data!H63 -> 14810000000 | G63: =IFERROR(E63/F63,0) -> 3.8696151
D64: 2021 | E64: =Data!F64 -> 101310000000 | F64: =Data!H64 -> 33110000000 | G64: =IFERROR(E64/F64,0) -> 3.0598007
D65: 2022 | E65: =Data!F65 -> 98083000000 | F65: =Data!H65 -> 40437000000 | G65: =IFERROR(E65/F65,0) -> 2.4255756
D66: 2023 | E66: =Data!F66 -> 156880000000 | F66: =Data!H66 -> 58468000000 | G66: =IFERROR(E66/F66,0) -> 2.6831771
D67: 2024 | E67: =Data!F67 -> 167240000000 | F67: =Data!H67 -> 70006000000 | G67: =IFERROR(E67/F67,0) -> 2.3889381
B68: 7 | C68: PT Asuransi Jiwa Astra | D68: 2014 | E68: =Data!F68 -> 0 | F68: =Data!H68 -> 0 | G68: =IFERROR(E68/F68,0) -> 0
D69: 2015 | E69: =Data!F69 -> 248432000000 | F69: =Data!H69 -> 323188000000 | G69: =IFERROR(E69/F69,0) -> 0.76869191
D70: 2016 | E70: =Data!F70 -> 654538000000 | F70: =Data!H70 -> 406803000000 | G70: =IFERROR(E70/F70,0) -> 1.6089803
D71: 2017 | E71: =Data!F71 -> 685087000000 | F71: =Data!H71 -> 364804000000 | G71: =IFERROR(E71/F71,0) -> 1.8779591
D72: 2018 | E72: =Data!F72 -> 957069000000 | F72: =Data!H72 -> 381609000000 | G72: =IFERROR(E72/F72,0) -> 2.5079833
D73: 2019 | E73: =Data!F73 -> 816259000000 | F73: =Data!H73 -> 397846000000 | G73: =IFERROR(E73/F73,0) -> 2.0516959
D74: 2020 | E74: =Data!F74 -> 786739000000 | F74: =Data!H74 -> 582749000000 | G74: =IFERROR(E74/F74,0) -> 1.3500478
D75: 2021 | E75: =Data!F75 -> 776133000000 | F75: =Data!H75 -> 386504000000 | G75: =IFERROR(E75/F75,0) -> 2.0080853
D76: 2022 | E76: =Data!F76 -> 889121000000 | F76: =Data!H76 -> 673005000000 | G76: =IFERROR(E76/F76,0) -> 1.3211209
D77: 2023 | E77: =Data!F77 -> 642546000000 | F77: =Data!H77 -> 840770000000 | G77: =IFERROR(E77/F77,0) -> 0.76423517
D78: 2024 | E78: =Data!F78 -> 566004000000 | F78: =Data!H78 -> 701500000000 | G78: =IFERROR(E78/F78,0) -> 0.80684818
B79: 8 | C79: PT Asuransi Jiwa BCA | D79: 2014 | E79: =Data!F79 -> 0 | F79: =Data!H79 -> 0 | G79: =IFERROR(E79/F79,0) -> 0
D80: 2015 | E80: =Data!F80 -> 18550000000 | F80: =Data!H80 -> 15519000000 | G80: =IFERROR(E80/F80,0) -> 1.195309
D81: 2016 | E81: =Data!F81 -> 49596000000 | F81: =Data!H81 -> 44397000000 | G81: =IFERROR(E81/F81,0) -> 1.1171025
D82: 2017 | E82: =Data!F82 -> 86147000000 | F82: =Data!H82 -> 96254000000 | G82: =IFERROR(E82/F82,0) -> 0.89499657
D83: 2018 | E83: =Data!F83 -> 56634000000 | F83: =Data!H83 -> 62173000000 | G83: =IFERROR(E83/F83,0) -> 0.91090988
D84: 2019 | E84: =Data!F84 -> 85756000000 | F84: =Data!H84 -> 76452000000 | G84: =IFERROR(E84/F84,0) -> 1.1216973
D85: 2020 | E85: =Data!F85 -> 134922000000 | F85: =Data!H85 -> 89869000000 | G85: =IFERROR(E85/F85,0) -> 1.5013186
D86: 2021 | E86: =Data!F86 -> 320269000000 | F86: =Data!H86 -> 84761000000 | G86: =IFERROR(E86/F86,0) -> 3.7784948
D87: 2022 | E87: =Data!F87 -> 227980000000 | F87: =Data!H87 -> 117537000000 | G87: =IFERROR(E87/F87,0) -> 1.9396445
D88: 2023 | E88: =Data!F88 -> 243787000000 | F88: =Data!H88 -> 132809000000 | G88: =IFERROR(E88/F88,0) -> 1.8356211
D89: 2024 | E89: =Data!F89 -> 225941000000 | F89: =Data!H89 -> 97813000000 | G89: =IFERROR(E89/F89,0) -> 2.3099281
B90: 9 | C90: PT Asuransi Jiwa Central Asia Raya | D90: 2014 | E90: =Data!F90 -> 0 | F90: =Data!H90 -> 0 | G90: =IFERROR(E90/F90,0) -> 0
D91: 2015 | E91: =Data!F91 -> 176774000000 | F91: =Data!H91 -> 62044000000 | G91: =IFERROR(E91/F91,0) -> 2.8491716
D92: 2016 | E92: =Data!F92 -> 145345000000 | F92: =Data!H92 -> 374125000000 | G92: =IFERROR(E92/F92,0) -> 0.38849315
D93: 2017 | E93: =Data!F93 -> 151859000000 | F93: =Data!H93 -> 403817000000 | G93: =IFERROR(E93/F93,0) -> 0.37605896
D94: 2018 | E94: =Data!F94 -> 137938000000 | F94: =Data!H94 -> 446855000000 | G94: =IFERROR(E94/F94,0) -> 0.30868626
D95: 2019 | E95: =Data!F95 -> 130012000000 | F95: =Data!H95 -> 410765000000 | G95: =IFERROR(E95/F95,0) -> 0.31651187
D96: 2020 | E96: =Data!F96 -> 141833000000 | F96: =Data!H96 -> 418551000000 | G96: =IFERROR(E96/F96,0) -> 0.33886671
D97: 2021 | E97: =Data!F97 -> 173195000000 | F97: =Data!H97 -> 389107000000 | G97: =IFERROR(E97/F97,0) -> 0.44510893
D98: 2022 | E98: =Data!F98 -> 218200000000 | F98: =Data!H98 -> 384877000000 | G98: =IFERROR(E98/F98,0) -> 0.56693437
D99: 2023 | E99: =Data!F99 -> 336666000000 | F99: =Data!H99 -> 515004000000 | G99: =IFERROR(E99/F99,0) -> 0.65371531
D100: 2024 | E100: =Data!F100 -> 468992000000 | F100: =Data!H100 -> 403540000000 | G100: =IFERROR(E100/F100,0) -> 1.1621946
...

Sheet Cash Ratio
A1: Sub Sektor | B1: No | C1: Nama Perusahaan | D1: Tahun | E1: Kas | F1: Hutang Lancar | G1: Cash Ratio
A2: Asuransi Jiwa | B2: 1 | C2: Asuransi Jiwa Bersama Bumiputera 1912 | D2: 2014 | E2: =Data!E2 -> 0 | F2: =Data!H2 -> 0 | G2: =IFERROR(E2/F2,0) -> 0
D3: 2015 | E3: =Data!E3 -> 0 | F3: =Data!H3 -> 0 | G3: =IFERROR(E3/F3,0) -> 0
D4: 2016 | E4: =Data!E4 -> 0 | F4: =Data!H4 -> 0 | G4: =IFERROR(E4/F4,0) -> 0
D5: 2017 | E5: =Data!E5 -> 0 | F5: =Data!H5 -> 0 | G5: =IFERROR(E5/F5,0) -> 0
D6: 2018 | E6: =Data!E6 -> 0 | F6: =Data!H6 -> 0 | G6: =IFERROR(E6/F6,0) -> 0
D7: 2019 | E7: =Data!E7 -> 0 | F7: =Data!H7 -> 0 | G7: =IFERROR(E7/F7,0) -> 0
D8: 2020 | E8: =Data!E8 -> 0 | F8: =Data!H8 -> 0 | G8: =IFERROR(E8/F8,0) -> 0
D9: 2021 | E9: =Data!E9 -> 0 | F9: =Data!H9 -> 0 | G9: =IFERROR(E9/F9,0) -> 0
D10: 2022 | E10: =Data!E10 -> 0 | F10: =Data!H10 -> 0 | G10: =IFERROR(E10/F10,0) -> 0
D11: 2023 | E11: =Data!E11 -> 0 | F11: =Data!H11 -> 0 | G11: =IFERROR(E11/F11,0) -> 0
D12: 2024 | E12: =Data!E12 -> 0 | F12: =Data!H12 -> 0 | G12: =IFERROR(E12/F12,0) -> 0
B13: 2 | C13: PT AIA Financial | D13: 2014 | E13: =Data!E13 -> 0 | F13: =Data!H13 -> 0 | G13: =IFERROR(E13/F13,0) -> 0
D14: 2015 | E14: =Data!E14 -> 322334000000 | F14: =Data!H14 -> 1833519000000 | G14: =IFERROR(E14/F14,0) -> 0.17580074
D15: 2016 | E15: =Data!E15 -> 383884000000 | F15: =Data!H15 -> 2103474000000 | G15: =IFERROR(E15/F15,0) -> 0.1825
D16: 2017 | E16: =Data!E16 -> 461296000000 | F16: =Data!H16 -> 3116639000000 | G16: =IFERROR(E16/F16,0) -> 0.14801073
D17: 2018 | E17: =Data!E17 -> 718593000000 | F17: =Data!H17 -> 3329580000000 | G17: =IFERROR(E17/F17,0) -> 0.21582091
D18: 2019 | E18: =Data!E18 -> 1028736000000 | F18: =Data!H18 -> 3399335000000 | G18: =IFERROR(E18/F18,0) -> 0.3026286
D19: 2020 | E19: =Data!E19 -> 1275183000000 | F19: =Data!H19 -> 3640926000000 | G19: =IFERROR(E19/F19,0) -> 0.3502359
D20: 2021 | E20: =Data!E20 -> 1225179000000 | F20: =Data!H20 -> 3465695000000 | G20: =IFERROR(E20/F20,0) -> 0.35351611
D21: 2022 | E21: =Data!E21 -> 1379712000000 | F21: =Data!H21 -> 3771309000000 | G21: =IFERROR(E21/F21,0) -> 0.36584433
D22: 2023 | E22: =Data!E22 -> 841975000000 | F22: =Data!H22 -> 3324784000000 | G22: =IFERROR(E22/F22,0) -> 0.25324202
D23: 2024 | E23: =Data!E23 -> 1063869000000 | F23: =Data!H23 -> 2965577000000 | G23: =IFERROR(E23/F23,0) -> 0.35873929
B24: 3 | C24: PT Asuransi Allianz Life Indonesia | D24: 2014 | E24: =Data!E24 -> 0 | F24: =Data!H24 -> 0 | G24: =IFERROR(E24/F24,0) -> 0
D25: 2015 | E25: =Data!E25 -> 459323000000 | F25: =Data!H25 -> 665956000000 | G25: =IFERROR(E25/F25,0) -> 0.68971974
D26: 2016 | E26: =Data!E26 -> 541939000000 | F26: =Data!H26 -> 953567000000 | G26: =IFERROR(E26/F26,0) -> 0.56832818
D27: 2017 | E27: =Data!E27 -> 400675000000 | F27: =Data!H27 -> 1244651000000 | G27: =IFERROR(E27/F27,0) -> 0.32191755
D28: 2018 | E28: =Data!E28 -> 445074000000 | F28: =Data!H28 -> 1580256000000 | G28: =IFERROR(E28/F28,0) -> 0.28164677
D29: 2019 | E29: =Data!E29 -> 593701000000 | F29: =Data!H29 -> 1291778000000 | G29: =IFERROR(E29/F29,0) -> 0.45959987
D30: 2020 | E30: =Data!E30 -> 757656000000 | F30: =Data!H30 -> 1443225000000 | G30: =IFERROR(E30/F30,0) -> 0.52497428
D31: 2021 | E31: =Data!E31 -> 781493000000 | F31: =Data!H31 -> 1539961000000 | G31: =IFERROR(E31/F31,0) -> 0.50747584
D32: 2022 | E32: =Data!E32 -> 917912000000 | F32: =Data!H32 -> 2321280000000 | G32: =IFERROR(E32/F32,0) -> 0.39543355
D33: 2023 | E33: =Data!E33 -> 1253189000000 | F33: =Data!H33 -> 2581811000000 | G33: =IFERROR(E33/F33,0) -> 0.48539146
D34: 2024 | E34: =Data!E34 -> 1400159000000 | F34: =Data!H34 -> 2735029000000 | G34: =IFERROR(E34/F34,0) -> 0.51193571
B35: 4 | C35: PT Asuransi Allianz Life Syariah Indonesia | D35: 2014 | E35: =Data!E35 -> 0 | F35: =Data!H35 -> 0 | G35: =IFERROR(E35/F35,0) -> 0
D36: 2015 | E36: =Data!E36 -> 0 | F36: =Data!H36 -> 0 | G36: =IFERROR(E36/F36,0) -> 0
D37: 2016 | E37: =Data!E37 -> 0 | F37: =Data!H37 -> 0 | G37: =IFERROR(E37/F37,0) -> 0
D38: 2017 | E38: =Data!E38 -> 0 | F38: =Data!H38 -> 0 | G38: =IFERROR(E38/F38,0) -> 0
D39: 2018 | E39: =Data!E39 -> 0 | F39: =Data!H39 -> 0 | G39: =IFERROR(E39/F39,0) -> 0
D40: 2019 | E40: =Data!E40 -> 0 | F40: =Data!H40 -> 0 | G40: =IFERROR(E40/F40,0) -> 0
D41: 2020 | E41: =Data!E41 -> 0 | F41: =Data!H41 -> 0 | G41: =IFERROR(E41/F41,0) -> 0
D42: 2021 | E42: =Data!E42 -> 0 | F42: =Data!H42 -> 0 | G42: =IFERROR(E42/F42,0) -> 0
D43: 2022 | E43: =Data!E43 -> 172936000000 | F43: =Data!H43 -> 516180000000 | G43: =IFERROR(E43/F43,0) -> 0.33503042
D44: 2023 | E44: =Data!E44 -> 206081000000 | F44: =Data!H44 -> 432783000000 | G44: =IFERROR(E44/F44,0) -> 0.47617628
D45: 2024 | E45: =Data!E45 -> 160128000000 | F45: =Data!H45 -> 370778000000 | G45: =IFERROR(E45/F45,0) -> 0.43187028
B46: 5 | C46: PT Asuransi BRI Life | D46: 2014 | E46: =Data!E46 -> 0 | F46: =Data!H46 -> 0 | G46: =IFERROR(E46/F46,0) -> 0
D47: 2015 | E47: =Data!E47 -> 31270004000 | F47: =Data!H47 -> 212592184000 | G47: =IFERROR(E47/F47,0) -> 0.14708915
D48: 2016 | E48: =Data!E48 -> 47737525000 | F48: =Data!H48 -> 132766311000 | G48: =IFERROR(E48/F48,0) -> 0.35956053
D49: 2017 | E49: =Data!E49 -> 51803533000 | F49: =Data!H49 -> 170181075000 | G49: =IFERROR(E49/F49,0) -> 0.30440243
D50: 2018 | E50: =Data!E50 -> 61423379000 | F50: =Data!H50 -> 362779204000 | G50: =IFERROR(E50/F50,0) -> 0.1693134
D51: 2019 | E51: =Data!E51 -> 68265000000 | F51: =Data!H51 -> 322081000000 | G51: =IFERROR(E51/F51,0) -> 0.21194979
D52: 2020 | E52: =Data!E52 -> 95700000000 | F52: =Data!H52 -> 255342000000 | G52: =IFERROR(E52/F52,0) -> 0.37479146
D53: 2021 | E53: =Data!E53 -> 79576000000 | F53: =Data!H53 -> 946159000000 | G53: =IFERROR(E53/F53,0) -> 0.084104257
D54: 2022 | E54: =Data!E54 -> 65266000000 | F54: =Data!H54 -> 577879000000 | G54: =IFERROR(E54/F54,0) -> 0.1129406
D55: 2023 | E55: =Data!E55 -> 66255000000 | F55: =Data!H55 -> 318534000000 | G55: =IFERROR(E55/F55,0) -> 0.20799977
D56: 2024 | E56: =Data!E56 -> 0 | F56: =Data!H56 -> 0 | G56: =IFERROR(E56/F56,0) -> 0
B57: 6 | C57: PT Asuransi Ciputra Indonesia | D57: 2014 | E57: =Data!E57 -> 0 | F57: =Data!H57 -> 0 | G57: =IFERROR(E57/F57,0) -> 0
D58: 2015 | E58: =Data!E58 -> 0 | F58: =Data!H58 -> 0 | G58: =IFERROR(E58/F58,0) -> 0
D59: 2016 | E59: =Data!E59 -> 7117000000 | F59: =Data!H59 -> 3417000000 | G59: =IFERROR(E59/F59,0) -> 2.0828212
D60: 2017 | E60: =Data!E60 -> 5273000000 | F60: =Data!H60 -> 7335000000 | G60: =IFERROR(E60/F60,0) -> 0.71888207
D61: 2018 | E61: =Data!E61 -> 9389000000 | F61: =Data!H61 -> 15989000000 | G61: =IFERROR(E61/F61,0) -> 0.58721621
D62: 2019 | E62: =Data!E62 -> 9265000000 | F62: =Data!H62 -> 14816000000 | G62: =IFERROR(E62/F62,0) -> 0.62533747
D63: 2020 | E63: =Data!E63 -> 24303000000 | F63: =Data!H63 -> 14810000000 | G63: =IFERROR(E63/F63,0) -> 1.6409858
D64: 2021 | E64: =Data!E64 -> 33236000000 | F64: =Data!H64 -> 33110000000 | G64: =IFERROR(E64/F64,0) -> 1.0038055
D65: 2022 | E65: =Data!E65 -> 29813000000 | F65: =Data!H65 -> 40437000000 | G65: =IFERROR(E65/F65,0) -> 0.73727032
D66: 2023 | E66: =Data!E66 -> 39592000000 | F66: =Data!H66 -> 58468000000 | G66: =IFERROR(E66/F66,0) -> 0.67715674
D67: 2024 | E67: =Data!E67 -> 42438000000 | F67: =Data!H67 -> 70006000000 | G67: =IFERROR(E67/F67,0) -> 0.60620518
B68: 7 | C68: PT Asuransi Jiwa Astra | D68: 2014 | E68: =Data!E68 -> 0 | F68: =Data!H68 -> 0 | G68: =IFERROR(E68/F68,0) -> 0
D69: 2015 | E69: =Data!E69 -> 187589000000 | F69: =Data!H69 -> 323188000000 | G69: =IFERROR(E69/F69,0) -> 0.58043306
D70: 2016 | E70: =Data!E70 -> 584373000000 | F70: =Data!H70 -> 406803000000 | G70: =IFERROR(E70/F70,0) -> 1.4365012
D71: 2017 | E71: =Data!E71 -> 589034000000 | F71: =Data!H71 -> 364804000000 | G71: =IFERROR(E71/F71,0) -> 1.6146588
D72: 2018 | E72: =Data!E72 -> 805555000000 | F72: =Data!H72 -> 381609000000 | G72: =IFERROR(E72/F72,0) -> 2.1109434
D73: 2019 | E73: =Data!E73 -> 601357000000 | F73: =Data!H73 -> 397846000000 | G73: =IFERROR(E73/F73,0) -> 1.5115321
D74: 2020 | E74: =Data!E74 -> 588417000000 | F74: =Data!H74 -> 582749000000 | G74: =IFERROR(E74/F74,0) -> 1.0097263
D75: 2021 | E75: =Data!E75 -> 453748000000 | F75: =Data!H75 -> 386504000000 | G75: =IFERROR(E75/F75,0) -> 1.1739801
D76: 2022 | E76: =Data!E76 -> 554809000000 | F76: =Data!H76 -> 673005000000 | G76: =IFERROR(E76/F76,0) -> 0.82437575
D77: 2023 | E77: =Data!E77 -> 347200000000 | F77: =Data!H77 -> 840770000000 | G77: =IFERROR(E77/F77,0) -> 0.41295479
D78: 2024 | E78: =Data!E78 -> 295483000000 | F78: =Data!H78 -> 701500000000 | G78: =IFERROR(E78/F78,0) -> 0.42121597
B79: 8 | C79: PT Asuransi Jiwa BCA | D79: 2014 | E79: =Data!E79 -> 0 | F79: =Data!H79 -> 0 | G79: =IFERROR(E79/F79,0) -> 0
D80: 2015 | E80: =Data!E80 -> 10832000000 | F80: =Data!H80 -> 15519000000 | G80: =IFERROR(E80/F80,0) -> 0.69798312
D81: 2016 | E81: =Data!E81 -> 9355000000 | F81: =Data!H81 -> 44397000000 | G81: =IFERROR(E81/F81,0) -> 0.21071244
D82: 2017 | E82: =Data!E82 -> 9023000000 | F82: =Data!H82 -> 96254000000 | G82: =IFERROR(E82/F82,0) -> 0.093741559
D83: 2018 | E83: =Data!E83 -> 2165000000 | F83: =Data!H83 -> 62173000000 | G83: =IFERROR(E83/F83,0) -> 0.03482219
D84: 2019 | E84: =Data!E84 -> 5650000000 | F84: =Data!H84 -> 76452000000 | G84: =IFERROR(E84/F84,0) -> 0.073902579
D85: 2020 | E85: =Data!E85 -> 13881000000 | F85: =Data!H85 -> 89869000000 | G85: =IFERROR(E85/F85,0) -> 0.15445816
D86: 2021 | E86: =Data!E86 -> 2873000000 | F86: =Data!H86 -> 84761000000 | G86: =IFERROR(E86/F86,0) -> 0.033895306
D87: 2022 | E87: =Data!E87 -> 7230000000 | F87: =Data!H87 -> 117537000000 | G87: =IFERROR(E87/F87,0) -> 0.061512545
D88: 2023 | E88: =Data!E88 -> 3676000000 | F88: =Data!H88 -> 132809000000 | G88: =IFERROR(E88/F88,0) -> 0.027678847
D89: 2024 | E89: =Data!E89 -> 2728000000 | F89: =Data!H89 -> 97813000000 | G89: =IFERROR(E89/F89,0) -> 0.027889953
B90: 9 | C90: PT Asuransi Jiwa Central Asia Raya | D90: 2014 | E90: =Data!E90 -> 0 | F90: =Data!H90 -> 0 | G90: =IFERROR(E90/F90,0) -> 0
D91: 2015 | E91: =Data!E91 -> 9150000000 | F91: =Data!H91 -> 62044000000 | G91: =IFERROR(E91/F91,0) -> 0.14747598
D92: 2016 | E92: =Data!E92 -> 99955000000 | F92: =Data!H92 -> 374125000000 | G92: =IFERROR(E92/F92,0) -> 0.26717006
D93: 2017 | E93: =Data!E93 -> 19011000000 | F93: =Data!H93 -> 403817000000 | G93: =IFERROR(E93/F93,0) -> 0.047078256
D94: 2018 | E94: =Data!E94 -> 14894000000 | F94: =Data!H94 -> 446855000000 | G94: =IFERROR(E94/F94,0) -> 0.033330722
D95: 2019 | E95: =Data!E95 -> 13047000000 | F95: =Data!H95 -> 410765000000 | G95: =IFERROR(E95/F95,0) -> 0.031762687
D96: 2020 | E96: =Data!E96 -> 17657000000 | F96: =Data!H96 -> 418551000000 | G96: =IFERROR(E96/F96,0) -> 0.042186018
D97: 2021 | E97: =Data!E97 -> 12463000000 | F97: =Data!H97 -> 389107000000 | G97: =IFERROR(E97/F97,0) -> 0.03202975
D98: 2022 | E98: =Data!E98 -> 31388000000 | F98: =Data!H98 -> 384877000000 | G98: =IFERROR(E98/F98,0) -> 0.081553327
D99: 2023 | E99: =Data!E99 -> 14432000000 | F99: =Data!H99 -> 515004000000 | G99: =IFERROR(E99/F99,0) -> 0.028023083
D100: 2024 | E100: =Data!E100 -> 65375000000 | F100: =Data!H100 -> 403540000000 | G100: =IFERROR(E100/F100,0) -> 0.16200377
...

Sheet DAR
A1: Sub Sektor | B1: No | C1: Nama Perusahaan | D1: Tahun | E1: Total Hutang | F1: Total Aset | G1: Debt to Asset Ratio
A2: Asuransi Jiwa | B2: 1 | C2: Asuransi Jiwa Bersama Bumiputera 1912 | D2: 2014 | E2: =Data!I2 -> 0 | F2: =Data!G2 -> 0 | G2: =IFERROR(E2/F2,0) -> 0
D3: 2015 | E3: =Data!I3 -> 0 | F3: =Data!G3 -> 0 | G3: =IFERROR(E3/F3,0) -> 0
D4: 2016 | E4: =Data!I4 -> 0 | F4: =Data!G4 -> 0 | G4: =IFERROR(E4/F4,0) -> 0
D5: 2017 | E5: =Data!I5 -> 0 | F5: =Data!G5 -> 0 | G5: =IFERROR(E5/F5,0) -> 0
D6: 2018 | E6: =Data!I6 -> 0 | F6: =Data!G6 -> 0 | G6: =IFERROR(E6/F6,0) -> 0
D7: 2019 | E7: =Data!I7 -> 0 | F7: =Data!G7 -> 0 | G7: =IFERROR(E7/F7,0) -> 0
D8: 2020 | E8: =Data!I8 -> 0 | F8: =Data!G8 -> 0 | G8: =IFERROR(E8/F8,0) -> 0
D9: 2021 | E9: =Data!I9 -> 0 | F9: =Data!G9 -> 0 | G9: =IFERROR(E9/F9,0) -> 0
D10: 2022 | E10: =Data!I10 -> 0 | F10: =Data!G10 -> 0 | G10: =IFERROR(E10/F10,0) -> 0
D11: 2023 | E11: =Data!I11 -> 0 | F11: =Data!G11 -> 0 | G11: =IFERROR(E11/F11,0) -> 0
D12: 2024 | E12: =Data!I12 -> 0 | F12: =Data!G12 -> 0 | G12: =IFERROR(E12/F12,0) -> 0
B13: 2 | C13: PT AIA Financial | D13: 2014 | E13: =Data!I13 -> 0 | F13: =Data!G13 -> 0 | G13: =IFERROR(E13/F13,0) -> 0
D14: 2015 | E14: =Data!I14 -> 25291701000000 | F14: =Data!G14 -> 31860954000000 | G14: =IFERROR(E14/F14,0) -> 0.79381493
D15: 2016 | E15: =Data!I15 -> 28001542000000 | F15: =Data!G15 -> 35767906000000 | G15: =IFERROR(E15/F15,0) -> 0.7828678
D16: 2017 | E16: =Data!I16 -> 34375378000000 | F16: =Data!G16 -> 44937292000000 | G16: =IFERROR(E16/F16,0) -> 0.76496327
D17: 2018 | E17: =Data!I17 -> 35535336000000 | F17: =Data!G17 -> 46562563000000 | G17: =IFERROR(E17/F17,0) -> 0.76317397
D18: 2019 | E18: =Data!I18 -> 38172435000000 | F18: =Data!G18 -> 50043024000000 | G18: =IFERROR(E18/F18,0) -> 0.76279233
D19: 2020 | E19: =Data!I19 -> 41373205000000 | F19: =Data!G19 -> 53134780000000 | G19: =IFERROR(E19/F19,0) -> 0.7786464
D20: 2021 | E20: =Data!I20 -> 40473683000000 | F20: =Data!G20 -> 52330016000000 | G20: =IFERROR(E20/F20,0) -> 0.7734315
D21: 2022 | E21: =Data!I21 -> 36682436000000 | F21: =Data!G21 -> 44912325000000 | G21: =IFERROR(E21/F21,0) -> 0.81675656
D22: 2023 | E22: =Data!I22 -> 33736676000000 | F22: =Data!G22 -> 41785302000000 | G22: =IFERROR(E22/F22,0) -> 0.80738141
D23: 2024 | E23: =Data!I23 -> 30987181000000 | F23: =Data!G23 -> 39899482000000 | G23: =IFERROR(E23/F23,0) -> 0.77663116
B24: 3 | C24: PT Asuransi Allianz Life Indonesia | D24: 2014 | E24: =Data!I24 -> 0 | F24: =Data!G24 -> 0 | G24: =IFERROR(E24/F24,0) -> 0
D25: 2015 | E25: =Data!I25 -> 22909265000000 | F25: =Data!G25 -> 27635118000000 | G25: =IFERROR(E25/F25,0) -> 0.82899103
D26: 2016 | E26: =Data!I26 -> 24436046000000 | F26: =Data!G26 -> 30294789000000 | G26: =IFERROR(E26/F26,0) -> 0.80660889
D27: 2017 | E27: =Data!I27 -> 27527468000000 | F27: =Data!G27 -> 35751863000000 | G27: =IFERROR(E27/F27,0) -> 0.76995898
D28: 2018 | E28: =Data!I28 -> 27304202000000 | F28: =Data!G28 -> 35266933000000 | G28: =IFERROR(E28/F28,0) -> 0.77421538
D29: 2019 | E29: =Data!I29 -> 29736010000000 | F29: =Data!G29 -> 38345233000000 | G29: =IFERROR(E29/F29,0) -> 0.77548127
D30: 2020 | E30: =Data!I30 -> 31830554000000 | F30: =Data!G30 -> 41166712000000 | G30: =IFERROR(E30/F30,0) -> 0.77321099
D31: 2021 | E31: =Data!I31 -> 33849131000000 | F31: =Data!G31 -> 42808931000000 | G31: =IFERROR(E31/F31,0) -> 0.79070255
D32: 2022 | E32: =Data!I32 -> 32037270000000 | F32: =Data!G32 -> 41194961000000 | G32: =IFERROR(E32/F32,0) -> 0.77769876
D33: 2023 | E33: =Data!I33 -> 31712785000000 | F33: =Data!G33 -> 40147448000000 | G33: =IFERROR(E33/F33,0) -> 0.78990787
D34: 2024 | E34: =Data!I34 -> 30372565000000 | F34: =Data!G34 -> 39131978000000 | G34: =IFERROR(E34/F34,0) -> 0.77615716
B35: 4 | C35: PT Asuransi Allianz Life Syariah Indonesia | D35: 2014 | E35: =Data!I35 -> 0 | F35: =Data!G35 -> 0 | G35: =IFERROR(E35/F35,0) -> 0
D36: 2015 | E36: =Data!I36 -> 0 | F36: =Data!G36 -> 0 | G36: =IFERROR(E36/F36,0) -> 0
D37: 2016 | E37: =Data!I37 -> 0 | F37: =Data!G37 -> 0 | G37: =IFERROR(E37/F37,0) -> 0
D38: 2017 | E38: =Data!I38 -> 0 | F38: =Data!G38 -> 0 | G38: =IFERROR(E38/F38,0) -> 0
D39: 2018 | E39: =Data!I39 -> 0 | F39: =Data!G39 -> 0 | G39: =IFERROR(E39/F39,0) -> 0
D40: 2019 | E40: =Data!I40 -> 0 | F40: =Data!G40 -> 0 | G40: =IFERROR(E40/F40,0) -> 0
D41: 2020 | E41: =Data!I41 -> 0 | F41: =Data!G41 -> 0 | G41: =IFERROR(E41/F41,0) -> 0
D42: 2021 | E42: =Data!I42 -> 0 | F42: =Data!G42 -> 0 | G42: =IFERROR(E42/F42,0) -> 0
D43: 2022 | E43: =Data!I43 -> 891833000000 | F43: =Data!G43 -> 4337827000000 | G43: =IFERROR(E43/F43,0) -> 0.20559441
D44: 2023 | E44: =Data!I44 -> 867595000000 | F44: =Data!G44 -> 3620310000000 | G44: =IFERROR(E44/F44,0) -> 0.2396466
D45: 2024 | E45: =Data!I45 -> 913660000000 | F45: =Data!G45 -> 3339322000000 | G45: =IFERROR(E45/F45,0) -> 0.27360644
B46: 5 | C46: PT Asuransi BRI Life | D46: 2014 | E46: =Data!I46 -> 0 | F46: =Data!G46 -> 0 | G46: =IFERROR(E46/F46,0) -> 0
D47: 2015 | E47: =Data!I47 -> 3608103108000 | F47: =Data!G47 -> 4933308738000 | G47: =IFERROR(E47/F47,0) -> 0.7313759
D48: 2016 | E48: =Data!I48 -> 4512591084000 | F48: =Data!G48 -> 6176329027000 | G48: =IFERROR(E48/F48,0) -> 0.73062673
D49: 2017 | E49: =Data!I49 -> 5984418466000 | F49: =Data!G49 -> 8162691116000 | G49: =IFERROR(E49/F49,0) -> 0.73314283
D50: 2018 | E50: =Data!I50 -> 7033564683000 | F50: =Data!G50 -> 9356504263000 | G50: =IFERROR(E50/F50,0) -> 0.75172997
D51: 2019 | E51: =Data!I51 -> 8407279000000 | F51: =Data!G51 -> 11084971000000 | G51: =IFERROR(E51/F51,0) -> 0.75843942
D52: 2020 | E52: =Data!I52 -> 10081934000000 | F52: =Data!G52 -> 13044264000000 | G52: =IFERROR(E52/F52,0) -> 0.77290171
D53: 2021 | E53: =Data!I53 -> 11381796000000 | F53: =Data!G53 -> 18260736000000 | G53: =IFERROR(E53/F53,0) -> 0.62329339
D54: 2022 | E54: =Data!I54 -> 13552263000000 | F54: =Data!G54 -> 21494817000000 | G54: =IFERROR(E54/F54,0) -> 0.63048981
D55: 2023 | E55: =Data!I55 -> 14172581000000 | F55: =Data!G55 -> 23552167000000 | G55: =IFERROR(E55/F55,0) -> 0.60175274
D56: 2024 | E56: =Data!I56 -> 0 | F56: =Data!G56 -> 0 | G56: =IFERROR(E56/F56,0) -> 0
B57: 6 | C57: PT Asuransi Ciputra Indonesia | D57: 2014 | E57: =Data!I57 -> 0 | F57: =Data!G57 -> 0 | G57: =IFERROR(E57/F57,0) -> 0
D58: 2015 | E58: =Data!I58 -> 0 | F58: =Data!G58 -> 0 | G58: =IFERROR(E58/F58,0) -> 0
D59: 2016 | E59: =Data!I59 -> 3417000000 | F59: =Data!G59 -> 98507000000 | G59: =IFERROR(E59/F59,0) -> 0.03468789
D60: 2017 | E60: =Data!I60 -> 11160000000 | F60: =Data!G60 -> 116479000000 | G60: =IFERROR(E60/F60,0) -> 0.095811262
D61: 2018 | E61: =Data!I61 -> 50492000000 | F61: =Data!G61 -> 152680000000 | G61: =IFERROR(E61/F61,0) -> 0.33070474
D62: 2019 | E62: =Data!I62 -> 87535000000 | F62: =Data!G62 -> 214472000000 | G62: =IFERROR(E62/F62,0) -> 0.40814186
D63: 2020 | E63: =Data!I63 -> 138272000000 | F63: =Data!G63 -> 278255000000 | G63: =IFERROR(E63/F63,0) -> 0.49692548
D64: 2021 | E64: =Data!I64 -> 252304000000 | F64: =Data!G64 -> 384372000000 | G64: =IFERROR(E64/F64,0) -> 0.65640577
D65: 2022 | E65: =Data!I65 -> 359910000000 | F65: =Data!G65 -> 517439000000 | G65: =IFERROR(E65/F65,0) -> 0.69556025
D66: 2023 | E66: =Data!I66 -> 548082000000 | F66: =Data!G66 -> 714057000000 | G66: =IFERROR(E66/F66,0) -> 0.76756057
D67: 2024 | E67: =Data!I67 -> 796246000000 | F67: =Data!G67 -> 997332000000 | G67: =IFERROR(E67/F67,0) -> 0.79837607
B68: 7 | C68: PT Asuransi Jiwa Astra | D68: 2014 | E68: =Data!I68 -> 0 | F68: =Data!G68 -> 0 | G68: =IFERROR(E68/F68,0) -> 0
D69: 2015 | E69: =Data!I69 -> 1364281000000 | F69: =Data!G69 -> 1899837000000 | G69: =IFERROR(E69/F69,0) -> 0.71810424
D70: 2016 | E70: =Data!I70 -> 2965233000000 | F70: =Data!G70 -> 3802688000000 | G70: =IFERROR(E70/F70,0) -> 0.77977289
D71: 2017 | E71: =Data!I71 -> 3703552000000 | F71: =Data!G71 -> 4315435000000 | G71: =IFERROR(E71/F71,0) -> 0.85821059
D72: 2018 | E72: =Data!I72 -> 4569886000000 | F72: =Data!G72 -> 5004717000000 | G72: =IFERROR(E72/F72,0) -> 0.91311577
D73: 2019 | E73: =Data!I73 -> 5043700000000 | F73: =Data!G73 -> 5901298000000 | G73: =IFERROR(E73/F73,0) -> 0.85467638
D74: 2020 | E74: =Data!I74 -> 5746720000000 | F74: =Data!G74 -> 6587066000000 | G74: =IFERROR(E74/F74,0) -> 0.87242484
D75: 2021 | E75: =Data!I75 -> 6266517000000 | F75: =Data!G75 -> 7092935000000 | G75: =IFERROR(E75/F75,0) -> 0.88348716
D76: 2022 | E76: =Data!I76 -> 6661879000000 | F76: =Data!G76 -> 7345755000000 | G76: =IFERROR(E76/F76,0) -> 0.90690188
D77: 2023 | E77: =Data!I77 -> 6800327000000 | F77: =Data!G77 -> 7501061000000 | G77: =IFERROR(E77/F77,0) -> 0.90658202
D78: 2024 | E78: =Data!I78 -> 6056599000000 | F78: =Data!G78 -> 6806055000000 | G78: =IFERROR(E78/F78,0) -> 0.88988393
B79: 8 | C79: PT Asuransi Jiwa BCA | D79: 2014 | E79: =Data!I79 -> 0 | F79: =Data!G79 -> 0 | G79: =IFERROR(E79/F79,0) -> 0
D80: 2015 | E80: =Data!I80 -> 52698000000 | F80: =Data!G80 -> 281282000000 | G80: =IFERROR(E80/F80,0) -> 0.18734935
D81: 2016 | E81: =Data!I81 -> 181020000000 | F81: =Data!G81 -> 385447000000 | G81: =IFERROR(E81/F81,0) -> 0.46963655
D82: 2017 | E82: =Data!I82 -> 375260000000 | F82: =Data!G82 -> 842122000000 | G82: =IFERROR(E82/F82,0) -> 0.44561239
D83: 2018 | E83: =Data!I83 -> 514818000000 | F83: =Data!G83 -> 902876000000 | G83: =IFERROR(E83/F83,0) -> 0.5701979
D84: 2019 | E84: =Data!I84 -> 753776000000 | F84: =Data!G84 -> 1154689000000 | G84: =IFERROR(E84/F84,0) -> 0.65279569
D85: 2020 | E85: =Data!I85 -> 975453000000 | F85: =Data!G85 -> 1467896000000 | G85: =IFERROR(E85/F85,0) -> 0.6645246
D86: 2021 | E86: =Data!I86 -> 1397617000000 | F86: =Data!G86 -> 1930213000000 | G86: =IFERROR(E86/F86,0) -> 0.72407398
D87: 2022 | E87: =Data!I87 -> 1688561000000 | F87: =Data!G87 -> 2347921000000 | G87: =IFERROR(E87/F87,0) -> 0.71917283
D88: 2023 | E88: =Data!I88 -> 2148138000000 | F88: =Data!G88 -> 2878724000000 | G88: =IFERROR(E88/F88,0) -> 0.74621186
D89: 2024 | E89: =Data!I89 -> 2525508000000 | F89: =Data!G89 -> 3339666000000 | G89: =IFERROR(E89/F89,0) -> 0.75621574
B90: 9 | C90: PT Asuransi Jiwa Central Asia Raya | D90: 2014 | E90: =Data!I90 -> 0 | F90: =Data!G90 -> 0 | G90: =IFERROR(E90/F90,0) -> 0
D91: 2015 | E91: =Data!I91 -> 2852326000000 | F91: =Data!G91 -> 4598462000000 | G91: =IFERROR(E91/F91,0) -> 0.62027826
D92: 2016 | E92: =Data!I92 -> 3397124000000 | F92: =Data!G92 -> 5298273000000 | G92: =IFERROR(E92/F92,0) -> 0.64117572
D93: 2017 | E93: =Data!I93 -> 4348556000000 | F93: =Data!G93 -> 5618666000000 | G93: =IFERROR(E93/F93,0) -> 0.77394812
D94: 2018 | E94: =Data!I94 -> 5300406000000 | F94: =Data!G94 -> 6696353000000 | G94: =IFERROR(E94/F94,0) -> 0.79153623
D95: 2019 | E95: =Data!I95 -> 6383523000000 | F95: =Data!G95 -> 8158087000000 | G95: =IFERROR(E95/F95,0) -> 0.78247793
D96: 2020 | E96: =Data!I96 -> 6749524000000 | F96: =Data!G96 -> 8569933000000 | G96: =IFERROR(E96/F96,0) -> 0.78758189
D97: 2021 | E97: =Data!I97 -> 7169272000000 | F97: =Data!G97 -> 10111397000000 | G97: =IFERROR(E97/F97,0) -> 0.70902883
D98: 2022 | E98: =Data!I98 -> 7279861000000 | F98: =Data!G98 -> 10357588000000 | G98: =IFERROR(E98/F98,0) -> 0.70285292
D99: 2023 | E99: =Data!I99 -> 7874976000000 | F99: =Data!G99 -> 11033985000000 | G99: =IFERROR(E99/F99,0) -> 0.71370189
D100: 2024 | E100: =Data!I100 -> 7771730000000 | F100: =Data!G100 -> 11181540000000 | G100: =IFERROR(E100/F100,0) -> 0.69505006
...

Sheet DER
A1: Sub Sektor | B1: No | C1: Nama Perusahaan | D1: Tahun | E1: Total Hutang | F1: Total Ekuitas | G1: Debt to Equity Ratio
A2: Asuransi Jiwa | B2: 1 | C2: Asuransi Jiwa Bersama Bumiputera 1912 | D2: 2014 | E2: =Data!I2 -> 0 | F2: =Data!K2 -> 0 | G2: =IFERROR(E2/F2,0) -> 0
D3: 2015 | E3: =Data!I3 -> 0 | F3: =Data!K3 -> 0 | G3: =IFERROR(E3/F3,0) -> 0
D4: 2016 | E4: =Data!I4 -> 0 | F4: =Data!K4 -> 0 | G4: =IFERROR(E4/F4,0) -> 0
D5: 2017 | E5: =Data!I5 -> 0 | F5: =Data!K5 -> 0 | G5: =IFERROR(E5/F5,0) -> 0
D6: 2018 | E6: =Data!I6 -> 0 | F6: =Data!K6 -> 0 | G6: =IFERROR(E6/F6,0) -> 0
D7: 2019 | E7: =Data!I7 -> 0 | F7: =Data!K7 -> 0 | G7: =IFERROR(E7/F7,0) -> 0
D8: 2020 | E8: =Data!I8 -> 0 | F8: =Data!K8 -> 0 | G8: =IFERROR(E8/F8,0) -> 0
D9: 2021 | E9: =Data!I9 -> 0 | F9: =Data!K9 -> 0 | G9: =IFERROR(E9/F9,0) -> 0
D10: 2022 | E10: =Data!I10 -> 0 | F10: =Data!K10 -> 0 | G10: =IFERROR(E10/F10,0) -> 0
D11: 2023 | E11: =Data!I11 -> 0 | F11: =Data!K11 -> 0 | G11: =IFERROR(E11/F11,0) -> 0
D12: 2024 | E12: =Data!I12 -> 0 | F12: =Data!K12 -> 0 | G12: =IFERROR(E12/F12,0) -> 0
B13: 2 | C13: PT AIA Financial | D13: 2014 | E13: =Data!I13 -> 0 | F13: =Data!K13 -> 0 | G13: =IFERROR(E13/F13,0) -> 0
D14: 2015 | E14: =Data!I14 -> 25291701000000 | F14: =Data!K14 -> 6569253000000 | G14: =IFERROR(E14/F14,0) -> 3.8500117
D15: 2016 | E15: =Data!I15 -> 28001542000000 | F15: =Data!K15 -> 7766364000000 | G15: =IFERROR(E15/F15,0) -> 3.6054893
D16: 2017 | E16: =Data!I16 -> 34375378000000 | F16: =Data!K16 -> 10561914000000 | G16: =IFERROR(E16/F16,0) -> 3.2546542
D17: 2018 | E17: =Data!I17 -> 35535336000000 | F17: =Data!K17 -> 11027227000000 | G17: =IFERROR(E17/F17,0) -> 3.2225088
D18: 2019 | E18: =Data!I18 -> 38172435000000 | F18: =Data!K18 -> 11870589000000 | G18: =IFERROR(E18/F18,0) -> 3.2157153
D19: 2020 | E19: =Data!I19 -> 41373205000000 | F19: =Data!K19 -> 11761575000000 | G19: =IFERROR(E19/F19,0) -> 3.5176586
D20: 2021 | E20: =Data!I20 -> 40473683000000 | F20: =Data!K20 -> 11856333000000 | G20: =IFERROR(E20/F20,0) -> 3.4136763
D21: 2022 | E21: =Data!I21 -> 36682436000000 | F21: =Data!K21 -> 8229889000000 | G21: =IFERROR(E21/F21,0) -> 4.4572212
D22: 2023 | E22: =Data!I22 -> 33736676000000 | F22: =Data!K22 -> 8048626000000 | G22: =IFERROR(E22/F22,0) -> 4.1916069
D23: 2024 | E23: =Data!I23 -> 30987181000000 | F23: =Data!K23 -> 8912301000000 | G23: =IFERROR(E23/F23,0) -> 3.4769002
B24: 3 | C24: PT Asuransi Allianz Life Indonesia | D24: 2014 | E24: =Data!I24 -> 0 | F24: =Data!K24 -> 0 | G24: =IFERROR(E24/F24,0) -> 0
D25: 2015 | E25: =Data!I25 -> 22909265000000 | F25: =Data!K25 -> 4355995000000 | G25: =IFERROR(E25/F25,0) -> 5.2592496
D26: 2016 | E26: =Data!I26 -> 24436046000000 | F26: =Data!K26 -> 5381290000000 | G26: =IFERROR(E26/F26,0) -> 4.5409272
D27: 2017 | E27: =Data!I27 -> 27527468000000 | F27: =Data!K27 -> 6030989000000 | G27: =IFERROR(E27/F27,0) -> 4.5643373
D28: 2018 | E28: =Data!I28 -> 27304202000000 | F28: =Data!K28 -> 5768100000000 | G28: =IFERROR(E28/F28,0) -> 4.7336561
D29: 2019 | E29: =Data!I29 -> 29736010000000 | F29: =Data!K29 -> 6511324000000 | G29: =IFERROR(E29/F29,0) -> 4.5668147
D30: 2020 | E30: =Data!I30 -> 31830554000000 | F30: =Data!K30 -> 7090980000000 | G30: =IFERROR(E30/F30,0) -> 4.4888794
D31: 2021 | E31: =Data!I31 -> 33849131000000 | F31: =Data!K31 -> 6945025000000 | G31: =IFERROR(E31/F31,0) -> 4.8738674
D32: 2022 | E32: =Data!I32 -> 32037270000000 | F32: =Data!K32 -> 7208812000000 | G32: =IFERROR(E32/F32,0) -> 4.4441816
D33: 2023 | E33: =Data!I33 -> 31712785000000 | F33: =Data!K33 -> 6640072000000 | G33: =IFERROR(E33/F33,0) -> 4.77597
D34: 2024 | E34: =Data!I34 -> 30372565000000 | F34: =Data!K34 -> 7301939000000 | G34: =IFERROR(E34/F34,0) -> 4.1595205
B35: 4 | C35: PT Asuransi Allianz Life Syariah Indonesia | D35: 2014 | E35: =Data!I35 -> 0 | F35: =Data!K35 -> 0 | G35: =IFERROR(E35/F35,0) -> 0
D36: 2015 | E36: =Data!I36 -> 0 | F36: =Data!K36 -> 0 | G36: =IFERROR(E36/F36,0) -> 0
D37: 2016 | E37: =Data!I37 -> 0 | F37: =Data!K37 -> 0 | G37: =IFERROR(E37/F37,0) -> 0
D38: 2017 | E38: =Data!I38 -> 0 | F38: =Data!K38 -> 0 | G38: =IFERROR(E38/F38,0) -> 0
D39: 2018 | E39: =Data!I39 -> 0 | F39: =Data!K39 -> 0 | G39: =IFERROR(E39/F39,0) -> 0
D40: 2019 | E40: =Data!I40 -> 0 | F40: =Data!K40 -> 0 | G40: =IFERROR(E40/F40,0) -> 0
D41: 2020 | E41: =Data!I41 -> 0 | F41: =Data!K41 -> 0 | G41: =IFERROR(E41/F41,0) -> 0
D42: 2021 | E42: =Data!I42 -> 0 | F42: =Data!K42 -> 0 | G42: =IFERROR(E42/F42,0) -> 0
D43: 2022 | E43: =Data!I43 -> 891833000000 | F43: =Data!K43 -> 1497483000000 | G43: =IFERROR(E43/F43,0) -> 0.59555467
D44: 2023 | E44: =Data!I44 -> 867595000000 | F44: =Data!K44 -> 958124000000 | G44: =IFERROR(E44/F44,0) -> 0.90551432
D45: 2024 | E45: =Data!I45 -> 913660000000 | F45: =Data!K45 -> 968188000000 | G45: =IFERROR(E45/F45,0) -> 0.94368036
B46: 5 | C46: PT Asuransi BRI Life | D46: 2014 | E46: =Data!I46 -> 0 | F46: =Data!K46 -> 0 | G46: =IFERROR(E46/F46,0) -> 0
D47: 2015 | E47: =Data!I47 -> 3608103108000 | F47: =Data!K47 -> 4933308738000 | G47: =IFERROR(E47/F47,0) -> 0.7313759
D48: 2016 | E48: =Data!I48 -> 4512591084000 | F48: =Data!K48 -> 6176329027000 | G48: =IFERROR(E48/F48,0) -> 0.73062673
D49: 2017 | E49: =Data!H49 -> 170181075000 | F49: =Data!K49 -> 2104006591000 | G49: =IFERROR(E49/F49,0) -> 0.080884288
D50: 2018 | E50: =Data!I50 -> 7033564683000 | F50: =Data!K50 -> 2231804990000 | G50: =IFERROR(E50/F50,0) -> 3.151514
D51: 2019 | E51: =Data!I51 -> 8407279000000 | F51: =Data!K51 -> 2563929000000 | G51: =IFERROR(E51/F51,0) -> 3.2790608
D52: 2020 | E52: =Data!I52 -> 10081934000000 | F52: =Data!K52 -> 2794003000000 | G52: =IFERROR(E52/F52,0) -> 3.6084192
D53: 2021 | E53: =Data!I53 -> 11381796000000 | F53: =Data!K53 -> 6683102000000 | G53: =IFERROR(E53/F53,0) -> 1.7030708
D54: 2022 | E54: =Data!I54 -> 13552263000000 | F54: =Data!K54 -> 7706566000000 | G54: =IFERROR(E54/F54,0) -> 1.7585346
D55: 2023 | E55: =Data!I55 -> 14172581000000 | F55: =Data!K55 -> 9111525000000 | G55: =IFERROR(E55/F55,0) -> 1.5554565
D56: 2024 | E56: =Data!I56 -> 0 | F56: =Data!K56 -> 0 | G56: =IFERROR(E56/F56,0) -> 0
B57: 6 | C57: PT Asuransi Ciputra Indonesia | D57: 2014 | E57: =Data!I57 -> 0 | F57: =Data!K57 -> 0 | G57: =IFERROR(E57/F57,0) -> 0
D58: 2015 | E58: =Data!I58 -> 0 | F58: =Data!K58 -> 0 | G58: =IFERROR(E58/F58,0) -> 0
D59: 2016 | E59: =Data!I59 -> 3417000000 | F59: =Data!K59 -> 95091000000 | G59: =IFERROR(E59/F59,0) -> 0.035934
D60: 2017 | E60: =Data!I60 -> 11160000000 | F60: =Data!K60 -> 105319000000 | G60: =IFERROR(E60/F60,0) -> 0.10596379
D61: 2018 | E61: =Data!I61 -> 50492000000 | F61: =Data!K61 -> 102188000000 | G61: =IFERROR(E61/F61,0) -> 0.4941089
D62: 2019 | E62: =Data!I62 -> 87535000000 | F62: =Data!K62 -> 126937000000 | G62: =IFERROR(E62/F62,0) -> 0.68959405
D63: 2020 | E63: =Data!I63 -> 138272000000 | F63: =Data!K63 -> 139982000000 | G63: =IFERROR(E63/F63,0) -> 0.98778414
D64: 2021 | E64: =Data!I64 -> 252304000000 | F64: =Data!K64 -> 132068000000 | G64: =IFERROR(E64/F64,0) -> 1.9104098
D65: 2022 | E65: =Data!I65 -> 359910000000 | F65: =Data!K65 -> 157529000000 | G65: =IFERROR(E65/F65,0) -> 2.2847222
D66: 2023 | E66: =Data!I66 -> 548082000000 | F66: =Data!K66 -> 165975000000 | G66: =IFERROR(E66/F66,0) -> 3.3021961
D67: 2024 | E67: =Data!I67 -> 796246000000 | F67: =Data!K67 -> 201086000000 | G67: =IFERROR(E67/F67,0) -> 3.9597287
B68: 7 | C68: PT Asuransi Jiwa Astra | D68: 2014 | E68: =Data!I68 -> 0 | F68: =Data!K68 -> 0 | G68: =IFERROR(E68/F68,0) -> 0
D69: 2015 | E69: =Data!I69 -> 1364281000000 | F69: =Data!K69 -> 535556000000 | G69: =IFERROR(E69/F69,0) -> 2.5474105
D70: 2016 | E70: =Data!I70 -> 2965233000000 | F70: =Data!K70 -> 837455000000 | G70: =IFERROR(E70/F70,0) -> 3.540767
D71: 2017 | E71: =Data!I71 -> 3703552000000 | F71: =Data!K71 -> 611883000000 | G71: =IFERROR(E71/F71,0) -> 6.0527127
D72: 2018 | E72: =Data!I72 -> 4569886000000 | F72: =Data!K72 -> 434830000000 | G72: =IFERROR(E72/F72,0) -> 10.509592
D73: 2019 | E73: =Data!I73 -> 5043700000000 | F73: =Data!K73 -> 857598000000 | G73: =IFERROR(E73/F73,0) -> 5.8811938
D74: 2020 | E74: =Data!I74 -> 5746720000000 | F74: =Data!K74 -> 840112000000 | G74: =IFERROR(E74/F74,0) -> 6.8404213
D75: 2021 | E75: =Data!I75 -> 6266517000000 | F75: =Data!K75 -> 826251000000 | G75: =IFERROR(E75/F75,0) -> 7.5842777
D76: 2022 | E76: =Data!I76 -> 6661879000000 | F76: =Data!K76 -> 683137000000 | G76: =IFERROR(E76/F76,0) -> 9.7518931
D77: 2023 | E77: =Data!I77 -> 6800327000000 | F77: =Data!K77 -> 699090000000 | G77: =IFERROR(E77/F77,0) -> 9.7273985
D78: 2024 | E78: =Data!I78 -> 6056599000000 | F78: =Data!K78 -> 748206000000 | G78: =IFERROR(E78/F78,0) -> 8.0948282
B79: 8 | C79: PT Asuransi Jiwa BCA | D79: 2014 | E79: =Data!I79 -> 0 | F79: =Data!K79 -> 0 | G79: =IFERROR(E79/F79,0) -> 0
D80: 2015 | E80: =Data!I80 -> 52698000000 | F80: =Data!K80 -> 228584000000 | G80: =IFERROR(E80/F80,0) -> 0.23054107
D81: 2016 | E81: =Data!I81 -> 181020000000 | F81: =Data!K81 -> 204426000000 | G81: =IFERROR(E81/F81,0) -> 0.8855038
D82: 2017 | E82: =Data!I82 -> 375260000000 | F82: =Data!K82 -> 466862000000 | G82: =IFERROR(E82/F82,0) -> 0.80379213
D83: 2018 | E83: =Data!I83 -> 514818000000 | F83: =Data!K83 -> 388058000000 | G83: =IFERROR(E83/F83,0) -> 1.3266522
D84: 2019 | E84: =Data!I84 -> 753776000000 | F84: =Data!K84 -> 400913000000 | G84: =IFERROR(E84/F84,0) -> 1.8801486
D85: 2020 | E85: =Data!I85 -> 975453000000 | F85: =Data!K85 -> 492443000000 | G85: =IFERROR(E85/F85,0) -> 1.9808445
D86: 2021 | E86: =Data!I86 -> 1397617000000 | F86: =Data!K86 -> 532596000000 | G86: =IFERROR(E86/F86,0) -> 2.6241598
D87: 2022 | E87: =Data!I87 -> 1688561000000 | F87: =Data!K87 -> 659360000000 | G87: =IFERROR(E87/F87,0) -> 2.5609091
D88: 2023 | E88: =Data!I88 -> 2148138000000 | F88: =Data!K88 -> 730586000000 | G88: =IFERROR(E88/F88,0) -> 2.9402945
D89: 2024 | E89: =Data!I89 -> 2525508000000 | F89: =Data!K89 -> 814158000000 | G89: =IFERROR(E89/F89,0) -> 3.1019876
B90: 9 | C90: PT Asuransi Jiwa Central Asia Raya | D90: 2014 | E90: =Data!I90 -> 0 | F90: =Data!K90 -> 0 | G90: =IFERROR(E90/F90,0) -> 0
D91: 2015 | E91: =Data!I91 -> 2852326000000 | F91: =Data!K91 -> 1729967000000 | G91: =IFERROR(E91/F91,0) -> 1.6487748
D92: 2016 | E92: =Data!I92 -> 3397124000000 | F92: =Data!K92 -> 1901149000000 | G92: =IFERROR(E92/F92,0) -> 1.7868794
D93: 2017 | E93: =Data!I93 -> 4348556000000 | F93: =Data!K93 -> 1270110000000 | G93: =IFERROR(E93/F93,0) -> 3.4237633
D94: 2018 | E94: =Data!I94 -> 5300406000000 | F94: =Data!K94 -> 6696353000000 | G94: =IFERROR(E94/F94,0) -> 0.79153623
D95: 2019 | E95: =Data!I95 -> 6383523000000 | F95: =Data!K95 -> 8158087000000 | G95: =IFERROR(E95/F95,0) -> 0.78247793
D96: 2020 | E96: =Data!I96 -> 6749524000000 | F96: =Data!K96 -> 1820409000000 | G96: =IFERROR(E96/F96,0) -> 3.7076965
D97: 2021 | E97: =Data!I97 -> 7169272000000 | F97: =Data!K97 -> 2942125000000 | G97: =IFERROR(E97/F97,0) -> 2.4367666
D98: 2022 | E98: =Data!I98 -> 7279861000000 | F98: =Data!K98 -> 3077726000000 | G98: =IFERROR(E98/F98,0) -> 2.3653376
D99: 2023 | E99: =Data!I99 -> 7874976000000 | F99: =Data!K99 -> 3159009000000 | G99: =IFERROR(E99/F99,0) -> 2.4928628
D100: 2024 | E100: =Data!I100 -> 7771730000000 | F100: =Data!K100 -> 3409810000000 | G100: =IFERROR(E100/F100,0) -> 2.2792267
...

Sheet NPM
A1: Sub Sektor | B1: No | C1: Nama Perusahaan | D1: Tahun | E1: Laba Bersih | F1: Total Pendapatan | G1: Net Profit Margin
A2: Asuransi Jiwa | B2: 1 | C2: Asuransi Jiwa Bersama Bumiputera 1912 | D2: 2014 | E2: =Data!N2 -> 0 | F2: =Data!L2 -> 0 | G2: =IFERROR(E2/F2,0) -> 0
D3: 2015 | E3: =Data!N3 -> 0 | F3: =Data!L3 -> 0 | G3: =IFERROR(E3/F3,0) -> 0
D4: 2016 | E4: =Data!N4 -> 0 | F4: =Data!L4 -> 0 | G4: =IFERROR(E4/F4,0) -> 0
D5: 2017 | E5: =Data!N5 -> 0 | F5: =Data!L5 -> 0 | G5: =IFERROR(E5/F5,0) -> 0
D6: 2018 | E6: =Data!N6 -> 0 | F6: =Data!L6 -> 0 | G6: =IFERROR(E6/F6,0) -> 0
D7: 2019 | E7: =Data!N7 -> 0 | F7: =Data!L7 -> 0 | G7: =IFERROR(E7/F7,0) -> 0
D8: 2020 | E8: =Data!N8 -> 0 | F8: =Data!L8 -> 0 | G8: =IFERROR(E8/F8,0) -> 0
D9: 2021 | E9: =Data!N9 -> 0 | F9: =Data!L9 -> 0 | G9: =IFERROR(E9/F9,0) -> 0
D10: 2022 | E10: =Data!N10 -> 0 | F10: =Data!L10 -> 0 | G10: =IFERROR(E10/F10,0) -> 0
D11: 2023 | E11: =Data!N11 -> 0 | F11: =Data!L11 -> 0 | G11: =IFERROR(E11/F11,0) -> 0
D12: 2024 | E12: =Data!N12 -> 0 | F12: =Data!L12 -> 0 | G12: =IFERROR(E12/F12,0) -> 0
B13: 2 | C13: PT AIA Financial | D13: 2014 | E13: =Data!N13 -> 0 | F13: =Data!L13 -> 11948691000000 | G13: =IFERROR(E13/F13,0) -> 0
D14: 2015 | E14: =Data!N14 -> 848437000000 | F14: =Data!L14 -> 8985907000000 | G14: =IFERROR(E14/F14,0) -> 0.094418627
D15: 2016 | E15: =Data!N15 -> 1197111000000 | F15: =Data!L15 -> 13264521000000 | G15: =IFERROR(E15/F15,0) -> 0.090249094
D16: 2017 | E16: =Data!N16 -> 1562417000000 | F16: =Data!L16 -> 15523134000000 | G16: =IFERROR(E16/F16,0) -> 0.10065087
D17: 2018 | E17: =Data!N17 -> 1065313000000 | F17: =Data!L17 -> 12786352000000 | G17: =IFERROR(E17/F17,0) -> 0.083316414
D18: 2019 | E18: =Data!N18 -> 2104310000000 | F18: =Data!L18 -> 15545577000000 | G18: =IFERROR(E18/F18,0) -> 0.1353639
D19: 2020 | E19: =Data!N19 -> -410562000000 | F19: =Data!L19 -> 15658951000000 | G19: =IFERROR(E19/F19,0) -> -0.026218998
D20: 2021 | E20: =Data!N20 -> -586757000000 | F20: =Data!L20 -> 15671921000000 | G20: =IFERROR(E20/F20,0) -> -0.037440018
D21: 2022 | E21: =Data!N21 -> -785208000000 | F21: =Data!L21 -> 11948182000000 | G21: =IFERROR(E21/F21,0) -> -0.06571778
D22: 2023 | E22: =Data!N22 -> 876769000000 | F22: =Data!L22 -> 12931853000000 | G22: =IFERROR(E22/F22,0) -> 0.067799178
D23: 2024 | E23: =Data!N23 -> 1419919000000 | F23: =Data!L23 -> 10095098000000 | G23: =IFERROR(E23/F23,0) -> 0.14065431
B24: 3 | C24: PT Asuransi Allianz Life Indonesia | D24: 2014 | E24: =Data!N24 -> 0 | F24: =Data!L24 -> 12354658000000 | G24: =IFERROR(E24/F24,0) -> 0
D25: 2015 | E25: =Data!N25 -> 806099000000 | F25: =Data!L25 -> 8593467000000 | G25: =IFERROR(E25/F25,0) -> 0.0938037
D26: 2016 | E26: =Data!N26 -> 899890000000 | F26: =Data!L26 -> 11372680000000 | G26: =IFERROR(E26/F26,0) -> 0.079127347
D27: 2017 | E27: =Data!N27 -> 649699000000 | F27: =Data!L27 -> 13302120000000 | G27: =IFERROR(E27/F27,0) -> 0.048841764
D28: 2018 | E28: =Data!N28 -> 137111000000 | F28: =Data!L28 -> 10531156000000 | G28: =IFERROR(E28/F28,0) -> 0.013019558
D29: 2019 | E29: =Data!N29 -> 1493224000000 | F29: =Data!L29 -> 15153459000000 | G29: =IFERROR(E29/F29,0) -> 0.098540142
D30: 2020 | E30: =Data!N30 -> 1129656000000 | F30: =Data!L30 -> 18812789000000 | G30: =IFERROR(E30/F30,0) -> 0.060047237
D31: 2021 | E31: =Data!N31 -> 404045000000 | F31: =Data!L31 -> 20725660000000 | G31: =IFERROR(E31/F31,0) -> 0.019494916
D32: 2022 | E32: =Data!N32 -> 107318000000 | F32: =Data!L32 -> 14203983000000 | G32: =IFERROR(E32/F32,0) -> 0.0075554864
D33: 2023 | E33: =Data!N33 -> 481260000000 | F33: =Data!L33 -> 17375945000000 | G33: =IFERROR(E33/F33,0) -> 0.027696911
D34: 2024 | E34: =Data!N34 -> 961867000000 | F34: =Data!L34 -> 18185132000000 | G34: =IFERROR(E34/F34,0) -> 0.052893045
B35: 4 | C35: PT Asuransi Allianz Life Syariah Indonesia | D35: 2014 | E35: =Data!N35 -> 0 | F35: =Data!L35 -> 0 | G35: =IFERROR(E35/F35,0) -> 0
D36: 2015 | E36: =Data!N36 -> 0 | F36: =Data!L36 -> 0 | G36: =IFERROR(E36/F36,0) -> 0
D37: 2016 | E37: =Data!N37 -> 0 | F37: =Data!L37 -> 0 | G37: =IFERROR(E37/F37,0) -> 0
D38: 2017 | E38: =Data!N38 -> 0 | F38: =Data!L38 -> 0 | G38: =IFERROR(E38/F38,0) -> 0
D39: 2018 | E39: =Data!N39 -> 0 | F39: =Data!L39 -> 0 | G39: =IFERROR(E39/F39,0) -> 0
D40: 2019 | E40: =Data!N40 -> 0 | F40: =Data!L40 -> 0 | G40: =IFERROR(E40/F40,0) -> 0
D41: 2020 | E41: =Data!N41 -> 0 | F41: =Data!L41 -> 0 | G41: =IFERROR(E41/F41,0) -> 0
D42: 2021 | E42: =Data!N42 -> 0 | F42: =Data!L42 -> 0 | G42: =IFERROR(E42/F42,0) -> 0
D43: 2022 | E43: =Data!N43 -> 382661000000 | F43: =Data!L43 -> 1070003000000 | G43: =IFERROR(E43/F43,0) -> 0.3576261
D44: 2023 | E44: =Data!N44 -> 232895000000 | F44: =Data!L44 -> 1217667000000 | G44: =IFERROR(E44/F44,0) -> 0.19126329
D45: 2024 | E45: =Data!N45 -> 58584000000 | F45: =Data!L45 -> 1130418000000 | G45: =IFERROR(E45/F45,0) -> 0.051825077
B46: 5 | C46: PT Asuransi BRI Life | D46: 2014 | E46: =Data!N46 -> 0 | F46: =Data!L46 -> 0 | G46: =IFERROR(E46/F46,0) -> 0
D47: 2015 | E47: =Data!N47 -> 0 | F47: =Data!L47 -> 0 | G47: =IFERROR(E47/F47,0) -> 0
D48: 2016 | E48: =Data!N48 -> 331486312000 | F48: =Data!L48 -> 3542155857000 | G48: =IFERROR(E48/F48,0) -> 0.093583209
D49: 2017 | E49: =Data!N49 -> 538226085000 | F49: =Data!L49 -> 4403365381000 | G49: =IFERROR(E49/F49,0) -> 0.12223062
D50: 2018 | E50: =Data!N50 -> 291908712000 | F50: =Data!L50 -> 4872269263000 | G50: =IFERROR(E50/F50,0) -> 0.05991227
D51: 2019 | E51: =Data!N51 -> 452204000000 | F51: =Data!L51 -> 5671048000000 | G51: =IFERROR(E51/F51,0) -> 0.079739054
D52: 2020 | E52: =Data!N52 -> 230074000000 | F52: =Data!L52 -> 6379851000000 | G52: =IFERROR(E52/F52,0) -> 0.036062598
D53: 2021 | E53: =Data!N53 -> 39099000000 | F53: =Data!L53 -> 7264440000000 | G53: =IFERROR(E53/F53,0) -> 0.0053822456
D54: 2022 | E54: =Data!N54 -> 283472000000 | F54: =Data!L54 -> 9141344000000 | G54: =IFERROR(E54/F54,0) -> 0.031009882
D55: 2023 | E55: =Data!N55 -> 634959000000 | F55: =Data!L55 -> 9194450000000 | G55: =IFERROR(E55/F55,0) -> 0.069058943
D56: 2024 | E56: =Data!N56 -> 0 | F56: =Data!L56 -> 0 | G56: =IFERROR(E56/F56,0) -> 0
B57: 6 | C57: PT Asuransi Ciputra Indonesia | D57: 2014 | E57: =Data!N57 -> 0 | F57: =Data!L57 -> 0 | G57: =IFERROR(E57/F57,0) -> 0
D58: 2015 | E58: =Data!N58 -> 0 | F58: =Data!L58 -> 0 | G58: =IFERROR(E58/F58,0) -> 0
D59: 2016 | E59: =Data!N59 -> -4909000000 | F59: =Data!L59 -> 3041000000 | G59: =IFERROR(E59/F59,0) -> -1.6142716
D60: 2017 | E60: =Data!N60 -> -19772000000 | F60: =Data!L60 -> 13468000000 | G60: =IFERROR(E60/F60,0) -> -1.4680725
D61: 2018 | E61: =Data!N61 -> -43131000000 | F61: =Data!L61 -> 59888000000 | G61: =IFERROR(E61/F61,0) -> -0.72019436
D62: 2019 | E62: =Data!N62 -> -45250000000 | F62: =Data!L62 -> 104287000000 | G62: =IFERROR(E62/F62,0) -> -0.43389876
D63: 2020 | E63: =Data!N63 -> -36955000000 | F63: =Data!L63 -> 110130000000 | G63: =IFERROR(E63/F63,0) -> -0.33555798
D64: 2021 | E64: =Data!N64 -> -52914000000 | F64: =Data!L64 -> 244885000000 | G64: =IFERROR(E64/F64,0) -> -0.21607693
D65: 2022 | E65: =Data!N65 -> 460000000 | F65: =Data!L65 -> 334681000000 | G65: =IFERROR(E65/F65,0) -> 0.0013744431
D66: 2023 | E66: =Data!N66 -> 8447000000 | F66: =Data!L66 -> 467731000000 | G66: =IFERROR(E66/F66,0) -> 0.018059526
D67: 2024 | E67: =Data!N67 -> 35110000000 | F67: =Data!L67 -> 587025000000 | G67: =IFERROR(E67/F67,0) -> 0.059810059
B68: 7 | C68: PT Asuransi Jiwa Astra | D68: 2014 | E68: =Data!N68 -> 0 | F68: =Data!L68 -> 613328000000 | G68: =IFERROR(E68/F68,0) -> 0
D69: 2015 | E69: =Data!N69 -> -177698000000 | F69: =Data!L69 -> 1310956000000 | G69: =IFERROR(E69/F69,0) -> -0.13554841
D70: 2016 | E70: =Data!N70 -> -268101000000 | F70: =Data!L70 -> 2981581000000 | G70: =IFERROR(E70/F70,0) -> -0.089919073
D71: 2017 | E71: =Data!N71 -> -255572000000 | F71: =Data!L71 -> 3796659000000 | G71: =IFERROR(E71/F71,0) -> -0.067314974
D72: 2018 | E72: =Data!N72 -> -177053000000 | F72: =Data!L72 -> 3611633000000 | G72: =IFERROR(E72/F72,0) -> -0.049022977
D73: 2019 | E73: =Data!N73 -> -77232000000 | F73: =Data!L73 -> 3346426000000 | G73: =IFERROR(E73/F73,0) -> -0.02307895
D74: 2020 | E74: =Data!N74 -> -16497000000 | F74: =Data!L74 -> 3645793000000 | G74: =IFERROR(E74/F74,0) -> -0.0045249415
D75: 2021 | E75: =Data!N75 -> -13860000000 | F75: =Data!L75 -> 5769733000000 | G75: =IFERROR(E75/F75,0) -> -0.0024021909
D76: 2022 | E76: =Data!N76 -> -143113000000 | F76: =Data!L76 -> 5918222000000 | G76: =IFERROR(E76/F76,0) -> -0.024181756
D77: 2023 | E77: =Data!N77 -> 15952000000 | F77: =Data!L77 -> 6350888000000 | G77: =IFERROR(E77/F77,0) -> 0.0025117747
D78: 2024 | E78: =Data!N78 -> 49115000000 | F78: =Data!L78 -> 5855479000000 | G78: =IFERROR(E78/F78,0) -> 0.0083878706
B79: 8 | C79: PT Asuransi Jiwa BCA | D79: 2014 | E79: =Data!N79 -> 0 | F79: =Data!L79 -> 17340000000 | G79: =IFERROR(E79/F79,0) -> 0
D80: 2015 | E80: =Data!N80 -> -27031000000 | F80: =Data!L80 -> 108628000000 | G80: =IFERROR(E80/F80,0) -> -0.24884008
D81: 2016 | E81: =Data!N81 -> -24158000000 | F81: =Data!L81 -> 289387000000 | G81: =IFERROR(E81/F81,0) -> -0.083479908
D82: 2017 | E82: =Data!N82 -> -37565000000 | F82: =Data!L82 -> 445563000000 | G82: =IFERROR(E82/F82,0) -> -0.084309065
D83: 2018 | E83: =Data!N83 -> -78803000000 | F83: =Data!L83 -> 585605000000 | G83: =IFERROR(E83/F83,0) -> -0.13456682
D84: 2019 | E84: =Data!N84 -> 12855000000 | F84: =Data!L84 -> 800269000000 | G84: =IFERROR(E84/F84,0) -> 0.016063349
D85: 2020 | E85: =Data!N85 -> 91530000000 | F85: =Data!L85 -> 991129000000 | G85: =IFERROR(E85/F85,0) -> 0.09234923
D86: 2021 | E86: =Data!N86 -> 40152000000 | F86: =Data!L86 -> 1316137000000 | G86: =IFERROR(E86/F86,0) -> 0.030507462
D87: 2022 | E87: =Data!N87 -> 51764000000 | F87: =Data!L87 -> 1382687000000 | G87: =IFERROR(E87/F87,0) -> 0.037437251
D88: 2023 | E88: =Data!N88 -> 71227000000 | F88: =Data!L88 -> 1576409000000 | G88: =IFERROR(E88/F88,0) -> 0.045183071
D89: 2024 | E89: =Data!N89 -> 83571000000 | F89: =Data!L89 -> 1481484000000 | G89: =IFERROR(E89/F89,0) -> 0.056410329
B90: 9 | C90: PT Asuransi Jiwa Central Asia Raya | D90: 2014 | E90: =Data!N90 -> 0 | F90: =Data!L90 -> 1111447000000 | G90: =IFERROR(E90/F90,0) -> 0
D91: 2015 | E91: =Data!N91 -> -187450000000 | F91: =Data!L91 -> 1157281000000 | G91: =IFERROR(E91/F91,0) -> -0.16197449
D92: 2016 | E92: =Data!N92 -> 201331000000 | F92: =Data!L92 -> 1932573000000 | G92: =IFERROR(E92/F92,0) -> 0.10417769
D93: 2017 | E93: =Data!N93 -> -590339000000 | F93: =Data!L93 -> 2584123000000 | G93: =IFERROR(E93/F93,0) -> -0.22844849
D94: 2018 | E94: =Data!N94 -> 175397000000 | F94: =Data!L94 -> 2626306000000 | G94: =IFERROR(E94/F94,0) -> 0.066784678
D95: 2019 | E95: =Data!N95 -> 396160000000 | F95: =Data!L95 -> 3015912000000 | G95: =IFERROR(E95/F95,0) -> 0.13135662
D96: 2020 | E96: =Data!N96 -> 70612000000 | F96: =Data!L96 -> 2727108000000 | G96: =IFERROR(E96/F96,0) -> 0.025892631
D97: 2021 | E97: =Data!N97 -> 1154523000000 | F97: =Data!L97 -> 2794098000000 | G97: =IFERROR(E97/F97,0) -> 0.41320061
D98: 2022 | E98: =Data!N98 -> 158806000000 | F98: =Data!L98 -> 2587182000000 | G98: =IFERROR(E98/F98,0) -> 0.061381843
D99: 2023 | E99: =Data!N99 -> 107690000000 | F99: =Data!L99 -> 2996848000000 | G99: =IFERROR(E99/F99,0) -> 0.035934422
D100: 2024 | E100: =Data!N100 -> 277265000000 | F100: =Data!L100 -> 2435099000000 | G100: =IFERROR(E100/F100,0) -> 0.1138619
...

Sheet ROA
A1: Sub Sektor | B1: No | C1: Nama Perusahaan | D1: Tahun | E1: Laba Bersih | F1: Total Aset | G1: Retun on Asset
A2: Asuransi Jiwa | B2: 1 | C2: Asuransi Jiwa Bersama Bumiputera 1912 | D2: 2014 | E2: =Data!N2 -> 0 | F2: =Data!G2 -> 0 | G2: =IFERROR(E2/F2,0) -> 0
D3: 2015 | E3: =Data!N3 -> 0 | F3: =Data!G3 -> 0 | G3: =IFERROR(E3/F3,0) -> 0
D4: 2016 | E4: =Data!N4 -> 0 | F4: =Data!G4 -> 0 | G4: =IFERROR(E4/F4,0) -> 0
D5: 2017 | E5: =Data!N5 -> 0 | F5: =Data!G5 -> 0 | G5: =IFERROR(E5/F5,0) -> 0
D6: 2018 | E6: =Data!N6 -> 0 | F6: =Data!G6 -> 0 | G6: =IFERROR(E6/F6,0) -> 0
D7: 2019 | E7: =Data!N7 -> 0 | F7: =Data!G7 -> 0 | G7: =IFERROR(E7/F7,0) -> 0
D8: 2020 | E8: =Data!N8 -> 0 | F8: =Data!G8 -> 0 | G8: =IFERROR(E8/F8,0) -> 0
D9: 2021 | E9: =Data!N9 -> 0 | F9: =Data!G9 -> 0 | G9: =IFERROR(E9/F9,0) -> 0
D10: 2022 | E10: =Data!N10 -> 0 | F10: =Data!G10 -> 0 | G10: =IFERROR(E10/F10,0) -> 0
D11: 2023 | E11: =Data!N11 -> 0 | F11: =Data!G11 -> 0 | G11: =IFERROR(E11/F11,0) -> 0
D12: 2024 | E12: =Data!N12 -> 0 | F12: =Data!G12 -> 0 | G12: =IFERROR(E12/F12,0) -> 0
B13: 2 | C13: PT AIA Financial | D13: 2014 | E13: =Data!N13 -> 0 | F13: =Data!G13 -> 0 | G13: =IFERROR(E13/F13,0) -> 0
D14: 2015 | E14: =Data!N14 -> 848437000000 | F14: =Data!G14 -> 31860954000000 | G14: =IFERROR(E14/F14,0) -> 0.026629366
D15: 2016 | E15: =Data!N15 -> 1197111000000 | F15: =Data!G15 -> 35767906000000 | G15: =IFERROR(E15/F15,0) -> 0.033468859
D16: 2017 | E16: =Data!N16 -> 1562417000000 | F16: =Data!G16 -> 44937292000000 | G16: =IFERROR(E16/F16,0) -> 0.034768829
D17: 2018 | E17: =Data!N17 -> 1065313000000 | F17: =Data!G17 -> 46562563000000 | G17: =IFERROR(E17/F17,0) -> 0.022879174
D18: 2019 | E18: =Data!N18 -> 2104310000000 | F18: =Data!G18 -> 50043024000000 | G18: =IFERROR(E18/F18,0) -> 0.042050017
D19: 2020 | E19: =Data!N19 -> -410562000000 | F19: =Data!G19 -> 53134780000000 | G19: =IFERROR(E19/F19,0) -> -0.0077268034
D20: 2021 | E20: =Data!N20 -> -586757000000 | F20: =Data!G20 -> 52330016000000 | G20: =IFERROR(E20/F20,0) -> -0.011212628
D21: 2022 | E21: =Data!N21 -> -785208000000 | F21: =Data!G21 -> 44912325000000 | G21: =IFERROR(E21/F21,0) -> -0.01748313
D22: 2023 | E22: =Data!N22 -> 876769000000 | F22: =Data!G22 -> 41785302000000 | G22: =IFERROR(E22/F22,0) -> 0.020982713
D23: 2024 | E23: =Data!N23 -> 1419919000000 | F23: =Data!G23 -> 39899482000000 | G23: =IFERROR(E23/F23,0) -> 0.035587404
B24: 3 | C24: PT Asuransi Allianz Life Indonesia | D24: 2014 | E24: =Data!N24 -> 0 | F24: =Data!G24 -> 0 | G24: =IFERROR(E24/F24,0) -> 0
D25: 2015 | E25: =Data!N25 -> 806099000000 | F25: =Data!G25 -> 27635118000000 | G25: =IFERROR(E25/F25,0) -> 0.029169371
D26: 2016 | E26: =Data!N26 -> 899890000000 | F26: =Data!G26 -> 30294789000000 | G26: =IFERROR(E26/F26,0) -> 0.029704449
D27: 2017 | E27: =Data!N27 -> 649699000000 | F27: =Data!G27 -> 35751863000000 | G27: =IFERROR(E27/F27,0) -> 0.018172452
D28: 2018 | E28: =Data!N28 -> 137111000000 | F28: =Data!G28 -> 35266933000000 | G28: =IFERROR(E28/F28,0) -> 0.0038878062
D29: 2019 | E29: =Data!N29 -> 1493224000000 | F29: =Data!G29 -> 38345233000000 | G29: =IFERROR(E29/F29,0) -> 0.038941581
D30: 2020 | E30: =Data!N30 -> 1129656000000 | F30: =Data!G30 -> 41166712000000 | G30: =IFERROR(E30/F30,0) -> 0.027441006
D31: 2021 | E31: =Data!N31 -> 404045000000 | F31: =Data!G31 -> 42808931000000 | G31: =IFERROR(E31/F31,0) -> 0.0094383343
D32: 2022 | E32: =Data!N32 -> 107318000000 | F32: =Data!G32 -> 41194961000000 | G32: =IFERROR(E32/F32,0) -> 0.0026051244
D33: 2023 | E33: =Data!N33 -> 481260000000 | F33: =Data!G33 -> 40147448000000 | G33: =IFERROR(E33/F33,0) -> 0.011987312
D34: 2024 | E34: =Data!N34 -> 961867000000 | F34: =Data!G34 -> 39131978000000 | G34: =IFERROR(E34/F34,0) -> 0.024580076
B35: 4 | C35: PT Asuransi Allianz Life Syariah Indonesia | D35: 2014 | E35: =Data!N35 -> 0 | F35: =Data!G35 -> 0 | G35: =IFERROR(E35/F35,0) -> 0
D36: 2015 | E36: =Data!N36 -> 0 | F36: =Data!G36 -> 0 | G36: =IFERROR(E36/F36,0) -> 0
D37: 2016 | E37: =Data!N37 -> 0 | F37: =Data!G37 -> 0 | G37: =IFERROR(E37/F37,0) -> 0
D38: 2017 | E38: =Data!N38 -> 0 | F38: =Data!G38 -> 0 | G38: =IFERROR(E38/F38,0) -> 0
D39: 2018 | E39: =Data!N39 -> 0 | F39: =Data!G39 -> 0 | G39: =IFERROR(E39/F39,0) -> 0
D40: 2019 | E40: =Data!N40 -> 0 | F40: =Data!G40 -> 0 | G40: =IFERROR(E40/F40,0) -> 0
D41: 2020 | E41: =Data!N41 -> 0 | F41: =Data!G41 -> 0 | G41: =IFERROR(E41/F41,0) -> 0
D42: 2021 | E42: =Data!N42 -> 0 | F42: =Data!G42 -> 0 | G42: =IFERROR(E42/F42,0) -> 0
D43: 2022 | E43: =Data!N43 -> 382661000000 | F43: =Data!G43 -> 4337827000000 | G43: =IFERROR(E43/F43,0) -> 0.088214906
D44: 2023 | E44: =Data!N44 -> 232895000000 | F44: =Data!G44 -> 3620310000000 | G44: =IFERROR(E44/F44,0) -> 0.064330126
D45: 2024 | E45: =Data!N45 -> 58584000000 | F45: =Data!G45 -> 3339322000000 | G45: =IFERROR(E45/F45,0) -> 0.017543681
B46: 5 | C46: PT Asuransi BRI Life | D46: 2014 | E46: =Data!N46 -> 0 | F46: =Data!G46 -> 0 | G46: =IFERROR(E46/F46,0) -> 0
D47: 2015 | E47: =Data!N47 -> 0 | F47: =Data!G47 -> 4933308738000 | G47: =IFERROR(E47/F47,0) -> 0
D48: 2016 | E48: =Data!N48 -> 331486312000 | F48: =Data!G48 -> 6176329027000 | G48: =IFERROR(E48/F48,0) -> 0.053670443
D49: 2017 | E49: =Data!N49 -> 538226085000 | F49: =Data!E49 -> 51803533000 | G49: =IFERROR(E49/F49,0) -> 10.389756
D50: 2018 | E50: =Data!N50 -> 291908712000 | F50: =Data!G50 -> 9356504263000 | G50: =IFERROR(E50/F50,0) -> 0.03119848
D51: 2019 | E51: =Data!N51 -> 452204000000 | F51: =Data!G51 -> 11084971000000 | G51: =IFERROR(E51/F51,0) -> 0.040794333
D52: 2020 | E52: =Data!N52 -> 230074000000 | F52: =Data!G52 -> 13044264000000 | G52: =IFERROR(E52/F52,0) -> 0.017637944
D53: 2021 | E53: =Data!N53 -> 39099000000 | F53: =Data!G53 -> 18260736000000 | G53: =IFERROR(E53/F53,0) -> 0.0021411514
D54: 2022 | E54: =Data!N54 -> 283472000000 | F54: =Data!G54 -> 21494817000000 | G54: =IFERROR(E54/F54,0) -> 0.013187923
D55: 2023 | E55: =Data!N55 -> 634959000000 | F55: =Data!G55 -> 23552167000000 | G55: =IFERROR(E55/F55,0) -> 0.026959685
D56: 2024 | E56: =Data!N56 -> 0 | F56: =Data!G56 -> 0 | G56: =IFERROR(E56/F56,0) -> 0
B57: 6 | C57: PT Asuransi Ciputra Indonesia | D57: 2014 | E57: =Data!N57 -> 0 | F57: =Data!G57 -> 0 | G57: =IFERROR(E57/F57,0) -> 0
D58: 2015 | E58: =Data!N58 -> 0 | F58: =Data!G58 -> 0 | G58: =IFERROR(E58/F58,0) -> 0
D59: 2016 | E59: =Data!N59 -> -4909000000 | F59: =Data!G59 -> 98507000000 | G59: =IFERROR(E59/F59,0) -> -0.049834022
D60: 2017 | E60: =Data!N60 -> -19772000000 | F60: =Data!G60 -> 116479000000 | G60: =IFERROR(E60/F60,0) -> -0.16974734
D61: 2018 | E61: =Data!N61 -> -43131000000 | F61: =Data!G61 -> 152680000000 | G61: =IFERROR(E61/F61,0) -> -0.2824928
D62: 2019 | E62: =Data!N62 -> -45250000000 | F62: =Data!G62 -> 214472000000 | G62: =IFERROR(E62/F62,0) -> -0.21098325
D63: 2020 | E63: =Data!N63 -> -36955000000 | F63: =Data!G63 -> 278255000000 | G63: =IFERROR(E63/F63,0) -> -0.13280983
D64: 2021 | E64: =Data!N64 -> -52914000000 | F64: =Data!G64 -> 384372000000 | G64: =IFERROR(E64/F64,0) -> -0.13766351
D65: 2022 | E65: =Data!N65 -> 460000000 | F65: =Data!G65 -> 517439000000 | G65: =IFERROR(E65/F65,0) -> 0.00088899368
D66: 2023 | E66: =Data!N66 -> 8447000000 | F66: =Data!G66 -> 714057000000 | G66: =IFERROR(E66/F66,0) -> 0.011829588
D67: 2024 | E67: =Data!N67 -> 35110000000 | F67: =Data!G67 -> 997332000000 | G67: =IFERROR(E67/F67,0) -> 0.035203924
B68: 7 | C68: PT Asuransi Jiwa Astra | D68: 2014 | E68: =Data!N68 -> 0 | F68: =Data!G68 -> 0 | G68: =IFERROR(E68/F68,0) -> 0
D69: 2015 | E69: =Data!N69 -> -177698000000 | F69: =Data!G69 -> 1899837000000 | G69: =IFERROR(E69/F69,0) -> -0.093533287
D70: 2016 | E70: =Data!N70 -> -268101000000 | F70: =Data!G70 -> 3802688000000 | G70: =IFERROR(E70/F70,0) -> -0.070503023
D71: 2017 | E71: =Data!N71 -> -255572000000 | F71: =Data!G71 -> 4315435000000 | G71: =IFERROR(E71/F71,0) -> -0.059222767
D72: 2018 | E72: =Data!N72 -> -177053000000 | F72: =Data!G72 -> 5004717000000 | G72: =IFERROR(E72/F72,0) -> -0.035377225
D73: 2019 | E73: =Data!N73 -> -77232000000 | F73: =Data!G73 -> 5901298000000 | G73: =IFERROR(E73/F73,0) -> -0.01308729
D74: 2020 | E74: =Data!N74 -> -16497000000 | F74: =Data!G74 -> 6587066000000 | G74: =IFERROR(E74/F74,0) -> -0.0025044534
D75: 2021 | E75: =Data!N75 -> -13860000000 | F75: =Data!G75 -> 7092935000000 | G75: =IFERROR(E75/F75,0) -> -0.0019540571
D76: 2022 | E76: =Data!N76 -> -143113000000 | F76: =Data!G76 -> 7345755000000 | G76: =IFERROR(E76/F76,0) -> -0.019482409
D77: 2023 | E77: =Data!N77 -> 15952000000 | F77: =Data!G77 -> 7501061000000 | G77: =IFERROR(E77/F77,0) -> 0.0021266325
D78: 2024 | E78: =Data!N78 -> 49115000000 | F78: =Data!G78 -> 6806055000000 | G78: =IFERROR(E78/F78,0) -> 0.0072163684
B79: 8 | C79: PT Asuransi Jiwa BCA | D79: 2014 | E79: =Data!N79 -> 0 | F79: =Data!G79 -> 0 | G79: =IFERROR(E79/F79,0) -> 0
D80: 2015 | E80: =Data!N80 -> -27031000000 | F80: =Data!G80 -> 281282000000 | G80: =IFERROR(E80/F80,0) -> -0.096099288
D81: 2016 | E81: =Data!N81 -> -24158000000 | F81: =Data!G81 -> 385447000000 | G81: =IFERROR(E81/F81,0) -> -0.062675284
D82: 2017 | E82: =Data!N82 -> -37565000000 | F82: =Data!G82 -> 842122000000 | G82: =IFERROR(E82/F82,0) -> -0.044607551
D83: 2018 | E83: =Data!N83 -> -78803000000 | F83: =Data!G83 -> 902876000000 | G83: =IFERROR(E83/F83,0) -> -0.087279981
D84: 2019 | E84: =Data!N84 -> 12855000000 | F84: =Data!G84 -> 1154689000000 | G84: =IFERROR(E84/F84,0) -> 0.011132868
D85: 2020 | E85: =Data!N85 -> 91530000000 | F85: =Data!G85 -> 1467896000000 | G85: =IFERROR(E85/F85,0) -> 0.062354554
D86: 2021 | E86: =Data!N86 -> 40152000000 | F86: =Data!G86 -> 1930213000000 | G86: =IFERROR(E86/F86,0) -> 0.020801849
D87: 2022 | E87: =Data!N87 -> 51764000000 | F87: =Data!G87 -> 2347921000000 | G87: =IFERROR(E87/F87,0) -> 0.022046738
D88: 2023 | E88: =Data!N88 -> 71227000000 | F88: =Data!G88 -> 2878724000000 | G88: =IFERROR(E88/F88,0) -> 0.02474256
D89: 2024 | E89: =Data!N89 -> 83571000000 | F89: =Data!G89 -> 3339666000000 | G89: =IFERROR(E89/F89,0) -> 0.02502376
B90: 9 | C90: PT Asuransi Jiwa Central Asia Raya | D90: 2014 | E90: =Data!N90 -> 0 | F90: =Data!G90 -> 0 | G90: =IFERROR(E90/F90,0) -> 0
D91: 2015 | E91: =Data!N91 -> -187450000000 | F91: =Data!G91 -> 4598462000000 | G91: =IFERROR(E91/F91,0) -> -0.040763629
D92: 2016 | E92: =Data!N92 -> 201331000000 | F92: =Data!G92 -> 5298273000000 | G92: =IFERROR(E92/F92,0) -> 0.037999363
D93: 2017 | E93: =Data!N93 -> -590339000000 | F93: =Data!G93 -> 5618666000000 | G93: =IFERROR(E93/F93,0) -> -0.10506747
D94: 2018 | E94: =Data!N94 -> 175397000000 | F94: =Data!G94 -> 6696353000000 | G94: =IFERROR(E94/F94,0) -> 0.026192914
D95: 2019 | E95: =Data!N95 -> 396160000000 | F95: =Data!G95 -> 8158087000000 | G95: =IFERROR(E95/F95,0) -> 0.048560404
D96: 2020 | E96: =Data!N96 -> 70612000000 | F96: =Data!G96 -> 8569933000000 | G96: =IFERROR(E96/F96,0) -> 0.0082395043
D97: 2021 | E97: =Data!N97 -> 1154523000000 | F97: =Data!G97 -> 10111397000000 | G97: =IFERROR(E97/F97,0) -> 0.11418036
D98: 2022 | E98: =Data!N98 -> 158806000000 | F98: =Data!G98 -> 10357588000000 | G98: =IFERROR(E98/F98,0) -> 0.015332334
D99: 2023 | E99: =Data!N99 -> 107690000000 | F99: =Data!G99 -> 11033985000000 | G99: =IFERROR(E99/F99,0) -> 0.0097598465
D100: 2024 | E100: =Data!N100 -> 277265000000 | F100: =Data!G100 -> 11181540000000 | G100: =IFERROR(E100/F100,0) -> 0.024796674
...

Sheet ROE
A1: Sub Sektor | B1: No | C1: Nama Perusahaan | D1: Tahun | E1: Laba Bersih | F1: Total Ekuitas | G1: Retun on Equity
A2: Asuransi Jiwa | B2: 1 | C2: Asuransi Jiwa Bersama Bumiputera 1912 | D2: 2014 | E2: =Data!N2 -> 0 | F2: =Data!K2 -> 0 | G2: =IFERROR(E2/F2,0) -> 0
D3: 2015 | E3: =Data!N3 -> 0 | F3: =Data!K3 -> 0 | G3: =IFERROR(E3/F3,0) -> 0
D4: 2016 | E4: =Data!N4 -> 0 | F4: =Data!K4 -> 0 | G4: =IFERROR(E4/F4,0) -> 0
D5: 2017 | E5: =Data!N5 -> 0 | F5: =Data!K5 -> 0 | G5: =IFERROR(E5/F5,0) -> 0
D6: 2018 | E6: =Data!N6 -> 0 | F6: =Data!K6 -> 0 | G6: =IFERROR(E6/F6,0) -> 0
D7: 2019 | E7: =Data!N7 -> 0 | F7: =Data!K7 -> 0 | G7: =IFERROR(E7/F7,0) -> 0
D8: 2020 | E8: =Data!N8 -> 0 | F8: =Data!K8 -> 0 | G8: =IFERROR(E8/F8,0) -> 0
D9: 2021 | E9: =Data!N9 -> 0 | F9: =Data!K9 -> 0 | G9: =IFERROR(E9/F9,0) -> 0
D10: 2022 | E10: =Data!N10 -> 0 | F10: =Data!K10 -> 0 | G10: =IFERROR(E10/F10,0) -> 0
D11: 2023 | E11: =Data!N11 -> 0 | F11: =Data!K11 -> 0 | G11: =IFERROR(E11/F11,0) -> 0
D12: 2024 | E12: =Data!N12 -> 0 | F12: =Data!K12 -> 0 | G12: =IFERROR(E12/F12,0) -> 0
B13: 2 | C13: PT AIA Financial | D13: 2014 | E13: =Data!N13 -> 0 | F13: =Data!K13 -> 0 | G13: =IFERROR(E13/F13,0) -> 0
D14: 2015 | E14: =Data!N14 -> 848437000000 | F14: =Data!K14 -> 6569253000000 | G14: =IFERROR(E14/F14,0) -> 0.12915274
D15: 2016 | E15: =Data!N15 -> 1197111000000 | F15: =Data!K15 -> 7766364000000 | G15: =IFERROR(E15/F15,0) -> 0.15414047
D16: 2017 | E16: =Data!N16 -> 1562417000000 | F16: =Data!K16 -> 10561914000000 | G16: =IFERROR(E16/F16,0) -> 0.14792934
D17: 2018 | E17: =Data!N17 -> 1065313000000 | F17: =Data!K17 -> 11027227000000 | G17: =IFERROR(E17/F17,0) -> 0.096607515
D18: 2019 | E18: =Data!N18 -> 2104310000000 | F18: =Data!K18 -> 11870589000000 | G18: =IFERROR(E18/F18,0) -> 0.1772709
D19: 2020 | E19: =Data!N19 -> -410562000000 | F19: =Data!K19 -> 11761575000000 | G19: =IFERROR(E19/F19,0) -> -0.03490706
D20: 2021 | E20: =Data!N20 -> -586757000000 | F20: =Data!K20 -> 11856333000000 | G20: =IFERROR(E20/F20,0) -> -0.04948891
D21: 2022 | E21: =Data!N21 -> -785208000000 | F21: =Data!K21 -> 8229889000000 | G21: =IFERROR(E21/F21,0) -> -0.095409306
D22: 2023 | E22: =Data!N22 -> 876769000000 | F22: =Data!K22 -> 8048626000000 | G22: =IFERROR(E22/F22,0) -> 0.108934
D23: 2024 | E23: =Data!N23 -> 1419919000000 | F23: =Data!K23 -> 8912301000000 | G23: =IFERROR(E23/F23,0) -> 0.15932126
B24: 3 | C24: PT Asuransi Allianz Life Indonesia | D24: 2014 | E24: =Data!N24 -> 0 | F24: =Data!K24 -> 0 | G24: =IFERROR(E24/F24,0) -> 0
D25: 2015 | E25: =Data!N25 -> 806099000000 | F25: =Data!K25 -> 4355995000000 | G25: =IFERROR(E25/F25,0) -> 0.18505508
D26: 2016 | E26: =Data!N26 -> 899890000000 | F26: =Data!K26 -> 5381290000000 | G26: =IFERROR(E26/F26,0) -> 0.1672257
D27: 2017 | E27: =Data!N27 -> 649699000000 | F27: =Data!K27 -> 6030989000000 | G27: =IFERROR(E27/F27,0) -> 0.10772678
D28: 2018 | E28: =Data!N28 -> 137111000000 | F28: =Data!K28 -> 5768100000000 | G28: =IFERROR(E28/F28,0) -> 0.023770566
D29: 2019 | E29: =Data!N29 -> 1493224000000 | F29: =Data!K29 -> 6511324000000 | G29: =IFERROR(E29/F29,0) -> 0.22932725
D30: 2020 | E30: =Data!N30 -> 1129656000000 | F30: =Data!K30 -> 7090980000000 | G30: =IFERROR(E30/F30,0) -> 0.15930887
D31: 2021 | E31: =Data!N31 -> 404045000000 | F31: =Data!K31 -> 6945025000000 | G31: =IFERROR(E31/F31,0) -> 0.058177616
D32: 2022 | E32: =Data!N32 -> 107318000000 | F32: =Data!K32 -> 7208812000000 | G32: =IFERROR(E32/F32,0) -> 0.014887058
D33: 2023 | E33: =Data!N33 -> 481260000000 | F33: =Data!K33 -> 6640072000000 | G33: =IFERROR(E33/F33,0) -> 0.07247813
D34: 2024 | E34: =Data!N34 -> 961867000000 | F34: =Data!K34 -> 7301939000000 | G34: =IFERROR(E34/F34,0) -> 0.13172761
B35: 4 | C35: PT Asuransi Allianz Life Syariah Indonesia | D35: 2014 | E35: =Data!N35 -> 0 | F35: =Data!K35 -> 0 | G35: =IFERROR(E35/F35,0) -> 0
D36: 2015 | E36: =Data!N36 -> 0 | F36: =Data!K36 -> 0 | G36: =IFERROR(E36/F36,0) -> 0
D37: 2016 | E37: =Data!N37 -> 0 | F37: =Data!K37 -> 0 | G37: =IFERROR(E37/F37,0) -> 0
D38: 2017 | E38: =Data!N38 -> 0 | F38: =Data!K38 -> 0 | G38: =IFERROR(E38/F38,0) -> 0
D39: 2018 | E39: =Data!N39 -> 0 | F39: =Data!K39 -> 0 | G39: =IFERROR(E39/F39,0) -> 0
D40: 2019 | E40: =Data!N40 -> 0 | F40: =Data!K40 -> 0 | G40: =IFERROR(E40/F40,0) -> 0
D41: 2020 | E41: =Data!N41 -> 0 | F41: =Data!K41 -> 0 | G41: =IFERROR(E41/F41,0) -> 0
D42: 2021 | E42: =Data!N42 -> 0 | F42: =Data!K42 -> 0 | G42: =IFERROR(E42/F42,0) -> 0
D43: 2022 | E43: =Data!N43 -> 382661000000 | F43: =Data!K43 -> 1497483000000 | G43: =IFERROR(E43/F43,0) -> 0.25553612
D44: 2023 | E44: =Data!N44 -> 232895000000 | F44: =Data!K44 -> 958124000000 | G44: =IFERROR(E44/F44,0) -> 0.24307397
D45: 2024 | E45: =Data!N45 -> 58584000000 | F45: =Data!K45 -> 968188000000 | G45: =IFERROR(E45/F45,0) -> 0.060508909
B46: 5 | C46: PT Asuransi BRI Life | D46: 2014 | E46: =Data!N46 -> 0 | F46: =Data!K46 -> 0 | G46: =IFERROR(E46/F46,0) -> 0
D47: 2015 | E47: =Data!N47 -> 0 | F47: =Data!K47 -> 4933308738000 | G47: =IFERROR(E47/F47,0) -> 0
D48: 2016 | E48: =Data!N48 -> 331486312000 | F48: =Data!K48 -> 6176329027000 | G48: =IFERROR(E48/F48,0) -> 0.053670443
D49: 2017 | E49: =Data!N49 -> 538226085000 | F49: =Data!K49 -> 2104006591000 | G49: =IFERROR(E49/F49,0) -> 0.25581008
D50: 2018 | E50: =Data!N50 -> 291908712000 | F50: =Data!K50 -> 2231804990000 | G50: =IFERROR(E50/F50,0) -> 0.1307949
D51: 2019 | E51: =Data!N51 -> 452204000000 | F51: =Data!K51 -> 2563929000000 | G51: =IFERROR(E51/F51,0) -> 0.1763715
D52: 2020 | E52: =Data!N52 -> 230074000000 | F52: =Data!K52 -> 2794003000000 | G52: =IFERROR(E52/F52,0) -> 0.082345652
D53: 2021 | E53: =Data!N53 -> 39099000000 | F53: =Data!K53 -> 6683102000000 | G53: =IFERROR(E53/F53,0) -> 0.0058504269
D54: 2022 | E54: =Data!N54 -> 283472000000 | F54: =Data!K54 -> 7706566000000 | G54: =IFERROR(E54/F54,0) -> 0.036783179
D55: 2023 | E55: =Data!N55 -> 634959000000 | F55: =Data!K55 -> 9111525000000 | G55: =IFERROR(E55/F55,0) -> 0.069687456
D56: 2024 | E56: =Data!N56 -> 0 | F56: =Data!K56 -> 0 | G56: =IFERROR(E56/F56,0) -> 0
B57: 6 | C57: PT Asuransi Ciputra Indonesia | D57: 2014 | E57: =Data!N57 -> 0 | F57: =Data!K57 -> 0 | G57: =IFERROR(E57/F57,0) -> 0
D58: 2015 | E58: =Data!N58 -> 0 | F58: =Data!K58 -> 0 | G58: =IFERROR(E58/F58,0) -> 0
D59: 2016 | E59: =Data!N59 -> -4909000000 | F59: =Data!K59 -> 95091000000 | G59: =IFERROR(E59/F59,0) -> -0.051624234
D60: 2017 | E60: =Data!N60 -> -19772000000 | F60: =Data!K60 -> 105319000000 | G60: =IFERROR(E60/F60,0) -> -0.18773441
D61: 2018 | E61: =Data!N61 -> -43131000000 | F61: =Data!K61 -> 102188000000 | G61: =IFERROR(E61/F61,0) -> -0.422075
D62: 2019 | E62: =Data!N62 -> -45250000000 | F62: =Data!K62 -> 126937000000 | G62: =IFERROR(E62/F62,0) -> -0.35647605
D63: 2020 | E63: =Data!N63 -> -36955000000 | F63: =Data!K63 -> 139982000000 | G63: =IFERROR(E63/F63,0) -> -0.26399823
D64: 2021 | E64: =Data!N64 -> -52914000000 | F64: =Data!K64 -> 132068000000 | G64: =IFERROR(E64/F64,0) -> -0.40065724
D65: 2022 | E65: =Data!N65 -> 460000000 | F65: =Data!K65 -> 157529000000 | G65: =IFERROR(E65/F65,0) -> 0.0029200973
D66: 2023 | E66: =Data!N66 -> 8447000000 | F66: =Data!K66 -> 165975000000 | G66: =IFERROR(E66/F66,0) -> 0.050893207
D67: 2024 | E67: =Data!N67 -> 35110000000 | F67: =Data!K67 -> 201086000000 | G67: =IFERROR(E67/F67,0) -> 0.17460191
B68: 7 | C68: PT Asuransi Jiwa Astra | D68: 2014 | E68: =Data!N68 -> 0 | F68: =Data!K68 -> 0 | G68: =IFERROR(E68/F68,0) -> 0
D69: 2015 | E69: =Data!N69 -> -177698000000 | F69: =Data!K69 -> 535556000000 | G69: =IFERROR(E69/F69,0) -> -0.33180097
D70: 2016 | E70: =Data!N70 -> -268101000000 | F70: =Data!K70 -> 837455000000 | G70: =IFERROR(E70/F70,0) -> -0.3201378
D71: 2017 | E71: =Data!N71 -> -255572000000 | F71: =Data!K71 -> 611883000000 | G71: =IFERROR(E71/F71,0) -> -0.41768116
D72: 2018 | E72: =Data!N72 -> -177053000000 | F72: =Data!K72 -> 434830000000 | G72: =IFERROR(E72/F72,0) -> -0.40717752
D73: 2019 | E73: =Data!N73 -> -77232000000 | F73: =Data!K73 -> 857598000000 | G73: =IFERROR(E73/F73,0) -> -0.09005618
D74: 2020 | E74: =Data!N74 -> -16497000000 | F74: =Data!K74 -> 840112000000 | G74: =IFERROR(E74/F74,0) -> -0.019636667
D75: 2021 | E75: =Data!N75 -> -13860000000 | F75: =Data!K75 -> 826251000000 | G75: =IFERROR(E75/F75,0) -> -0.016774564
D76: 2022 | E76: =Data!N76 -> -143113000000 | F76: =Data!K76 -> 683137000000 | G76: =IFERROR(E76/F76,0) -> -0.20949385
D77: 2023 | E77: =Data!N77 -> 15952000000 | F77: =Data!K77 -> 699090000000 | G77: =IFERROR(E77/F77,0) -> 0.022818235
D78: 2024 | E78: =Data!N78 -> 49115000000 | F78: =Data!K78 -> 748206000000 | G78: =IFERROR(E78/F78,0) -> 0.065643686
B79: 8 | C79: PT Asuransi Jiwa BCA | D79: 2014 | E79: =Data!N79 -> 0 | F79: =Data!K79 -> 0 | G79: =IFERROR(E79/F79,0) -> 0
D80: 2015 | E80: =Data!N80 -> -27031000000 | F80: =Data!K80 -> 228584000000 | G80: =IFERROR(E80/F80,0) -> -0.11825412
D81: 2016 | E81: =Data!N81 -> -24158000000 | F81: =Data!K81 -> 204426000000 | G81: =IFERROR(E81/F81,0) -> -0.11817479
D82: 2017 | E82: =Data!N82 -> -37565000000 | F82: =Data!K82 -> 466862000000 | G82: =IFERROR(E82/F82,0) -> -0.080462749
D83: 2018 | E83: =Data!N83 -> -78803000000 | F83: =Data!K83 -> 388058000000 | G83: =IFERROR(E83/F83,0) -> -0.20307016
D84: 2019 | E84: =Data!N84 -> 12855000000 | F84: =Data!K84 -> 400913000000 | G84: =IFERROR(E84/F84,0) -> 0.032064313
D85: 2020 | E85: =Data!N85 -> 91530000000 | F85: =Data!K85 -> 492443000000 | G85: =IFERROR(E85/F85,0) -> 0.18586923
D86: 2021 | E86: =Data!N86 -> 40152000000 | F86: =Data!K86 -> 532596000000 | G86: =IFERROR(E86/F86,0) -> 0.075389226
D87: 2022 | E87: =Data!N87 -> 51764000000 | F87: =Data!K87 -> 659360000000 | G87: =IFERROR(E87/F87,0) -> 0.07850643
D88: 2023 | E88: =Data!N88 -> 71227000000 | F88: =Data!K88 -> 730586000000 | G88: =IFERROR(E88/F88,0) -> 0.097492971
D89: 2024 | E89: =Data!N89 -> 83571000000 | F89: =Data!K89 -> 814158000000 | G89: =IFERROR(E89/F89,0) -> 0.10264715
B90: 9 | C90: PT Asuransi Jiwa Central Asia Raya | D90: 2014 | E90: =Data!N90 -> 0 | F90: =Data!K90 -> 0 | G90: =IFERROR(E90/F90,0) -> 0
D91: 2015 | E91: =Data!N91 -> -187450000000 | F91: =Data!K91 -> 1729967000000 | G91: =IFERROR(E91/F91,0) -> -0.10835467
D92: 2016 | E92: =Data!N92 -> 201331000000 | F92: =Data!K92 -> 1901149000000 | G92: =IFERROR(E92/F92,0) -> 0.10589964
D93: 2017 | E93: =Data!N93 -> -590339000000 | F93: =Data!K93 -> 1270110000000 | G93: =IFERROR(E93/F93,0) -> -0.4647936
D94: 2018 | E94: =Data!N94 -> 175397000000 | F94: =Data!K94 -> 6696353000000 | G94: =IFERROR(E94/F94,0) -> 0.026192914
D95: 2019 | E95: =Data!N95 -> 396160000000 | F95: =Data!K95 -> 8158087000000 | G95: =IFERROR(E95/F95,0) -> 0.048560404
D96: 2020 | E96: =Data!N96 -> 70612000000 | F96: =Data!K96 -> 1820409000000 | G96: =IFERROR(E96/F96,0) -> 0.038789085
D97: 2021 | E97: =Data!N97 -> 1154523000000 | F97: =Data!K97 -> 2942125000000 | G97: =IFERROR(E97/F97,0) -> 0.39241127
D98: 2022 | E98: =Data!N98 -> 158806000000 | F98: =Data!K98 -> 3077726000000 | G98: =IFERROR(E98/F98,0) -> 0.051598485
D99: 2023 | E99: =Data!N99 -> 107690000000 | F99: =Data!K99 -> 3159009000000 | G99: =IFERROR(E99/F99,0) -> 0.034089805
D100: 2024 | E100: =Data!N100 -> 277265000000 | F100: =Data!K100 -> 3409810000000 | G100: =IFERROR(E100/F100,0) -> 0.081313915
...

Sheet KM
A1: Sub Sektor | B1: No | C1: Nama Perusahaan | D1: Tahun | E1: Persentase Kepemilikan Terbesar | F1: Keterangan
A2: Asuransi Jiwa | B2: 1 | C2: Asuransi Jiwa Bersama Bumiputera 1912 | D2: 2014 | E2: =IFERROR(Data!O2,0) -> 0 | F2: =Data!P2 -> 0
D3: 2015 | E3: =Data!O3 -> 0 | F3: =Data!P3 -> 0
D4: 2016 | E4: =Data!O4 -> 0 | F4: =Data!P4 -> 0
D5: 2017 | E5: =Data!O5 -> 0 | F5: =Data!P5 -> 0
D6: 2018 | E6: =Data!O6 -> 0 | F6: =Data!P6 -> 0
D7: 2019 | E7: =Data!O7 -> 0 | F7: =Data!P7 -> 0
D8: 2020 | E8: =Data!O8 -> 0 | F8: =Data!P8 -> 0
D9: 2021 | E9: =Data!O9 -> 0 | F9: =Data!P9 -> 0
D10: 2022 | E10: =Data!O10 -> 0 | F10: =Data!P10 -> 0
D11: 2023 | E11: =Data!O11 -> 0 | F11: =Data!P11 -> 0
D12: 2024 | E12: =Data!O12 -> 0 | F12: =Data!P12 -> 0
B13: 2 | C13: PT AIA Financial | D13: 2014 | E13: =Data!O13 -> 0 | F13: =Data!P13 -> 0
D14: 2015 | E14: =Data!O14 -> 0.8 | F14: =Data!P14 -> AIA International Limited
D15: 2016 | E15: =Data!O15 -> 0.8 | F15: =Data!P15 -> AIA International Limited
D16: 2017 | E16: =Data!O16 -> 0.95 | F16: =Data!P16 -> AIA International Limited
D17: 2018 | E17: =Data!O17 -> 0.95 | F17: =Data!P17 -> AIA International Limited
D18: 2019 | E18: =Data!O18 -> 0.9499 | F18: =Data!P18 -> AIA International Limited
D19: 2020 | E19: =Data!O19 -> 0.9499 | F19: =Data!P19 -> AIA International Limited
D20: 2021 | E20: =Data!O20 -> 0.9499 | F20: =Data!P20 -> AIA International Limited
D21: 2022 | E21: =Data!O21 -> 0.9499 | F21: =Data!P21 -> AIA International Limited
D22: 2023 | E22: =Data!O22 -> 0.9499 | F22: =Data!P22 -> AIA International Limited
D23: 2024 | E23: =Data!O23 -> 0.9499 | F23: =Data!P23 -> AIA International Limited
B24: 3 | C24: PT Asuransi Allianz Life Indonesia | D24: 2014 | E24: =Data!O24 -> 0 | F24: =Data!P24 -> 0
D25: 2015 | E25: =Data!O25 -> 0.9976 | F25: =Data!P25 -> Allianz Asia Pacific & Africa GmbH
D26: 2016 | E26: =Data!O26 -> 0.9976 | F26: =Data!P26 -> Allianz Asia Pacific & Africa GmbH
D27: 2017 | E27: =Data!O27 -> 0.9976 | F27: =Data!P27 -> Allianz Asia Pacific & Africa GmbH
D28: 2018 | E28: =Data!O28 -> 0.9976 | F28: =Data!P28 -> Allianz Asia Pacific & Africa GmbH
D29: 2019 | E29: =Data!O29 -> 0.9976 | F29: =Data!P29 -> Allianz Asia Pacific & Africa GmbH
D30: 2020 | E30: =Data!O30 -> 0.9976 | F30: =Data!P30 -> Allianz Asia Pacific & Africa GmbH
D31: 2021 | E31: =Data!O31 -> 0.9976 | F31: =Data!P31 -> Allianz Asia Pacific & Africa GmbH
D32: 2022 | E32: =Data!O32 -> 0.9976 | F32: =Data!P32 -> Allianz Asia Pacific & Africa GmbH
D33: 2023 | E33: =Data!O33 -> 0.9976 | F33: =Data!P33 -> Allianz Asia Pacific & Africa GmbH
D34: 2024 | E34: =Data!O34 -> 0.9976 | F34: =Data!P34 -> Allianz Asia Pacific & Africa GmbH
B35: 4 | C35: PT Asuransi Allianz Life Syariah Indonesia | D35: 2014 | E35: =Data!O35 -> 0 | F35: =Data!P35 -> 0
D36: 2015 | E36: =Data!O36 -> 0 | F36: =Data!P36 -> 0
D37: 2016 | E37: =Data!O37 -> 0 | F37: =Data!P37 -> 0
D38: 2017 | E38: =Data!O38 -> 0 | F38: =Data!P38 -> 0
D39: 2018 | E39: =Data!O39 -> 0 | F39: =Data!P39 -> 0
D40: 2019 | E40: =Data!O40 -> 0 | F40: =Data!P40 -> 0
D41: 2020 | E41: =Data!O41 -> 0 | F41: =Data!P41 -> 0
D42: 2021 | E42: =Data!O42 -> 0 | F42: =Data!P42 -> 0
D43: 2022 | E43: =Data!O43 -> 0 | F43: =Data!P43 -> 0
D44: 2023 | E44: =Data!O44 -> 0.9999 | F44: =Data!P44 -> PT Asuransi Allianz Life Indonesia
D45: 2024 | E45: =Data!O45 -> 0.99 | F45: =Data!P45 -> PT Asuransi Allianz Life Indonesia
B46: 5 | C46: PT Asuransi BRI Life | D46: 2014 | E46: =Data!O46 -> 0 | F46: =Data!P46 -> 0
D47: 2015 | E47: =Data!O47 -> 0 | F47: =Data!P47 -> 0
D48: 2016 | E48: =Data!O48 -> 0 | F48: =Data!P48 -> 0
D49: 2017 | E49: =Data!O49 -> 0.91 | F49: =Data!P49 -> PT Bank Rakyat Indonesia
D50: 2018 | E50: =Data!O50 -> 0.91 | F50: =Data!P50 -> PT Bank Rakyat Indonesia
D51: 2019 | E51: =Data!O51 -> 0.9101 | F51: =Data!P51 -> PT Bank Rakyat Indonesia
D52: 2020 | E52: =Data!O52 -> 0.9101 | F52: =Data!P52 -> PT Bank Rakyat Indonesia
D53: 2021 | E53: =Data!O53 -> 0.6383 | F53: =Data!P53 -> PT Bank Rakyat Indonesia
D54: 2022 | E54: =Data!O54 -> 0.5902 | F54: =Data!P54 -> PT Bank Rakyat Indonesia
D55: 2023 | E55: =Data!O55 -> 0.5477 | F55: =Data!P55 -> PT Bank Rakyat Indonesia
D56: 2024 | E56: =Data!O56 -> 0 | F56: =Data!P56 -> 0
B57: 6 | C57: PT Asuransi Ciputra Indonesia | D57: 2014 | E57: =Data!O57 -> 0 | F57: =Data!P57 -> 0
D58: 2015 | E58: =Data!O58 -> 0 | F58: =Data!P58 -> 0
D59: 2016 | E59: =Data!O59 -> 0 | F59: =Data!P59 -> 0
D60: 2017 | E60: =Data!O60 -> 0.6 | F60: =Data!P60 -> PT Ciputra Internasional
D61: 2018 | E61: =Data!O61 -> 0.6 | F61: =Data!P61 -> PT Ciputra Internasional
D62: 2019 | E62: =Data!O62 -> 0.6 | F62: =Data!P62 -> PT Ciputra Internasional
D63: 2020 | E63: =Data!O63 -> 0.6 | F63: =Data!P63 -> PT Ciputra Internasional
D64: 2021 | E64: =Data!O64 -> 0.6 | F64: =Data!P64 -> PT Ciputra Internasional
D65: 2022 | E65: =Data!O65 -> 0.6 | F65: =Data!P65 -> PT Ciputra Internasional
D66: 2023 | E66: =Data!O66 -> 0.6 | F66: =Data!P66 -> PT Ciputra Internasional
D67: 2024 | E67: =Data!O67 -> 0.6 | F67: =Data!P67 -> PT Ciputra Internasional
B68: 7 | C68: PT Asuransi Jiwa Astra | D68: 2014 | E68: =Data!O68 -> 0 | F68: =Data!P68 -> 0
D69: 2015 | E69: =Data!O69 -> 0.5 | F69: =Data!P69 -> Aviva International Holding dan PT Astra International
D70: 2016 | E70: =Data!O70 -> 0.5 | F70: =Data!P70 -> Aviva International Holding dan PT Astra International
D71: 2017 | E71: =Data!O71 -> 0.5 | F71: =Data!P71 -> Aviva International Holding dan PT Astra International
D72: 2018 | E72: =Data!O72 -> 0.5 | F72: =Data!P72 -> Aviva International Holding dan PT Astra International
D73: 2019 | E73: =Data!O73 -> 0.5 | F73: =Data!P73 -> Aviva International Holding dan PT Astra International
D74: 2020 | E74: =Data!O74 -> 0.4999 | F74: =Data!P74 -> PT Astra International dan PT Sedaya Multi Investama
D75: 2021 | E75: =Data!O75 -> 0.4999 | F75: =Data!P75 -> PT Astra International dan PT Sedaya Multi Investama
D76: 2022 | E76: =Data!O76 -> 0.4999 | F76: =Data!P76 -> PT Astra International dan PT Sedaya Multi Investama
D77: 2023 | E77: =Data!O77 -> 0.4999 | F77: =Data!P77 -> PT Astra International dan PT Sedaya Multi Investama
D78: 2024 | E78: =Data!O78 -> 0.4999 | F78: =Data!P78 -> PT Astra International dan PT Sedaya Multi Investama
B79: 8 | C79: PT Asuransi Jiwa BCA | D79: 2014 | E79: =Data!O79 -> 0 | F79: =Data!P79 -> 0
D80: 2015 | E80: =Data!O80 -> 0.9999 | F80: =Data!P80 -> PT BCA Sekuritas
D81: 2016 | E81: =Data!O81 -> 0.9999 | F81: =Data!P81 -> PT BCA Sekuritas
D82: 2017 | E82: =Data!O82 -> 0.9 | F82: =Data!P82 -> PT BCA Sekuritas
D83: 2018 | E83: =Data!O83 -> 0.9 | F83: =Data!P83 -> PT BCA Sekuritas
D84: 2019 | E84: =Data!O84 -> 0.9 | F84: =Data!P84 -> PT BCA Sekuritas
D85: 2020 | E85: =Data!O85 -> 0.9 | F85: =Data!P85 -> PT BCA Sekuritas
D86: 2021 | E86: =Data!O86 -> 0.9 | F86: =Data!P86 -> PT BCA Sekuritas
D87: 2022 | E87: =Data!O87 -> 0.9 | F87: =Data!P87 -> PT BCA Sekuritas
D88: 2023 | E88: =Data!O88 -> 0.9 | F88: =Data!P88 -> PT BCA Sekuritas
D89: 2024 | E89: =Data!O89 -> 0.9 | F89: =Data!P89 -> PT BCA Sekuritas
B90: 9 | C90: PT Asuransi Jiwa Central Asia Raya | D90: 2014 | E90: =Data!O90 -> 0 | F90: =Data!P90 -> 0
D91: 2015 | E91: =Data!O91 -> 0.9999 | F91: =Data!P91 -> PT Asuransi Central Asia
D92: 2016 | E92: =Data!O92 -> 0.99 | F92: =Data!P92 -> PT Asuransi Central Asia
D93: 2017 | E93: =Data!O93 -> 0.99 | F93: =Data!P93 -> PT Asuransi Central Asia
D94: 2018 | E94: =Data!O94 -> 0.99 | F94: =Data!P94 -> PT Asuransi Central Asia
D95: 2019 | E95: =Data!O95 -> 0.99 | F95: =Data!P95 -> PT Asuransi Central Asia
D96: 2020 | E96: =Data!O96 -> 0.99 | F96: =Data!P96 -> PT Asuransi Central Asia
D97: 2021 | E97: =Data!O97 -> 0.99 | F97: =Data!P97 -> PT Asuransi Central Asia
D98: 2022 | E98: =Data!O98 -> 0.99 | F98: =Data!P98 -> PT Asuransi Central Asia
D99: 2023 | E99: =Data!O99 -> 0.99 | F99: =Data!P99 -> PT Asuransi Central Asia
D100: 2024 | E100: =Data!O100 -> 0.99 | F100: =Data!P100 -> PT Asuransi Central Asia
...

Sheet KI
A1: Sub Sektor | B1: No | C1: Nama Perusahaan | D1: Tahun | E1: Jumlah Komisaris Independen
A2: Asuransi Jiwa | B2: 1 | C2: Asuransi Jiwa Bersama Bumiputera 1912 | D2: 2014 | E2: =Data!Q2 -> 0
D3: 2015 | E3: =Data!Q3 -> 0
D4: 2016 | E4: =Data!Q4 -> 0
D5: 2017 | E5: =Data!Q5 -> 0
D6: 2018 | E6: =Data!Q6 -> 0
D7: 2019 | E7: =Data!Q7 -> 0
D8: 2020 | E8: =Data!Q8 -> 0
D9: 2021 | E9: =Data!Q9 -> 0
D10: 2022 | E10: =Data!Q10 -> 0
D11: 2023 | E11: =Data!Q11 -> 0
D12: 2024 | E12: =Data!Q12 -> 0
B13: 2 | C13: PT AIA Financial | D13: 2014 | E13: =Data!Q13 -> 0
D14: 2015 | E14: =Data!Q14 -> 2
D15: 2016 | E15: =Data!Q15 -> 2
D16: 2017 | E16: =Data!Q16 -> 2
D17: 2018 | E17: =Data!Q17 -> 2
D18: 2019 | E18: =Data!Q18 -> 2
D19: 2020 | E19: =Data!Q19 -> 2
D20: 2021 | E20: =Data!Q20 -> 1
D21: 2022 | E21: =Data!Q21 -> 1
D22: 2023 | E22: =Data!Q22 -> 2
D23: 2024 | E23: =Data!Q23 -> 1
B24: 3 | C24: PT Asuransi Allianz Life Indonesia | D24: 2014 | E24: =Data!Q24 -> 0
D25: 2015 | E25: =Data!Q25 -> 2
D26: 2016 | E26: =Data!Q26 -> 2
D27: 2017 | E27: =Data!Q27 -> 2
D28: 2018 | E28: =Data!Q28 -> 2
D29: 2019 | E29: =Data!Q29 -> 2
D30: 2020 | E30: =Data!Q30 -> 2
D31: 2021 | E31: =Data!Q31 -> 2
D32: 2022 | E32: =Data!Q32 -> 2
D33: 2023 | E33: =Data!Q33 -> 2
D34: 2024 | E34: =Data!Q34 -> 2
B35: 4 | C35: PT Asuransi Allianz Life Syariah Indonesia | D35: 2014 | E35: =Data!Q35 -> 0
D36: 2015 | E36: =Data!Q36 -> 0
D37: 2016 | E37: =Data!Q37 -> 0
D38: 2017 | E38: =Data!Q38 -> 0
D39: 2018 | E39: =Data!Q39 -> 0
D40: 2019 | E40: =Data!Q40 -> 0
D41: 2020 | E41: =Data!Q41 -> 0
D42: 2021 | E42: =Data!Q42 -> 0
D43: 2022 | E43: =Data!Q43 -> 0
D44: 2023 | E44: =Data!Q44 -> 2
D45: 2024 | E45: =Data!Q45 -> 2
B46: 5 | C46: PT Asuransi BRI Life | D46: 2014 | E46: =Data!Q46 -> 0
D47: 2015 | E47: =Data!Q47 -> 0
D48: 2016 | E48: =Data!Q48 -> 0
D49: 2017 | E49: =Data!Q49 -> 3
D50: 2018 | E50: =Data!Q50 -> 2
D51: 2019 | E51: =Data!Q51 -> 3
D52: 2020 | E52: =Data!Q52 -> 2
D53: 2021 | E53: =Data!Q53 -> 4
D54: 2022 | E54: =Data!Q54 -> 3
D55: 2023 | E55: =Data!Q55 -> 3
D56: 2024 | E56: =Data!Q56 -> 0
B57: 6 | C57: PT Asuransi Ciputra Indonesia | D57: 2014 | E57: =Data!Q57 -> 0
D58: 2015 | E58: =Data!Q58 -> 0
D59: 2016 | E59: =Data!Q59 -> 0
D60: 2017 | E60: =Data!Q60 -> 2
D61: 2018 | E61: =Data!Q61 -> 2
D62: 2019 | E62: =Data!Q62 -> 2
D63: 2020 | E63: =Data!Q63 -> 2
D64: 2021 | E64: =Data!Q64 -> 2
D65: 2022 | E65: =Data!Q65 -> 2
D66: 2023 | E66: =Data!Q66 -> 2
D67: 2024 | E67: =Data!Q67 -> 2
B68: 7 | C68: PT Asuransi Jiwa Astra | D68: 2014 | E68: =Data!Q68 -> 0
D69: 2015 | E69: =Data!Q69 -> 2
D70: 2016 | E70: =Data!Q70 -> 2
D71: 2017 | E71: =Data!Q71 -> 2
D72: 2018 | E72: =Data!Q72 -> 2
D73: 2019 | E73: =Data!Q73 -> 2
D74: 2020 | E74: =Data!Q74 -> 2
D75: 2021 | E75: =Data!Q75 -> 2
D76: 2022 | E76: =Data!Q76 -> 2
D77: 2023 | E77: =Data!Q77 -> 2
D78: 2024 | E78: =Data!Q78 -> 2
B79: 8 | C79: PT Asuransi Jiwa BCA | D79: 2014 | E79: =Data!Q79 -> 0
D80: 2015 | E80: =Data!Q80 -> 2
D81: 2016 | E81: =Data!Q81 -> 1
D82: 2017 | E82: =Data!Q82 -> 0
D83: 2018 | E83: =Data!Q83 -> 0
D84: 2019 | E84: =Data!Q84 -> 0
D85: 2020 | E85: =Data!Q85 -> 0
D86: 2021 | E86: =Data!Q86 -> 2
D87: 2022 | E87: =Data!Q87 -> 2
D88: 2023 | E88: =Data!Q88 -> 2
D89: 2024 | E89: =Data!Q89 -> 2
B90: 9 | C90: PT Asuransi Jiwa Central Asia Raya | D90: 2014 | E90: =Data!Q90 -> 0
D91: 2015 | E91: =Data!Q91 -> 2
D92: 2016 | E92: =Data!Q92 -> 2
D93: 2017 | E93: =Data!Q93 -> 2
D94: 2018 | E94: =Data!Q94 -> 2
D95: 2019 | E95: =Data!Q95 -> 2
D96: 2020 | E96: =Data!Q96 -> 2
D97: 2021 | E97: =Data!Q97 -> 2
D98: 2022 | E98: =Data!Q98 -> 2
D99: 2023 | E99: =Data!Q99 -> 2
D100: 2024 | E100: =Data!Q100 -> 2
...

Sheet IO
A1: Sub Sektor | B1: No | C1: Nama Perusahaan | D1: Tahun | E1: Persentase Kepemilikan oleh Komisaris dan Direksi
A2: Asuransi Jiwa | B2: 1 | C2: Asuransi Jiwa Bersama Bumiputera 1912 | D2: 2014 | E2: =Data!U2 -> 0
D3: 2015 | E3: =Data!U3 -> 0
D4: 2016 | E4: =Data!U4 -> 0
D5: 2017 | E5: =Data!U5 -> 0
D6: 2018 | E6: =Data!U6 -> 0
D7: 2019 | E7: =Data!U7 -> 0
D8: 2020 | E8: =Data!U8 -> 0
D9: 2021 | E9: =Data!U9 -> 0
D10: 2022 | E10: =Data!U10 -> 0
D11: 2023 | E11: =Data!U11 -> 0
D12: 2024 | E12: =Data!U12 -> 0
B13: 2 | C13: PT AIA Financial | D13: 2014 | E13: =Data!U13 -> 0
D14: 2015 | E14: =Data!U14 -> 0
D15: 2016 | E15: =Data!U15 -> 0
D16: 2017 | E16: =Data!U16 -> 0
D17: 2018 | E17: =Data!U17 -> 0
D18: 2019 | E18: =Data!U18 -> 0
D19: 2020 | E19: =Data!U19 -> 0
D20: 2021 | E20: =Data!U20 -> 0
D21: 2022 | E21: =Data!U21 -> 0
D22: 2023 | E22: =Data!U22 -> 0
D23: 2024 | E23: =Data!U23 -> 0
B24: 3 | C24: PT Asuransi Allianz Life Indonesia | D24: 2014 | E24: =Data!U24 -> 0
D25: 2015 | E25: =Data!U25 -> 0
D26: 2016 | E26: =Data!U26 -> 0
D27: 2017 | E27: =Data!U27 -> 0
D28: 2018 | E28: =Data!U28 -> 0
D29: 2019 | E29: =Data!U29 -> 0
D30: 2020 | E30: =Data!U30 -> 0
D31: 2021 | E31: =Data!U31 -> 0
D32: 2022 | E32: =Data!U32 -> 0
D33: 2023 | E33: =Data!U33 -> 0
D34: 2024 | E34: =Data!U34 -> 0
B35: 4 | C35: PT Asuransi Allianz Life Syariah Indonesia | D35: 2014 | E35: =Data!U35 -> 0
D36: 2015 | E36: =Data!U36 -> 0
D37: 2016 | E37: =Data!U37 -> 0
D38: 2017 | E38: =Data!U38 -> 0
D39: 2018 | E39: =Data!U39 -> 0
D40: 2019 | E40: =Data!U40 -> 0
D41: 2020 | E41: =Data!U41 -> 0
D42: 2021 | E42: =Data!U42 -> 0
D43: 2022 | E43: =Data!U43 -> 0
D44: 2023 | E44: =Data!U44 -> 0
D45: 2024 | E45: =Data!U45 -> 0
B46: 5 | C46: PT Asuransi BRI Life | D46: 2014 | E46: =Data!U46 -> 0
D47: 2015 | E47: =Data!U47 -> 0
D48: 2016 | E48: =Data!U48 -> 0
D49: 2017 | E49: =Data!U49 -> 0
D50: 2018 | E50: =Data!U50 -> 0
D51: 2019 | E51: =Data!U51 -> 0
D52: 2020 | E52: =Data!U52 -> 0
D53: 2021 | E53: =Data!U53 -> 0
D54: 2022 | E54: =Data!U54 -> 0
D55: 2023 | E55: =Data!U55 -> 0
D56: 2024 | E56: =Data!U56 -> 0
B57: 6 | C57: PT Asuransi Ciputra Indonesia | D57: 2014 | E57: =Data!U57 -> 0
D58: 2015 | E58: =Data!U58 -> 0
D59: 2016 | E59: =Data!U59 -> 0
D60: 2017 | E60: =Data!U60 -> 0
D61: 2018 | E61: =Data!U61 -> 0
D62: 2019 | E62: =Data!U62 -> 0
D63: 2020 | E63: =Data!U63 -> 0
D64: 2021 | E64: =Data!U64 -> 0
D65: 2022 | E65: =Data!U65 -> 0
D66: 2023 | E66: =Data!U66 -> 0
D67: 2024 | E67: =Data!U67 -> 0
B68: 7 | C68: PT Asuransi Jiwa Astra | D68: 2014 | E68: =Data!U68 -> 0
D69: 2015 | E69: =Data!U69 -> 0
D70: 2016 | E70: =Data!U70 -> 0
D71: 2017 | E71: =Data!U71 -> 0
D72: 2018 | E72: =Data!U72 -> 0
D73: 2019 | E73: =Data!U73 -> 0
D74: 2020 | E74: =Data!U74 -> 0
D75: 2021 | E75: =Data!U75 -> 0
D76: 2022 | E76: =Data!U76 -> 0
D77: 2023 | E77: =Data!U77 -> 0
D78: 2024 | E78: =Data!U78 -> 0
B79: 8 | C79: PT Asuransi Jiwa BCA | D79: 2014 | E79: =Data!U79 -> 0
D80: 2015 | E80: =Data!U80 -> 0
D81: 2016 | E81: =Data!U81 -> 0
D82: 2017 | E82: =Data!U82 -> 0
D83: 2018 | E83: =Data!U83 -> 0
D84: 2019 | E84: =Data!U84 -> 0
D85: 2020 | E85: =Data!U85 -> 0
D86: 2021 | E86: =Data!U86 -> 0
D87: 2022 | E87: =Data!U87 -> 0
D88: 2023 | E88: =Data!U88 -> 0
D89: 2024 | E89: =Data!U89 -> 0
B90: 9 | C90: PT Asuransi Jiwa Central Asia Raya | D90: 2014 | E90: =Data!U90 -> 0
D91: 2015 | E91: =Data!U91 -> 1e-05
D92: 2016 | E92: =Data!U92 -> 1e-05
D93: 2017 | E93: =Data!U93 -> 1e-05
D94: 2018 | E94: =Data!U94 -> 1e-05
D95: 2019 | E95: =Data!U95 -> 1e-05
D96: 2020 | E96: =Data!U96 -> 1e-05
D97: 2021 | E97: =Data!U97 -> 1e-05
D98: 2022 | E98: =Data!U98 -> 1e-05
D99: 2023 | E99: =Data!U99 -> 1e-05
D100: 2024 | E100: =Data!U100 -> 1e-05
...

Sheet BoC Size
A1: Sub Sektor | B1: No | C1: Nama Perusahaan | D1: Tahun | E1: Jumlah Dewan Komisaris
A2: Asuransi Jiwa | B2: 1 | C2: Asuransi Jiwa Bersama Bumiputera 1912 | D2: 2014 | E2: =Data!R2 -> 0
D3: 2015 | E3: =Data!R3 -> 0
D4: 2016 | E4: =Data!R4 -> 0
D5: 2017 | E5: =Data!R5 -> 0
D6: 2018 | E6: =Data!R6 -> 0
D7: 2019 | E7: =Data!R7 -> 0
D8: 2020 | E8: =Data!R8 -> 0
D9: 2021 | E9: =Data!R9 -> 0
D10: 2022 | E10: =Data!R10 -> 0
D11: 2023 | E11: =Data!R11 -> 0
D12: 2024 | E12: =Data!R12 -> 0
B13: 2 | C13: PT AIA Financial | D13: 2014 | E13: =Data!R13 -> 0
D14: 2015 | E14: =Data!R14 -> 4
D15: 2016 | E15: =Data!R15 -> 4
D16: 2017 | E16: =Data!R16 -> 4
D17: 2018 | E17: =Data!R17 -> 4
D18: 2019 | E18: =Data!R18 -> 4
D19: 2020 | E19: =Data!R19 -> 4
D20: 2021 | E20: =Data!R20 -> 3
D21: 2022 | E21: =Data!R21 -> 3
D22: 2023 | E22: =Data!R22 -> 4
D23: 2024 | E23: =Data!R23 -> 3
B24: 3 | C24: PT Asuransi Allianz Life Indonesia | D24: 2014 | E24: =Data!R24 -> 0
D25: 2015 | E25: =Data!R25 -> 3
D26: 2016 | E26: =Data!R26 -> 3
D27: 2017 | E27: =Data!R27 -> 4
D28: 2018 | E28: =Data!R28 -> 3
D29: 2019 | E29: =Data!R29 -> 3
D30: 2020 | E30: =Data!R30 -> 3
D31: 2021 | E31: =Data!R31 -> 4
D32: 2022 | E32: =Data!R32 -> 3
D33: 2023 | E33: =Data!R33 -> 4
D34: 2024 | E34: =Data!R34 -> 4
B35: 4 | C35: PT Asuransi Allianz Life Syariah Indonesia | D35: 2014 | E35: =Data!R35 -> 0
D36: 2015 | E36: =Data!R36 -> 0
D37: 2016 | E37: =Data!R37 -> 0
D38: 2017 | E38: =Data!R38 -> 0
D39: 2018 | E39: =Data!R39 -> 0
D40: 2019 | E40: =Data!R40 -> 0
D41: 2020 | E41: =Data!R41 -> 0
D42: 2021 | E42: =Data!R42 -> 0
D43: 2022 | E43: =Data!R43 -> 0
D44: 2023 | E44: =Data!R44 -> 3
D45: 2024 | E45: =Data!R45 -> 3
B46: 5 | C46: PT Asuransi BRI Life | D46: 2014 | E46: =Data!R46 -> 0
D47: 2015 | E47: =Data!R47 -> 0
D48: 2016 | E48: =Data!R48 -> 0
D49: 2017 | E49: =Data!R49 -> 5
D50: 2018 | E50: =Data!R50 -> 5
D51: 2019 | E51: =Data!R51 -> 6
D52: 2020 | E52: =Data!R52 -> 4
D53: 2021 | E53: =Data!R53 -> 6
D54: 2022 | E54: =Data!R54 -> 5
D55: 2023 | E55: =Data!R55 -> 5
D56: 2024 | E56: =Data!R56 -> 0
B57: 6 | C57: PT Asuransi Ciputra Indonesia | D57: 2014 | E57: =Data!R57 -> 0
D58: 2015 | E58: =Data!R58 -> 0
D59: 2016 | E59: =Data!R59 -> 0
D60: 2017 | E60: =Data!R60 -> 4
D61: 2018 | E61: =Data!R61 -> 4
D62: 2019 | E62: =Data!R62 -> 4
D63: 2020 | E63: =Data!R63 -> 4
D64: 2021 | E64: =Data!R64 -> 4
D65: 2022 | E65: =Data!R65 -> 4
D66: 2023 | E66: =Data!R66 -> 4
D67: 2024 | E67: =Data!R67 -> 3
B68: 7 | C68: PT Asuransi Jiwa Astra | D68: 2014 | E68: =Data!R68 -> 0
D69: 2015 | E69: =Data!R69 -> 4
D70: 2016 | E70: =Data!R70 -> 4
D71: 2017 | E71: =Data!R71 -> 4
D72: 2018 | E72: =Data!R72 -> 4
D73: 2019 | E73: =Data!R73 -> 4
D74: 2020 | E74: =Data!R74 -> 4
D75: 2021 | E75: =Data!R75 -> 4
D76: 2022 | E76: =Data!R76 -> 4
D77: 2023 | E77: =Data!R77 -> 4
D78: 2024 | E78: =Data!R78 -> 4
B79: 8 | C79: PT Asuransi Jiwa BCA | D79: 2014 | E79: =Data!R79 -> 0
D80: 2015 | E80: =Data!R80 -> 4
D81: 2016 | E81: =Data!R81 -> 3
D82: 2017 | E82: =Data!R82 -> 4
D83: 2018 | E83: =Data!R83 -> 4
D84: 2019 | E84: =Data!R84 -> 4
D85: 2020 | E85: =Data!R85 -> 4
D86: 2021 | E86: =Data!R86 -> 4
D87: 2022 | E87: =Data!R87 -> 4
D88: 2023 | E88: =Data!R88 -> 4
D89: 2024 | E89: =Data!R89 -> 4
B90: 9 | C90: PT Asuransi Jiwa Central Asia Raya | D90: 2014 | E90: =Data!R90 -> 0
D91: 2015 | E91: =Data!R91 -> 4
D92: 2016 | E92: =Data!R92 -> 4
D93: 2017 | E93: =Data!R93 -> 4
D94: 2018 | E94: =Data!R94 -> 4
D95: 2019 | E95: =Data!R95 -> 4
D96: 2020 | E96: =Data!R96 -> 4
D97: 2021 | E97: =Data!R97 -> 3
D98: 2022 | E98: =Data!R98 -> 3
D99: 2023 | E99: =Data!R99 -> 3
D100: 2024 | E100: =Data!R100 -> 3
...

Sheet TMT E DK
A1: Sub Sektor | B1: No | C1: Nama Perusahaan | D1: Tahun | E1: TMT Education (Dewan Komisaris)
A2: Asuransi Jiwa | B2: 1 | C2: Asuransi Jiwa Bersama Bumiputera 1912 | D2: 2014 | E2: =Data!V2 -> 0
D3: 2015 | E3: =Data!V3 -> 0
D4: 2016 | E4: =Data!V4 -> 0
D5: 2017 | E5: =Data!V5 -> 0
D6: 2018 | E6: =Data!V6 -> 0
D7: 2019 | E7: =Data!V7 -> 0
D8: 2020 | E8: =Data!V8 -> 0
D9: 2021 | E9: =Data!V9 -> 0
D10: 2022 | E10: =Data!V10 -> 0
D11: 2023 | E11: =Data!V11 -> 0
D12: 2024 | E12: =Data!V12 -> 0
B13: 2 | C13: PT AIA Financial | D13: 2014 | E13: =Data!V13 -> 0
D14: 2015 | E14: =Data!V14 -> 0
D15: 2016 | E15: =Data!V15 -> 0
D16: 2017 | E16: =Data!V16 -> 0
D17: 2018 | E17: =Data!V17 -> 0
D18: 2019 | E18: =Data!V18 -> 0
D19: 2020 | E19: =Data!V19 -> 0
D20: 2021 | E20: =Data!V20 -> 0
D21: 2022 | E21: =Data!V21 -> 0
D22: 2023 | E22: =Data!V22 -> 0
D23: 2024 | E23: =Data!V23 -> 0
B24: 3 | C24: PT Asuransi Allianz Life Indonesia | D24: 2014 | E24: =Data!V24 -> 0
D25: 2015 | E25: =Data!V25 -> 0
D26: 2016 | E26: =Data!V26 -> 0
D27: 2017 | E27: =Data!V27 -> 0
D28: 2018 | E28: =Data!V28 -> 0
D29: 2019 | E29: =Data!V29 -> 0
D30: 2020 | E30: =Data!V30 -> 8
D31: 2021 | E31: =Data!V31 -> 9
D32: 2022 | E32: =Data!V32 -> 8
D33: 2023 | E33: =Data!V33 -> 8
D34: 2024 | E34: =Data!V34 -> 8
B35: 4 | C35: PT Asuransi Allianz Life Syariah Indonesia | D35: 2014 | E35: =Data!V35 -> 0
D36: 2015 | E36: =Data!V36 -> 0
D37: 2016 | E37: =Data!V37 -> 0
D38: 2017 | E38: =Data!V38 -> 0
D39: 2018 | E39: =Data!V39 -> 0
D40: 2019 | E40: =Data!V40 -> 0
D41: 2020 | E41: =Data!V41 -> 0
D42: 2021 | E42: =Data!V42 -> 0
D43: 2022 | E43: =Data!V43 -> 0
D44: 2023 | E44: =Data!V44 -> 0
D45: 2024 | E45: =Data!V45 -> 0
B46: 5 | C46: PT Asuransi BRI Life | D46: 2014 | E46: =Data!V46 -> 0
D47: 2015 | E47: =Data!V47 -> 0
D48: 2016 | E48: =Data!V48 -> 0
D49: 2017 | E49: =Data!V49 -> 13
D50: 2018 | E50: =Data!V50 -> 13
D51: 2019 | E51: =Data!V51 -> 16
D52: 2020 | E52: =Data!V52 -> 12
D53: 2021 | E53: =Data!V53 -> 14
D54: 2022 | E54: =Data!V54 -> 11
D55: 2023 | E55: =Data!V55 -> 14
D56: 2024 | E56: =Data!V56 -> 0
B57: 6 | C57: PT Asuransi Ciputra Indonesia | D57: 2014 | E57: =Data!V57 -> 0
D58: 2015 | E58: =Data!V58 -> 0
D59: 2016 | E59: =Data!V59 -> 0
D60: 2017 | E60: =Data!V60 -> 12
D61: 2018 | E61: =Data!V61 -> 12
D62: 2019 | E62: =Data!V62 -> 12
D63: 2020 | E63: =Data!V63 -> 12
D64: 2021 | E64: =Data!V64 -> 12
D65: 2022 | E65: =Data!V65 -> 12
D66: 2023 | E66: =Data!V66 -> 12
D67: 2024 | E67: =Data!V67 -> 7
B68: 7 | C68: PT Asuransi Jiwa Astra | D68: 2014 | E68: =Data!V68 -> 0
D69: 2015 | E69: =Data!V69 -> 0
D70: 2016 | E70: =Data!V70 -> 0
D71: 2017 | E71: =Data!V71 -> 0
D72: 2018 | E72: =Data!V72 -> 0
D73: 2019 | E73: =Data!V73 -> 0
D74: 2020 | E74: =Data!V74 -> 0
D75: 2021 | E75: =Data!V75 -> 0
D76: 2022 | E76: =Data!V76 -> 10
D77: 2023 | E77: =Data!V77 -> 0
D78: 2024 | E78: =Data!V78 -> 0
B79: 8 | C79: PT Asuransi Jiwa BCA | D79: 2014 | E79: =Data!V79 -> 0
D80: 2015 | E80: =Data!V80 -> 0
D81: 2016 | E81: =Data!V81 -> 0
D82: 2017 | E82: =Data!V82 -> 0
D83: 2018 | E83: =Data!V83 -> 0
D84: 2019 | E84: =Data!V84 -> 0
D85: 2020 | E85: =Data!V85 -> 0
D86: 2021 | E86: =Data!V86 -> 0
D87: 2022 | E87: =Data!V87 -> 0
D88: 2023 | E88: =Data!V88 -> 0
D89: 2024 | E89: =Data!V89 -> 0
B90: 9 | C90: PT Asuransi Jiwa Central Asia Raya | D90: 2014 | E90: =Data!V90 -> 0
D91: 2015 | E91: =Data!V91 -> 0
D92: 2016 | E92: =Data!V92 -> 0
D93: 2017 | E93: =Data!V93 -> 0
D94: 2018 | E94: =Data!V94 -> 0
D95: 2019 | E95: =Data!V95 -> 0
D96: 2020 | E96: =Data!V96 -> 0
D97: 2021 | E97: =Data!V97 -> 0
D98: 2022 | E98: =Data!V98 -> 0
D99: 2023 | E99: =Data!V99 -> 0
D100: 2024 | E100: =Data!V100 -> 0
...

Sheet TMT E DD
A1: Sub Sektor | B1: No | C1: Nama Perusahaan | D1: Tahun | E1: TMT Education (Dewan Direksi)
A2: Asuransi Jiwa | B2: 1 | C2: Asuransi Jiwa Bersama Bumiputera 1912 | D2: 2014 | E2: =Data!X2 -> 0
D3: 2015 | E3: =Data!X3 -> 0
D4: 2016 | E4: =Data!X4 -> 0
D5: 2017 | E5: =Data!X5 -> 0
D6: 2018 | E6: =Data!X6 -> 0
D7: 2019 | E7: =Data!X7 -> 0
D8: 2020 | E8: =Data!X8 -> 0
D9: 2021 | E9: =Data!X9 -> 0
D10: 2022 | E10: =Data!X10 -> 0
D11: 2023 | E11: =Data!X11 -> 0
D12: 2024 | E12: =Data!X12 -> 0
B13: 2 | C13: PT AIA Financial | D13: 2014 | E13: =Data!X13 -> 0
D14: 2015 | E14: =Data!X14 -> 0
D15: 2016 | E15: =Data!X15 -> 0
D16: 2017 | E16: =Data!X16 -> 0
D17: 2018 | E17: =Data!X17 -> 0
D18: 2019 | E18: =Data!X18 -> 0
D19: 2020 | E19: =Data!X19 -> 0
D20: 2021 | E20: =Data!X20 -> 0
D21: 2022 | E21: =Data!X21 -> 0
D22: 2023 | E22: =Data!X22 -> 0
D23: 2024 | E23: =Data!X23 -> 0
B24: 3 | C24: PT Asuransi Allianz Life Indonesia | D24: 2014 | E24: =Data!X24 -> 0
D25: 2015 | E25: =Data!X25 -> 0
D26: 2016 | E26: =Data!X26 -> 0
D27: 2017 | E27: =Data!X27 -> 0
D28: 2018 | E28: =Data!X28 -> 0
D29: 2019 | E29: =Data!X29 -> 0
D30: 2020 | E30: =Data!X30 -> 14
D31: 2021 | E31: =Data!X31 -> 11
D32: 2022 | E32: =Data!X32 -> 8
D33: 2023 | E33: =Data!X33 -> 10
D34: 2024 | E34: =Data!X34 -> 6
B35: 4 | C35: PT Asuransi Allianz Life Syariah Indonesia | D35: 2014 | E35: =Data!X35 -> 0
D36: 2015 | E36: =Data!X36 -> 0
D37: 2016 | E37: =Data!X37 -> 0
D38: 2017 | E38: =Data!X38 -> 0
D39: 2018 | E39: =Data!X39 -> 0
D40: 2019 | E40: =Data!X40 -> 0
D41: 2020 | E41: =Data!X41 -> 0
D42: 2021 | E42: =Data!X42 -> 0
D43: 2022 | E43: =Data!X43 -> 0
D44: 2023 | E44: =Data!X44 -> 0
D45: 2024 | E45: =Data!X45 -> 0
B46: 5 | C46: PT Asuransi BRI Life | D46: 2014 | E46: =Data!X46 -> 0
D47: 2015 | E47: =Data!X47 -> 0
D48: 2016 | E48: =Data!X48 -> 0
D49: 2017 | E49: =Data!X49 -> 17
D50: 2018 | E50: =Data!X50 -> 16
D51: 2019 | E51: =Data!X51 -> 16
D52: 2020 | E52: =Data!X52 -> 10
D53: 2021 | E53: =Data!X53 -> 20
D54: 2022 | E54: =Data!X54 -> 11
D55: 2023 | E55: =Data!X55 -> 13
D56: 2024 | E56: =Data!X56 -> 0
B57: 6 | C57: PT Asuransi Ciputra Indonesia | D57: 2014 | E57: =Data!X57 -> 0
D58: 2015 | E58: =Data!X58 -> 0
D59: 2016 | E59: =Data!X59 -> 0
D60: 2017 | E60: =Data!X60 -> 7
D61: 2018 | E61: =Data!X61 -> 7
D62: 2019 | E62: =Data!X62 -> 7
D63: 2020 | E63: =Data!X63 -> 7
D64: 2021 | E64: =Data!X64 -> 7
D65: 2022 | E65: =Data!X65 -> 7
D66: 2023 | E66: =Data!X66 -> 7
D67: 2024 | E67: =Data!X67 -> 7
B68: 7 | C68: PT Asuransi Jiwa Astra | D68: 2014 | E68: =Data!X68 -> 0
D69: 2015 | E69: =Data!X69 -> 0
D70: 2016 | E70: =Data!X70 -> 0
D71: 2017 | E71: =Data!X71 -> 0
D72: 2018 | E72: =Data!X72 -> 0
D73: 2019 | E73: =Data!X73 -> 0
D74: 2020 | E74: =Data!X74 -> 0
D75: 2021 | E75: =Data!X75 -> 0
D76: 2022 | E76: =Data!X76 -> 11
D77: 2023 | E77: =Data!X77 -> 0
D78: 2024 | E78: =Data!X78 -> 0
B79: 8 | C79: PT Asuransi Jiwa BCA | D79: 2014 | E79: =Data!X79 -> 0
D80: 2015 | E80: =Data!X80 -> 0
D81: 2016 | E81: =Data!X81 -> 0
D82: 2017 | E82: =Data!X82 -> 0
D83: 2018 | E83: =Data!X83 -> 0
D84: 2019 | E84: =Data!X84 -> 0
D85: 2020 | E85: =Data!X85 -> 0
D86: 2021 | E86: =Data!X86 -> 0
D87: 2022 | E87: =Data!X87 -> 0
D88: 2023 | E88: =Data!X88 -> 0
D89: 2024 | E89: =Data!X89 -> 0
B90: 9 | C90: PT Asuransi Jiwa Central Asia Raya | D90: 2014 | E90: =Data!X90 -> 0
D91: 2015 | E91: =Data!X91 -> 0
D92: 2016 | E92: =Data!X92 -> 0
D93: 2017 | E93: =Data!X93 -> 0
D94: 2018 | E94: =Data!X94 -> 0
D95: 2019 | E95: =Data!X95 -> 0
D96: 2020 | E96: =Data!X96 -> 0
D97: 2021 | E97: =Data!X97 -> 0
D98: 2022 | E98: =Data!X98 -> 0
D99: 2023 | E99: =Data!X99 -> 0
D100: 2024 | E100: =Data!X100 -> 0
...

Sheet TMT Size
A1: Sub Sektor | B1: No | C1: Nama Perusahaan | D1: Tahun | E1: Jumlah Dewan Komisaris dan Jumlah Dewan Direksi
A2: Asuransi Jiwa | B2: 1 | C2: Asuransi Jiwa Bersama Bumiputera 1912 | D2: 2014 | E2: =Data!T2 -> 0
D3: 2015 | E3: =Data!T3 -> 0
D4: 2016 | E4: =Data!T4 -> 0
D5: 2017 | E5: =Data!T5 -> 0
D6: 2018 | E6: =Data!T6 -> 0
D7: 2019 | E7: =Data!T7 -> 0
D8: 2020 | E8: =Data!T8 -> 0
D9: 2021 | E9: =Data!T9 -> 0
D10: 2022 | E10: =Data!T10 -> 0
D11: 2023 | E11: =Data!T11 -> 0
D12: 2024 | E12: =Data!T12 -> 0
B13: 2 | C13: PT AIA Financial | D13: 2014 | E13: =Data!T13 -> 0
D14: 2015 | E14: =Data!T14 -> 9
D15: 2016 | E15: =Data!T15 -> 9
D16: 2017 | E16: =Data!T16 -> 9
D17: 2018 | E17: =Data!T17 -> 9
D18: 2019 | E18: =Data!T18 -> 8
D19: 2020 | E19: =Data!T19 -> 8
D20: 2021 | E20: =Data!T20 -> 7
D21: 2022 | E21: =Data!T21 -> 7
D22: 2023 | E22: =Data!T22 -> 9
D23: 2024 | E23: =Data!T23 -> 8
B24: 3 | C24: PT Asuransi Allianz Life Indonesia | D24: 2014 | E24: =Data!T24 -> 0
D25: 2015 | E25: =Data!T25 -> 7
D26: 2016 | E26: =Data!T26 -> 7
D27: 2017 | E27: =Data!T27 -> 9
D28: 2018 | E28: =Data!T28 -> 9
D29: 2019 | E29: =Data!T29 -> 9
D30: 2020 | E30: =Data!T30 -> 9
D31: 2021 | E31: =Data!T31 -> 9
D32: 2022 | E32: =Data!T32 -> 7
D33: 2023 | E33: =Data!T33 -> 8
D34: 2024 | E34: =Data!T34 -> 7
B35: 4 | C35: PT Asuransi Allianz Life Syariah Indonesia | D35: 2014 | E35: =Data!T35 -> 0
D36: 2015 | E36: =Data!T36 -> 0
D37: 2016 | E37: =Data!T37 -> 0
D38: 2017 | E38: =Data!T38 -> 0
D39: 2018 | E39: =Data!T39 -> 0
D40: 2019 | E40: =Data!T40 -> 0
D41: 2020 | E41: =Data!T41 -> 0
D42: 2021 | E42: =Data!T42 -> 0
D43: 2022 | E43: =Data!T43 -> 0
D44: 2023 | E44: =Data!T44 -> 6
D45: 2024 | E45: =Data!T45 -> 6
B46: 5 | C46: PT Asuransi BRI Life | D46: 2014 | E46: =Data!T46 -> 0
D47: 2015 | E47: =Data!T47 -> 0
D48: 2016 | E48: =Data!T48 -> 0
D49: 2017 | E49: =Data!T49 -> 11
D50: 2018 | E50: =Data!T50 -> 11
D51: 2019 | E51: =Data!T51 -> 12
D52: 2020 | E52: =Data!T52 -> 8
D53: 2021 | E53: =Data!T53 -> 14
D54: 2022 | E54: =Data!T54 -> 10
D55: 2023 | E55: =Data!T55 -> 10
D56: 2024 | E56: =Data!T56 -> 0
B57: 6 | C57: PT Asuransi Ciputra Indonesia | D57: 2014 | E57: =Data!T57 -> 0
D58: 2015 | E58: =Data!T58 -> 0
D59: 2016 | E59: =Data!T59 -> 0
D60: 2017 | E60: =Data!T60 -> 7
D61: 2018 | E61: =Data!T61 -> 7
D62: 2019 | E62: =Data!T62 -> 7
D63: 2020 | E63: =Data!T63 -> 7
D64: 2021 | E64: =Data!T64 -> 7
D65: 2022 | E65: =Data!T65 -> 7
D66: 2023 | E66: =Data!T66 -> 7
D67: 2024 | E67: =Data!T67 -> 6
B68: 7 | C68: PT Asuransi Jiwa Astra | D68: 2014 | E68: =Data!T68 -> 0
D69: 2015 | E69: =Data!T69 -> 10
D70: 2016 | E70: =Data!T70 -> 9
D71: 2017 | E71: =Data!T71 -> 8
D72: 2018 | E72: =Data!T72 -> 8
D73: 2019 | E73: =Data!T73 -> 10
D74: 2020 | E74: =Data!T74 -> 8
D75: 2021 | E75: =Data!T75 -> 8
D76: 2022 | E76: =Data!T76 -> 9
D77: 2023 | E77: =Data!T77 -> 9
D78: 2024 | E78: =Data!T78 -> 9
B79: 8 | C79: PT Asuransi Jiwa BCA | D79: 2014 | E79: =Data!T79 -> 0
D80: 2015 | E80: =Data!T80 -> 8
D81: 2016 | E81: =Data!T81 -> 7
D82: 2017 | E82: =Data!T82 -> 7
D83: 2018 | E83: =Data!T83 -> 7
D84: 2019 | E84: =Data!T84 -> 7
D85: 2020 | E85: =Data!T85 -> 8
D86: 2021 | E86: =Data!T86 -> 9
D87: 2022 | E87: =Data!T87 -> 8
D88: 2023 | E88: =Data!T88 -> 8
D89: 2024 | E89: =Data!T89 -> 8
B90: 9 | C90: PT Asuransi Jiwa Central Asia Raya | D90: 2014 | E90: =Data!T90 -> 0
D91: 2015 | E91: =Data!T91 -> 6
D92: 2016 | E92: =Data!T92 -> 7
D93: 2017 | E93: =Data!T93 -> 7
D94: 2018 | E94: =Data!T94 -> 7
D95: 2019 | E95: =Data!T95 -> 8
D96: 2020 | E96: =Data!T96 -> 8
D97: 2021 | E97: =Data!T97 -> 6
D98: 2022 | E98: =Data!T98 -> 7
D99: 2023 | E99: =Data!T99 -> 6
D100: 2024 | E100: =Data!T100 -> 7
...

Sheet TA
A1: Sub Sektor | B1: No | C1: Nama Perusahaan | D1: Tahun | E1: Total Aset
A2: Asuransi Jiwa | B2: 1 | C2: Asuransi Jiwa Bersama Bumiputera 1912 | D2: 2014 | E2: =Data!G2 -> 0
D3: 2015 | E3: =Data!G3 -> 0
D4: 2016 | E4: =Data!G4 -> 0
D5: 2017 | E5: =Data!G5 -> 0
D6: 2018 | E6: =Data!G6 -> 0
D7: 2019 | E7: =Data!G7 -> 0
D8: 2020 | E8: =Data!G8 -> 0
D9: 2021 | E9: =Data!G9 -> 0
D10: 2022 | E10: =Data!G10 -> 0
D11: 2023 | E11: =Data!G11 -> 0
D12: 2024 | E12: =Data!G12 -> 0
B13: 2 | C13: PT AIA Financial | D13: 2014 | E13: =Data!G13 -> 0
D14: 2015 | E14: =Data!G14 -> 31860954000000
D15: 2016 | E15: =Data!G15 -> 35767906000000
D16: 2017 | E16: =Data!G16 -> 44937292000000
D17: 2018 | E17: =Data!G17 -> 46562563000000
D18: 2019 | E18: =Data!G18 -> 50043024000000
D19: 2020 | E19: =Data!G19 -> 53134780000000
D20: 2021 | E20: =Data!G20 -> 52330016000000
D21: 2022 | E21: =Data!G21 -> 44912325000000
D22: 2023 | E22: =Data!G22 -> 41785302000000
D23: 2024 | E23: =Data!G23 -> 39899482000000
B24: 3 | C24: PT Asuransi Allianz Life Indonesia | D24: 2014 | E24: =Data!G24 -> 0
D25: 2015 | E25: =Data!G25 -> 27635118000000
D26: 2016 | E26: =Data!G26 -> 30294789000000
D27: 2017 | E27: =Data!G27 -> 35751863000000
D28: 2018 | E28: =Data!G28 -> 35266933000000
D29: 2019 | E29: =Data!G29 -> 38345233000000
D30: 2020 | E30: =Data!G30 -> 41166712000000
D31: 2021 | E31: =Data!G31 -> 42808931000000
D32: 2022 | E32: =Data!G32 -> 41194961000000
D33: 2023 | E33: =Data!G33 -> 40147448000000
D34: 2024 | E34: =Data!G34 -> 39131978000000
B35: 4 | C35: PT Asuransi Allianz Life Syariah Indonesia | D35: 2014 | E35: =Data!G35 -> 0
D36: 2015 | E36: =Data!G36 -> 0
D37: 2016 | E37: =Data!G37 -> 0
D38: 2017 | E38: =Data!G38 -> 0
D39: 2018 | E39: =Data!G39 -> 0
D40: 2019 | E40: =Data!G40 -> 0
D41: 2020 | E41: =Data!G41 -> 0
D42: 2021 | E42: =Data!G42 -> 0
D43: 2022 | E43: =Data!G43 -> 4337827000000
D44: 2023 | E44: =Data!G44 -> 3620310000000
D45: 2024 | E45: =Data!G45 -> 3339322000000
B46: 5 | C46: PT Asuransi BRI Life | D46: 2014 | E46: =Data!G46 -> 0
D47: 2015 | E47: =Data!G47 -> 4933308738000
D48: 2016 | E48: =Data!G48 -> 6176329027000
D49: 2017 | E49: =Data!G49 -> 8162691116000
D50: 2018 | E50: =Data!G50 -> 9356504263000
D51: 2019 | E51: =Data!G51 -> 11084971000000
D52: 2020 | E52: =Data!G52 -> 13044264000000
D53: 2021 | E53: =Data!G53 -> 18260736000000
D54: 2022 | E54: =Data!G54 -> 21494817000000
D55: 2023 | E55: =Data!G55 -> 23552167000000
D56: 2024 | E56: =Data!G56 -> 0
B57: 6 | C57: PT Asuransi Ciputra Indonesia | D57: 2014 | E57: =Data!G57 -> 0
D58: 2015 | E58: =Data!G58 -> 0
D59: 2016 | E59: =Data!G59 -> 98507000000
D60: 2017 | E60: =Data!G60 -> 116479000000
D61: 2018 | E61: =Data!G61 -> 152680000000
D62: 2019 | E62: =Data!G62 -> 214472000000
D63: 2020 | E63: =Data!G63 -> 278255000000
D64: 2021 | E64: =Data!G64 -> 384372000000
D65: 2022 | E65: =Data!G65 -> 517439000000
D66: 2023 | E66: =Data!G66 -> 714057000000
D67: 2024 | E67: =Data!G67 -> 997332000000
B68: 7 | C68: PT Asuransi Jiwa Astra | D68: 2014 | E68: =Data!G68 -> 0
D69: 2015 | E69: =Data!G69 -> 1899837000000
D70: 2016 | E70: =Data!G70 -> 3802688000000
D71: 2017 | E71: =Data!G71 -> 4315435000000
D72: 2018 | E72: =Data!G72 -> 5004717000000
D73: 2019 | E73: =Data!G73 -> 5901298000000
D74: 2020 | E74: =Data!G74 -> 6587066000000
D75: 2021 | E75: =Data!G75 -> 7092935000000
D76: 2022 | E76: =Data!G76 -> 7345755000000
D77: 2023 | E77: =Data!G77 -> 7501061000000
D78: 2024 | E78: =Data!G78 -> 6806055000000
B79: 8 | C79: PT Asuransi Jiwa BCA | D79: 2014 | E79: =Data!G79 -> 0
D80: 2015 | E80: =Data!G80 -> 281282000000
D81: 2016 | E81: =Data!G81 -> 385447000000
D82: 2017 | E82: =Data!G82 -> 842122000000
D83: 2018 | E83: =Data!G83 -> 902876000000
D84: 2019 | E84: =Data!G84 -> 1154689000000
D85: 2020 | E85: =Data!G85 -> 1467896000000
D86: 2021 | E86: =Data!G86 -> 1930213000000
D87: 2022 | E87: =Data!G87 -> 2347921000000
D88: 2023 | E88: =Data!G88 -> 2878724000000
D89: 2024 | E89: =Data!G89 -> 3339666000000
B90: 9 | C90: PT Asuransi Jiwa Central Asia Raya | D90: 2014 | E90: =Data!G90 -> 0
D91: 2015 | E91: =Data!G91 -> 4598462000000
D92: 2016 | E92: =Data!G92 -> 5298273000000
D93: 2017 | E93: =Data!G93 -> 5618666000000
D94: 2018 | E94: =Data!G94 -> 6696353000000
D95: 2019 | E95: =Data!G95 -> 8158087000000
D96: 2020 | E96: =Data!G96 -> 8569933000000
D97: 2021 | E97: =Data!G97 -> 10111397000000
D98: 2022 | E98: =Data!G98 -> 10357588000000
D99: 2023 | E99: =Data!G99 -> 11033985000000
D100: 2024 | E100: =Data!G100 -> 11181540000000
...

Sheet PR
A1: Sub Sektor | B1: No | C1: Nama Perusahaan | D1: Tahun | E1: Pendapatan | F1: Tingkat Pertumbuhan
A2: Asuransi Jiwa | B2: 1 | C2: Asuransi Jiwa Bersama Bumiputera 1912 | D2: 2014 | E2: =Data!L2 -> 0 | F2: =IFERROR((E2-E1)/E1,0) -> 0
D3: 2015 | E3: =Data!L3 -> 0 | F3: =IFERROR((E3-E2)/E2,0) -> 0
D4: 2016 | E4: =Data!L4 -> 0 | F4: =IFERROR((E4-E3)/E3,0) -> 0
D5: 2017 | E5: =Data!L5 -> 0 | F5: =IFERROR((E5-E4)/E4,0) -> 0
D6: 2018 | E6: =Data!L6 -> 0 | F6: =IFERROR((E6-E5)/E5,0) -> 0
D7: 2019 | E7: =Data!L7 -> 0 | F7: =IFERROR((E7-E6)/E6,0) -> 0
D8: 2020 | E8: =Data!L8 -> 0 | F8: =IFERROR((E8-E7)/E7,0) -> 0
D9: 2021 | E9: =Data!L9 -> 0 | F9: =IFERROR((E9-E8)/E8,0) -> 0
D10: 2022 | E10: =Data!L10 -> 0 | F10: =IFERROR((E10-E9)/E9,0) -> 0
D11: 2023 | E11: =Data!L11 -> 0 | F11: =IFERROR((E11-E10)/E10,0) -> 0
D12: 2024 | E12: =Data!L12 -> 0 | F12: =IFERROR((E12-E11)/E11,0) -> 0
B13: 2 | C13: PT AIA Financial | D13: 2014 | E13: =Data!L13 -> 11948691000000 | F13: =IFERROR((E13-E12)/E12,0) -> 0
D14: 2015 | E14: =Data!L14 -> 8985907000000 | F14: =IFERROR((E14-E13)/E13,0) -> -0.24795888
D15: 2016 | E15: =Data!L15 -> 13264521000000 | F15: =IFERROR((E15-E14)/E14,0) -> 0.47614715
D16: 2017 | E16: =Data!L16 -> 15523134000000 | F16: =IFERROR((E16-E15)/E15,0) -> 0.17027475
D17: 2018 | E17: =Data!L17 -> 12786352000000 | F17: =IFERROR((E17-E16)/E16,0) -> -0.17630344
D18: 2019 | E18: =Data!L18 -> 15545577000000 | F18: =IFERROR((E18-E17)/E17,0) -> 0.21579454
D19: 2020 | E19: =Data!L19 -> 15658951000000 | F19: =IFERROR((E19-E18)/E18,0) -> 0.0072930069
D20: 2021 | E20: =Data!L20 -> 15671921000000 | F20: =IFERROR((E20-E19)/E19,0) -> 0.00082828026
D21: 2022 | E21: =Data!L21 -> 11948182000000 | F21: =IFERROR((E21-E20)/E20,0) -> -0.23760578
D22: 2023 | E22: =Data!L22 -> 12931853000000 | F22: =IFERROR((E22-E21)/E21,0) -> 0.08232809
D23: 2024 | E23: =Data!L23 -> 10095098000000 | F23: =IFERROR((E23-E22)/E22,0) -> -0.21936183
B24: 3 | C24: PT Asuransi Allianz Life Indonesia | D24: 2014 | E24: =Data!L24 -> 12354658000000 | F24: =IFERROR((E24-E23)/E23,0) -> 0.22382745
D25: 2015 | E25: =Data!L25 -> 8593467000000 | F25: =IFERROR((E25-E24)/E24,0) -> -0.30443506
D26: 2016 | E26: =Data!L26 -> 11372680000000 | F26: =IFERROR((E26-E25)/E25,0) -> 0.32340998
D27: 2017 | E27: =Data!L27 -> 13302120000000 | F27: =IFERROR((E27-E26)/E26,0) -> 0.1696557
D28: 2018 | E28: =Data!L28 -> 10531156000000 | F28: =IFERROR((E28-E27)/E27,0) -> -0.20830995
D29: 2019 | E29: =Data!L29 -> 15153459000000 | F29: =IFERROR((E29-E28)/E28,0) -> 0.43891696
D30: 2020 | E30: =Data!L30 -> 18812789000000 | F30: =IFERROR((E30-E29)/E29,0) -> 0.2414848
D31: 2021 | E31: =Data!L31 -> 20725660000000 | F31: =IFERROR((E31-E30)/E30,0) -> 0.10167929
D32: 2022 | E32: =Data!L32 -> 14203983000000 | F32: =IFERROR((E32-E31)/E31,0) -> -0.31466679
D33: 2023 | E33: =Data!L33 -> 17375945000000 | F33: =IFERROR((E33-E32)/E32,0) -> 0.22331497
D34: 2024 | E34: =Data!L34 -> 18185132000000 | F34: =IFERROR((E34-E33)/E33,0) -> 0.046569381
B35: 4 | C35: PT Asuransi Allianz Life Syariah Indonesia | D35: 2014 | E35: =Data!L35 -> 0 | F35: 0
D36: 2015 | E36: =Data!L36 -> 0 | F36: =IFERROR((E36-E35)/E35,0) -> 0
D37: 2016 | E37: =Data!L37 -> 0 | F37: =IFERROR((E37-E36)/E36,0) -> 0
D38: 2017 | E38: =Data!L38 -> 0 | F38: =IFERROR((E38-E37)/E37,0) -> 0
D39: 2018 | E39: =Data!L39 -> 0 | F39: =IFERROR((E39-E38)/E38,0) -> 0
D40: 2019 | E40: =Data!L40 -> 0 | F40: =IFERROR((E40-E39)/E39,0) -> 0
D41: 2020 | E41: =Data!L41 -> 0 | F41: =IFERROR((E41-E40)/E40,0) -> 0
D42: 2021 | E42: =Data!L42 -> 0 | F42: =IFERROR((E42-E41)/E41,0) -> 0
D43: 2022 | E43: =Data!L43 -> 1070003000000 | F43: =IFERROR((E43-E42)/E42,0) -> 0
D44: 2023 | E44: =Data!L44 -> 1217667000000 | F44: =IFERROR((E44-E43)/E43,0) -> 0.13800335
D45: 2024 | E45: =Data!L45 -> 1130418000000 | F45: =IFERROR((E45-E44)/E44,0) -> -0.071652595
B46: 5 | C46: PT Asuransi BRI Life | D46: 2014 | E46: =Data!L46 -> 0 | F46: =IFERROR((E46-E45)/E45,0) -> -1
D47: 2015 | E47: =Data!L47 -> 0 | F47: =IFERROR((E47-E46)/E46,0) -> 0
D48: 2016 | E48: =Data!L48 -> 3542155857000 | F48: =IFERROR((E48-E47)/E47,0) -> 0
D49: 2017 | E49: =Data!L49 -> 4403365381000 | F49: =IFERROR((E49-E48)/E48,0) -> 0.24313146
D50: 2018 | E50: =Data!L50 -> 4872269263000 | F50: =IFERROR((E50-E49)/E49,0) -> 0.10648762
D51: 2019 | E51: =Data!L51 -> 5671048000000 | F51: =IFERROR((E51-E50)/E50,0) -> 0.16394388
D52: 2020 | E52: =Data!L52 -> 6379851000000 | F52: =IFERROR((E52-E51)/E51,0) -> 0.12498625
D53: 2021 | E53: =Data!L53 -> 7264440000000 | F53: =IFERROR((E53-E52)/E52,0) -> 0.13865355
D54: 2022 | E54: =Data!L54 -> 9141344000000 | F54: =IFERROR((E54-E53)/E53,0) -> 0.25836871
D55: 2023 | E55: =Data!L55 -> 9194450000000 | F55: =IFERROR((E55-E54)/E54,0) -> 0.0058094302
D56: 2024 | E56: =Data!L56 -> 0 | F56: =IFERROR((E56-E55)/E55,0) -> -1
B57: 6 | C57: PT Asuransi Ciputra Indonesia | D57: 2014 | E57: =Data!L57 -> 0 | F57: =IFERROR((E57-E56)/E56,0) -> 0
D58: 2015 | E58: =Data!L58 -> 0 | F58: =IFERROR((E58-E57)/E57,0) -> 0
D59: 2016 | E59: =Data!L59 -> 3041000000 | F59: =IFERROR((E59-E58)/E58,0) -> 0
D60: 2017 | E60: =Data!L60 -> 13468000000 | F60: =IFERROR((E60-E59)/E59,0) -> 3.4288063
D61: 2018 | E61: =Data!L61 -> 59888000000 | F61: =IFERROR((E61-E60)/E60,0) -> 3.4466884
D62: 2019 | E62: =Data!L62 -> 104287000000 | F62: =IFERROR((E62-E61)/E61,0) -> 0.74136722
D63: 2020 | E63: =Data!L63 -> 110130000000 | F63: =IFERROR((E63-E62)/E62,0) -> 0.056028076
D64: 2021 | E64: =Data!L64 -> 244885000000 | F64: =IFERROR((E64-E63)/E63,0) -> 1.2235994
D65: 2022 | E65: =Data!L65 -> 334681000000 | F65: =IFERROR((E65-E64)/E64,0) -> 0.3666864
D66: 2023 | E66: =Data!L66 -> 467731000000 | F66: =IFERROR((E66-E65)/E65,0) -> 0.39754273
D67: 2024 | E67: =Data!L67 -> 587025000000 | F67: =IFERROR((E67-E66)/E66,0) -> 0.25504831
B68: 7 | C68: PT Asuransi Jiwa Astra | D68: 2014 | E68: =Data!L68 -> 613328000000 | F68: =IFERROR((E68-E67)/E67,0) -> 0.044807291
D69: 2015 | E69: =Data!L69 -> 1310956000000 | F69: =IFERROR((E69-E68)/E68,0) -> 1.1374468
D70: 2016 | E70: =Data!L70 -> 2981581000000 | F70: =IFERROR((E70-E69)/E69,0) -> 1.2743563
D71: 2017 | E71: =Data!L71 -> 3796659000000 | F71: =IFERROR((E71-E70)/E70,0) -> 0.27337107
D72: 2018 | E72: =Data!L72 -> 3611633000000 | F72: =IFERROR((E72-E71)/E71,0) -> -0.0487339
D73: 2019 | E73: =Data!L73 -> 3346426000000 | F73: =IFERROR((E73-E72)/E72,0) -> -0.073431326
D74: 2020 | E74: =Data!L74 -> 3645793000000 | F74: =IFERROR((E74-E73)/E73,0) -> 0.089458724
D75: 2021 | E75: =Data!L75 -> 5769733000000 | F75: =IFERROR((E75-E74)/E74,0) -> 0.58257284
D76: 2022 | E76: =Data!L76 -> 5918222000000 | F76: =IFERROR((E76-E75)/E75,0) -> 0.025735853
D77: 2023 | E77: =Data!L77 -> 6350888000000 | F77: =IFERROR((E77-E76)/E76,0) -> 0.07310743
D78: 2024 | E78: =Data!L78 -> 5855479000000 | F78: =IFERROR((E78-E77)/E77,0) -> -0.078006257
B79: 8 | C79: PT Asuransi Jiwa BCA | D79: 2014 | E79: =Data!L79 -> 17340000000 | F79: =IFERROR((E79-E78)/E78,0) -> -0.99703867
D80: 2015 | E80: =Data!L80 -> 108628000000 | F80: =IFERROR((E80-E79)/E79,0) -> 5.2645905
D81: 2016 | E81: =Data!L81 -> 289387000000 | F81: =IFERROR((E81-E80)/E80,0) -> 1.6640185
D82: 2017 | E82: =Data!L82 -> 445563000000 | F82: =IFERROR((E82-E81)/E81,0) -> 0.5396787
D83: 2018 | E83: =Data!L83 -> 585605000000 | F83: =IFERROR((E83-E82)/E82,0) -> 0.31430348
D84: 2019 | E84: =Data!L84 -> 800269000000 | F84: =IFERROR((E84-E83)/E83,0) -> 0.36656791
D85: 2020 | E85: =Data!L85 -> 991129000000 | F85: =IFERROR((E85-E84)/E84,0) -> 0.23849481
D86: 2021 | E86: =Data!L86 -> 1316137000000 | F86: =IFERROR((E86-E85)/E85,0) -> 0.32791695
D87: 2022 | E87: =Data!L87 -> 1382687000000 | F87: =IFERROR((E87-E86)/E86,0) -> 0.050564645
D88: 2023 | E88: =Data!L88 -> 1576409000000 | F88: =IFERROR((E88-E87)/E87,0) -> 0.14010546
D89: 2024 | E89: =Data!L89 -> 1481484000000 | F89: =IFERROR((E89-E88)/E88,0) -> -0.060215972
B90: 9 | C90: PT Asuransi Jiwa Central Asia Raya | D90: 2014 | E90: =Data!L90 -> 1111447000000 | F90: =IFERROR((E90-E89)/E89,0) -> -0.24977455
D91: 2015 | E91: =Data!L91 -> 1157281000000 | F91: =IFERROR((E91-E90)/E90,0) -> 0.041238134
D92: 2016 | E92: =Data!L92 -> 1932573000000 | F92: =IFERROR((E92-E91)/E91,0) -> 0.66992545
D93: 2017 | E93: =Data!L93 -> 2584123000000 | F93: =IFERROR((E93-E92)/E92,0) -> 0.33714121
D94: 2018 | E94: =Data!L94 -> 2626306000000 | F94: =IFERROR((E94-E93)/E93,0) -> 0.016323913
D95: 2019 | E95: =Data!L95 -> 3015912000000 | F95: =IFERROR((E95-E94)/E94,0) -> 0.14834753
D96: 2020 | E96: =Data!L96 -> 2727108000000 | F96: =IFERROR((E96-E95)/E95,0) -> -0.095760088
D97: 2021 | E97: =Data!L97 -> 2794098000000 | F97: =IFERROR((E97-E96)/E96,0) -> 0.024564484
D98: 2022 | E98: =Data!L98 -> 2587182000000 | F98: =IFERROR((E98-E97)/E97,0) -> -0.074054668
D99: 2023 | E99: =Data!L99 -> 2996848000000 | F99: =IFERROR((E99-E98)/E98,0) -> 0.15834448
D100: 2024 | E100: =Data!L100 -> 2435099000000 | F100: =IFERROR((E100-E99)/E99,0) -> -0.18744661
...

Sheet Z Score
A1: Sub Sektor | B1: No | C1: Nama Perusahaan | D1: Tahun | E1: Aset Lancar | F1: Hutang Lancar | G1: Working Capital | H1: Total Aset | I1: X1 | J1: Laba Di Tahan | K1: Total Aset | L1: X2 | M1: EBIT | N1: Total Aset | O1: X3 | P1: Total Ekuitas | Q1: Total Hutang | R1: X4 | S1: Z-Score
A2: Asuransi Jiwa | B2: 1 | C2: Asuransi Jiwa Bersama Bumiputera 1912 | D2: 2014 | E2: =Data!F2 -> 0 | F2: =Data!H2 -> 0 | G2: =E2-F2 -> 0 | H2: =Data!G2 -> 0 | I2: =IFERROR(6.56*(G2/H2),0) -> 0 | J2: =Data!J2 -> 0 | K2: =H2 -> 0 | L2: =IFERROR(3.26*(J2/K2),0) -> 0 | M2: =Data!M2 -> 0 | N2: =K2 -> 0 | O2: =IFERROR(6.72*(M2/N2),0) -> 0 | P2: =Data!K2 -> 0 | Q2: =Data!I2 -> 0 | R2: =IFERROR(1.05*(P2/Q2),0) -> 0 | S2: =IFERROR(I2+L2+O2+R2,0) -> 0
D3: 2015 | E3: =Data!F3 -> 0 | F3: =Data!H3 -> 0 | G3: =E3-F3 -> 0 | H3: =Data!G3 -> 0 | I3: =IFERROR(6.56*(G3/H3),0) -> 0 | J3: =Data!J3 -> 0 | K3: =H3 -> 0 | L3: =IFERROR(3.26*(J3/K3),0) -> 0 | M3: =Data!M3 -> 0 | N3: =K3 -> 0 | O3: =IFERROR(6.72*(M3/N3),0) -> 0 | P3: =Data!K3 -> 0 | Q3: =Data!I3 -> 0 | R3: =IFERROR(1.05*(P3/Q3),0) -> 0 | S3: =IFERROR(I3+L3+O3+R3,0) -> 0
D4: 2016 | E4: =Data!F4 -> 0 | F4: =Data!H4 -> 0 | G4: =E4-F4 -> 0 | H4: =Data!G4 -> 0 | I4: =IFERROR(6.56*(G4/H4),0) -> 0 | J4: =Data!J4 -> 0 | K4: =H4 -> 0 | L4: =IFERROR(3.26*(J4/K4),0) -> 0 | M4: =Data!M4 -> 0 | N4: =K4 -> 0 | O4: =IFERROR(6.72*(M4/N4),0) -> 0 | P4: =Data!K4 -> 0 | Q4: =Data!I4 -> 0 | R4: =IFERROR(1.05*(P4/Q4),0) -> 0 | S4: =IFERROR(I4+L4+O4+R4,0) -> 0
D5: 2017 | E5: =Data!F5 -> 0 | F5: =Data!H5 -> 0 | G5: =E5-F5 -> 0 | H5: =Data!G5 -> 0 | I5: =IFERROR(6.56*(G5/H5),0) -> 0 | J5: =Data!J5 -> 0 | K5: =H5 -> 0 | L5: =IFERROR(3.26*(J5/K5),0) -> 0 | M5: =Data!M5 -> 0 | N5: =K5 -> 0 | O5: =IFERROR(6.72*(M5/N5),0) -> 0 | P5: =Data!K5 -> 0 | Q5: =Data!I5 -> 0 | R5: =IFERROR(1.05*(P5/Q5),0) -> 0 | S5: =IFERROR(I5+L5+O5+R5,0) -> 0
D6: 2018 | E6: =Data!F6 -> 0 | F6: =Data!H6 -> 0 | G6: =E6-F6 -> 0 | H6: =Data!G6 -> 0 | I6: =IFERROR(6.56*(G6/H6),0) -> 0 | J6: =Data!J6 -> 0 | K6: =H6 -> 0 | L6: =IFERROR(3.26*(J6/K6),0) -> 0 | M6: =Data!M6 -> 0 | N6: =K6 -> 0 | O6: =IFERROR(6.72*(M6/N6),0) -> 0 | P6: =Data!K6 -> 0 | Q6: =Data!I6 -> 0 | R6: =IFERROR(1.05*(P6/Q6),0) -> 0 | S6: =IFERROR(I6+L6+O6+R6,0) -> 0
D7: 2019 | E7: =Data!F7 -> 0 | F7: =Data!H7 -> 0 | G7: =E7-F7 -> 0 | H7: =Data!G7 -> 0 | I7: =IFERROR(6.56*(G7/H7),0) -> 0 | J7: =Data!J7 -> 0 | K7: =H7 -> 0 | L7: =IFERROR(3.26*(J7/K7),0) -> 0 | M7: =Data!M7 -> 0 | N7: =K7 -> 0 | O7: =IFERROR(6.72*(M7/N7),0) -> 0 | P7: =Data!K7 -> 0 | Q7: =Data!I7 -> 0 | R7: =IFERROR(1.05*(P7/Q7),0) -> 0 | S7: =IFERROR(I7+L7+O7+R7,0) -> 0
D8: 2020 | E8: =Data!F8 -> 0 | F8: =Data!H8 -> 0 | G8: =E8-F8 -> 0 | H8: =Data!G8 -> 0 | I8: =IFERROR(6.56*(G8/H8),0) -> 0 | J8: =Data!J8 -> 0 | K8: =H8 -> 0 | L8: =IFERROR(3.26*(J8/K8),0) -> 0 | M8: =Data!M8 -> 0 | N8: =K8 -> 0 | O8: =IFERROR(6.72*(M8/N8),0) -> 0 | P8: =Data!K8 -> 0 | Q8: =Data!I8 -> 0 | R8: =IFERROR(1.05*(P8/Q8),0) -> 0 | S8: =IFERROR(I8+L8+O8+R8,0) -> 0
D9: 2021 | E9: =Data!F9 -> 0 | F9: =Data!H9 -> 0 | G9: =E9-F9 -> 0 | H9: =Data!G9 -> 0 | I9: =IFERROR(6.56*(G9/H9),0) -> 0 | J9: =Data!J9 -> 0 | K9: =H9 -> 0 | L9: =IFERROR(3.26*(J9/K9),0) -> 0 | M9: =Data!M9 -> 0 | N9: =K9 -> 0 | O9: =IFERROR(6.72*(M9/N9),0) -> 0 | P9: =Data!K9 -> 0 | Q9: =Data!I9 -> 0 | R9: =IFERROR(1.05*(P9/Q9),0) -> 0 | S9: =IFERROR(I9+L9+O9+R9,0) -> 0
D10: 2022 | E10: =Data!F10 -> 0 | F10: =Data!H10 -> 0 | G10: =E10-F10 -> 0 | H10: =Data!G10 -> 0 | I10: =IFERROR(6.56*(G10/H10),0) -> 0 | J10: =Data!J10 -> 0 | K10: =H10 -> 0 | L10: =IFERROR(3.26*(J10/K10),0) -> 0 | M10: =Data!M10 -> 0 | N10: =K10 -> 0 | O10: =IFERROR(6.72*(M10/N10),0) -> 0 | P10: =Data!K10 -> 0 | Q10: =Data!I10 -> 0 | R10: =IFERROR(1.05*(P10/Q10),0) -> 0 | S10: =IFERROR(I10+L10+O10+R10,0) -> 0
D11: 2023 | E11: =Data!F11 -> 0 | F11: =Data!H11 -> 0 | G11: =E11-F11 -> 0 | H11: =Data!G11 -> 0 | I11: =IFERROR(6.56*(G11/H11),0) -> 0 | J11: =Data!J11 -> 0 | K11: =H11 -> 0 | L11: =IFERROR(3.26*(J11/K11),0) -> 0 | M11: =Data!M11 -> 0 | N11: =K11 -> 0 | O11: =IFERROR(6.72*(M11/N11),0) -> 0 | P11: =Data!K11 -> 0 | Q11: =Data!I11 -> 0 | R11: =IFERROR(1.05*(P11/Q11),0) -> 0 | S11: =IFERROR(I11+L11+O11+R11,0) -> 0
D12: 2024 | E12: =Data!F12 -> 0 | F12: =Data!H12 -> 0 | G12: =E12-F12 -> 0 | H12: =Data!G12 -> 0 | I12: =IFERROR(6.56*(G12/H12),0) -> 0 | J12: =Data!J12 -> 0 | K12: =H12 -> 0 | L12: =IFERROR(3.26*(J12/K12),0) -> 0 | M12: =Data!M12 -> 0 | N12: =K12 -> 0 | O12: =IFERROR(6.72*(M12/N12),0) -> 0 | P12: =Data!K12 -> 0 | Q12: =Data!I12 -> 0 | R12: =IFERROR(1.05*(P12/Q12),0) -> 0 | S12: =IFERROR(I12+L12+O12+R12,0) -> 0
B13: 2 | C13: PT AIA Financial | D13: 2014 | E13: =Data!F13 -> 0 | F13: =Data!H13 -> 0 | G13: =E13-F13 -> 0 | H13: =Data!G13 -> 0 | I13: =IFERROR(6.56*(G13/H13),0) -> 0 | J13: =Data!J13 -> 0 | K13: =H13 -> 0 | L13: =IFERROR(3.26*(J13/K13),0) -> 0 | M13: =Data!M13 -> 0 | N13: =K13 -> 0 | O13: =IFERROR(6.72*(M13/N13),0) -> 0 | P13: =Data!K13 -> 0 | Q13: =Data!I13 -> 0 | R13: =IFERROR(1.05*(P13/Q13),0) -> 0 | S13: =IFERROR(I13+L13+O13+R13,0) -> 0
D14: 2015 | E14: =Data!F14 -> 951139000000 | F14: =Data!H14 -> 1833519000000 | G14: =E14-F14 -> -882380000000 | H14: =Data!G14 -> 31860954000000 | I14: =IFERROR(6.56*(G14/H14),0) -> -0.18167732 | J14: =Data!J14 -> 5786895000000 | K14: =H14 -> 31860954000000 | L14: =IFERROR(3.26*(J14/K14),0) -> 0.59211277 | M14: =Data!M14 -> 1649123000000 | N14: =K14 -> 31860954000000 | O14: =IFERROR(6.72*(M14/N14),0) -> 0.3478272 | P14: =Data!K14 -> 6569253000000 | Q14: =Data!I14 -> 25291701000000 | R14: =IFERROR(1.05*(P14/Q14),0) -> 0.27272644 | S14: =IFERROR(I14+L14+O14+R14,0) -> 1.0309891
D15: 2016 | E15: =Data!F15 -> 1118793000000 | F15: =Data!H15 -> 2103474000000 | G15: =E15-F15 -> -984681000000 | H15: =Data!G15 -> 35767906000000 | I15: =IFERROR(6.56*(G15/H15),0) -> -0.18059507 | J15: =Data!J15 -> 6850440000000 | K15: =H15 -> 35767906000000 | L15: =IFERROR(3.26*(J15/K15),0) -> 0.62437075 | M15: =Data!M15 -> 1034240000000 | N15: =K15 -> 35767906000000 | O15: =IFERROR(6.72*(M15/N15),0) -> 0.19431087 | P15: =Data!K15 -> 7766364000000 | Q15: =Data!I15 -> 28001542000000 | R15: =IFERROR(1.05*(P15/Q15),0) -> 0.29122261 | S15: =IFERROR(I15+L15+O15+R15,0) -> 0.92930916
D16: 2017 | E16: =Data!F16 -> 1287320000000 | F16: =Data!H16 -> 3116639000000 | G16: =E16-F16 -> -1829319000000 | H16: =Data!G16 -> 44937292000000 | I16: =IFERROR(6.56*(G16/H16),0) -> -0.26704619 | J16: =Data!J16 -> 7239986000000 | K16: =H16 -> 44937292000000 | L16: =IFERROR(3.26*(J16/K16),0) -> 0.52522868 | M16: =Data!M16 -> 542068000000 | N16: =K16 -> 44937292000000 | O16: =IFERROR(6.72*(M16/N16),0) -> 0.081061782 | P16: =Data!K16 -> 10561914000000 | Q16: =Data!I16 -> 34375378000000 | R16: =IFERROR(1.05*(P16/Q16),0) -> 0.32261492 | S16: =IFERROR(I16+L16+O16+R16,0) -> 0.66185918
D17: 2018 | E17: =Data!F17 -> 1509812000000 | F17: =Data!H17 -> 3329580000000 | G17: =E17-F17 -> -1819768000000 | H17: =Data!G17 -> 46562563000000 | I17: =IFERROR(6.56*(G17/H17),0) -> -0.25637932 | J17: =Data!J17 -> 8566661000000 | K17: =H17 -> 46562563000000 | L17: =IFERROR(3.26*(J17/K17),0) -> 0.59978045 | M17: =Data!M17 -> 2150147000000 | N17: =K17 -> 46562563000000 | O17: =IFERROR(6.72*(M17/N17),0) -> 0.31031341 | P17: =Data!K17 -> 11027227000000 | Q17: =Data!I17 -> 35535336000000 | R17: =IFERROR(1.05*(P17/Q17),0) -> 0.32583309 | S17: =IFERROR(I17+L17+O17+R17,0) -> 0.97954763
D18: 2019 | E18: =Data!F18 -> 2019822000000 | F18: =Data!H18 -> 3399335000000 | G18: =E18-F18 -> -1379513000000 | H18: =Data!G18 -> 50043024000000 | I18: =IFERROR(6.56*(G18/H18),0) -> -0.1808365 | J18: =Data!J18 -> 7904525000000 | K18: =H18 -> 50043024000000 | L18: =IFERROR(3.26*(J18/K18),0) -> 0.51493194 | M18: =Data!M18 -> 449893000000 | N18: =K18 -> 50043024000000 | O18: =IFERROR(6.72*(M18/N18),0) -> 0.060413634 | P18: =Data!K18 -> 11870589000000 | Q18: =Data!I18 -> 38172435000000 | R18: =IFERROR(1.05*(P18/Q18),0) -> 0.32652144 | S18: =IFERROR(I18+L18+O18+R18,0) -> 0.72103052
D19: 2020 | E19: =Data!F19 -> 2189572000000 | F19: =Data!H19 -> 3640926000000 | G19: =E19-F19 -> -1451354000000 | H19: =Data!G19 -> 53134780000000 | I19: =IFERROR(6.56*(G19/H19),0) -> -0.17918362 | J19: =Data!J19 -> 7057134000000 | K19: =H19 -> 53134780000000 | L19: =IFERROR(3.26*(J19/K19),0) -> 0.43297924 | M19: =Data!M19 -> 718592000000 | N19: =K19 -> 53134780000000 | O19: =IFERROR(6.72*(M19/N19),0) -> 0.09088093 | P19: =Data!K19 -> 11761575000000 | Q19: =Data!I19 -> 41373205000000 | R19: =IFERROR(1.05*(P19/Q19),0) -> 0.29849401 | S19: =IFERROR(I19+L19+O19+R19,0) -> 0.64317056
D20: 2021 | E20: =Data!F20 -> 2332200000000 | F20: =Data!H20 -> 3465695000000 | G20: =E20-F20 -> -1133495000000 | H20: =Data!G20 -> 52330016000000 | I20: =IFERROR(6.56*(G20/H20),0) -> -0.14209297 | J20: =Data!J20 -> 6523045000000 | K20: =H20 -> 52330016000000 | L20: =IFERROR(3.26*(J20/K20),0) -> 0.40636576 | M20: =Data!M20 -> 1143810000000 | N20: =K20 -> 52330016000000 | O20: =IFERROR(6.72*(M20/N20),0) -> 0.14688326 | P20: =Data!K20 -> 11856333000000 | Q20: =Data!I20 -> 40473683000000 | R20: =IFERROR(1.05*(P20/Q20),0) -> 0.30758628 | S20: =IFERROR(I20+L20+O20+R20,0) -> 0.71874233
D21: 2022 | E21: =Data!F21 -> 2553937000000 | F21: =Data!H21 -> 3771309000000 | G21: =E21-F21 -> -1217372000000 | H21: =Data!G21 -> 44912325000000 | I21: =IFERROR(6.56*(G21/H21),0) -> -0.17781222 | J21: =Data!J21 -> 5603024000000 | K21: =H21 -> 44912325000000 | L21: =IFERROR(3.26*(J21/K21),0) -> 0.40670035 | M21: =Data!M21 -> 2655031000000 | N21: =K21 -> 44912325000000 | O21: =IFERROR(6.72*(M21/N21),0) -> 0.39725862 | P21: =Data!K21 -> 8229889000000 | Q21: =Data!I21 -> 36682436000000 | R21: =IFERROR(1.05*(P21/Q21),0) -> 0.23557278 | S21: =IFERROR(I21+L21+O21+R21,0) -> 0.86171953
D22: 2023 | E22: =Data!F22 -> 2217504000000 | F22: =Data!H22 -> 3324784000000 | G22: =E22-F22 -> -1107280000000 | H22: =Data!G22 -> 41785302000000 | I22: =IFERROR(6.56*(G22/H22),0) -> -0.17383521 | J22: =Data!J22 -> 6019271000000 | K22: =H22 -> 41785302000000 | L22: =IFERROR(3.26*(J22/K22),0) -> 0.46961067 | M22: =Data!M22 -> 1674911000000 | N22: =K22 -> 41785302000000 | O22: =IFERROR(6.72*(M22/N22),0) -> 0.2693627 | P22: =Data!K22 -> 8048626000000 | Q22: =Data!I22 -> 33736676000000 | R22: =IFERROR(1.05*(P22/Q22),0) -> 0.25050059 | S22: =IFERROR(I22+L22+O22+R22,0) -> 0.81563875
D23: 2024 | E23: =Data!F23 -> 2234181000000 | F23: =Data!H23 -> 2965577000000 | G23: =E23-F23 -> -731396000000 | H23: =Data!G23 -> 39899482000000 | I23: =IFERROR(6.56*(G23/H23),0) -> -0.12025113 | J23: =Data!J23 -> 7306046000000 | K23: =H23 -> 39899482000000 | L23: =IFERROR(3.26*(J23/K23),0) -> 0.59694284 | M23: =Data!M23 -> 1789193000000 | N23: =K23 -> 39899482000000 | O23: =IFERROR(6.72*(M23/N23),0) -> 0.30134168 | P23: =Data!K23 -> 8912301000000 | Q23: =Data!I23 -> 30987181000000 | R23: =IFERROR(1.05*(P23/Q23),0) -> 0.30199314 | S23: =IFERROR(I23+L23+O23+R23,0) -> 1.0800265
B24: 3 | C24: PT Asuransi Allianz Life Indonesia | D24: 2014 | E24: =Data!F24 -> 0 | F24: =Data!H24 -> 0 | G24: =E24-F24 -> 0 | H24: =Data!G24 -> 0 | I24: =IFERROR(6.56*(G24/H24),0) -> 0 | J24: =Data!J24 -> 0 | K24: =H24 -> 0 | L24: =IFERROR(3.26*(J24/K24),0) -> 0 | M24: =Data!M24 -> 0 | N24: =K24 -> 0 | O24: =IFERROR(6.72*(M24/N24),0) -> 0 | P24: =Data!K24 -> 0 | Q24: =Data!I24 -> 0 | R24: =IFERROR(1.05*(P24/Q24),0) -> 0 | S24: =IFERROR(I24+L24+O24+R24,0) -> 0
D25: 2015 | E25: =Data!F25 -> 688635000000 | F25: =Data!H25 -> 665956000000 | G25: =E25-F25 -> 22679000000 | H25: =Data!G25 -> 27635118000000 | I25: =IFERROR(6.56*(G25/H25),0) -> 0.0053835211 | J25: =Data!J25 -> 3103856000000 | K25: =H25 -> 27635118000000 | L25: =IFERROR(3.26*(J25/K25),0) -> 0.36614899 | M25: =Data!M25 -> 903774000000 | N25: =K25 -> 27635118000000 | O25: =IFERROR(6.72*(M25/N25),0) -> 0.21976969 | P25: =Data!K25 -> 4355995000000 | Q25: =Data!I25 -> 22909265000000 | R25: =IFERROR(1.05*(P25/Q25),0) -> 0.19964825 | S25: =IFERROR(I25+L25+O25+R25,0) -> 0.79095045
D26: 2016 | E26: =Data!F26 -> 937483000000 | F26: =Data!H26 -> 953567000000 | G26: =E26-F26 -> -16084000000 | H26: =Data!G26 -> 30294789000000 | I26: =IFERROR(6.56*(G26/H26),0) -> -0.0034828115 | J26: =Data!J26 -> 3996502000000 | K26: =H26 -> 30294789000000 | L26: =IFERROR(3.26*(J26/K26),0) -> 0.43006065 | M26: =Data!M26 -> 905890000000 | N26: =K26 -> 30294789000000 | O26: =IFERROR(6.72*(M26/N26),0) -> 0.20094482 | P26: =Data!K26 -> 5381290000000 | Q26: =Data!I26 -> 24436046000000 | R26: =IFERROR(1.05*(P26/Q26),0) -> 0.23123031 | S26: =IFERROR(I26+L26+O26+R26,0) -> 0.85875296
D27: 2017 | E27: =Data!F27 -> 1162598000000 | F27: =Data!H27 -> 1244651000000 | G27: =E27-F27 -> -82053000000 | H27: =Data!G27 -> 35751863000000 | I27: =IFERROR(6.56*(G27/H27),0) -> -0.015055654 | J27: =Data!J27 -> 4311634000000 | K27: =H27 -> 35751863000000 | L27: =IFERROR(3.26*(J27/K27),0) -> 0.39315229 | M27: =Data!M27 -> 329564000000 | N27: =K27 -> 35751863000000 | O27: =IFERROR(6.72*(M27/N27),0) -> 0.061945585 | P27: =Data!K27 -> 6030989000000 | Q27: =Data!I27 -> 27527468000000 | R27: =IFERROR(1.05*(P27/Q27),0) -> 0.23004435 | S27: =IFERROR(I27+L27+O27+R27,0) -> 0.67008657
D28: 2018 | E28: =Data!F28 -> 1438688000000 | F28: =Data!H28 -> 1580256000000 | G28: =E28-F28 -> -141568000000 | H28: =Data!G28 -> 35266933000000 | I28: =IFERROR(6.56*(G28/H28),0) -> -0.026333055 | J28: =Data!J28 -> 4737672000000 | K28: =H28 -> 35266933000000 | L28: =IFERROR(3.26*(J28/K28),0) -> 0.43794029 | M28: =Data!M28 -> 899975000000 | N28: =K28 -> 35266933000000 | O28: =IFERROR(6.72*(M28/N28),0) -> 0.17148732 | P28: =Data!K28 -> 5768100000000 | Q28: =Data!I28 -> 27304202000000 | R28: =IFERROR(1.05*(P28/Q28),0) -> 0.22181586 | S28: =IFERROR(I28+L28+O28+R28,0) -> 0.80491041
D29: 2019 | E29: =Data!F29 -> 1975159000000 | F29: =Data!H29 -> 1291778000000 | G29: =E29-F29 -> 683381000000 | H29: =Data!G29 -> 38345233000000 | I29: =IFERROR(6.56*(G29/H29),0) -> 0.116911 | J29: =Data!J29 -> 5161928000000 | K29: =H29 -> 38345233000000 | L29: =IFERROR(3.26*(J29/K29),0) -> 0.43885208 | M29: =Data!M29 -> 1526889000000 | N29: =K29 -> 38345233000000 | O29: =IFERROR(6.72*(M29/N29),0) -> 0.26758721 | P29: =Data!K29 -> 6511324000000 | Q29: =Data!I29 -> 29736010000000 | R29: =IFERROR(1.05*(P29/Q29),0) -> 0.22991956 | S29: =IFERROR(I29+L29+O29+R29,0) -> 1.0532698
D30: 2020 | E30: =Data!F30 -> 2544663000000 | F30: =Data!H30 -> 1443225000000 | G30: =E30-F30 -> 1101438000000 | H30: =Data!G30 -> 41166712000000 | I30: =IFERROR(6.56*(G30/H30),0) -> 0.1755164 | J30: =Data!J30 -> 5998414000000 | K30: =H30 -> 41166712000000 | L30: =IFERROR(3.26*(J30/K30),0) -> 0.47501558 | M30: =Data!M30 -> 1691295000000 | N30: =K30 -> 41166712000000 | O30: =IFERROR(6.72*(M30/N30),0) -> 0.27608477 | P30: =Data!K30 -> 7090980000000 | Q30: =Data!I30 -> 31830554000000 | R30: =IFERROR(1.05*(P30/Q30),0) -> 0.23391139 | S30: =IFERROR(I30+L30+O30+R30,0) -> 1.1605281
D31: 2021 | E31: =Data!F31 -> 2851127000000 | F31: =Data!H31 -> 1539961000000 | G31: =E31-F31 -> 1311166000000 | H31: =Data!G31 -> 42808931000000 | I31: =IFERROR(6.56*(G31/H31),0) -> 0.20092183 | J31: =Data!J31 -> 5949541000000 | K31: =H31 -> 42808931000000 | L31: =IFERROR(3.26*(J31/K31),0) -> 0.45307143 | M31: =Data!M31 -> 561475000000 | N31: =K31 -> 42808931000000 | O31: =IFERROR(6.72*(M31/N31),0) -> 0.088138431 | P31: =Data!K31 -> 6945025000000 | Q31: =Data!I31 -> 33849131000000 | R31: =IFERROR(1.05*(P31/Q31),0) -> 0.21543467 | S31: =IFERROR(I31+L31+O31+R31,0) -> 0.95756636
D32: 2022 | E32: =Data!F32 -> 3412009000000 | F32: =Data!H32 -> 2321280000000 | G32: =E32-F32 -> 1090729000000 | H32: =Data!G32 -> 41194961000000 | I32: =IFERROR(6.56*(G32/H32),0) -> 0.17369072 | J32: =Data!J32 -> 6757463000000 | K32: =H32 -> 41194961000000 | L32: =IFERROR(3.26*(J32/K32),0) -> 0.53475786 | M32: =Data!M32 -> 597200000000 | N32: =K32 -> 41194961000000 | O32: =IFERROR(6.72*(M32/N32),0) -> 0.097419294 | P32: =Data!K32 -> 7208812000000 | Q32: =Data!I32 -> 32037270000000 | R32: =IFERROR(1.05*(P32/Q32),0) -> 0.23626397 | S32: =IFERROR(I32+L32+O32+R32,0) -> 1.0421318
D33: 2023 | E33: =Data!F33 -> 3559943000000 | F33: =Data!H33 -> 2581811000000 | G33: =E33-F33 -> 978132000000 | H33: =Data!G33 -> 40147448000000 | I33: =IFERROR(6.56*(G33/H33),0) -> 0.1598245 | J33: =Data!J33 -> 6154142000000 | K33: =H33 -> 40147448000000 | L33: =IFERROR(3.26*(J33/K33),0) -> 0.4997205 | M33: =Data!M33 -> 372376000000 | N33: =K33 -> 40147448000000 | O33: =IFERROR(6.72*(M33/N33),0) -> 0.062329409 | P33: =Data!K33 -> 6640072000000 | Q33: =Data!I33 -> 31712785000000 | R33: =IFERROR(1.05*(P33/Q33),0) -> 0.21985062 | S33: =IFERROR(I33+L33+O33+R33,0) -> 0.94172504
D34: 2024 | E34: =Data!F34 -> 2585453000000 | F34: =Data!H34 -> 2735029000000 | G34: =E34-F34 -> -149576000000 | H34: =Data!G34 -> 39131978000000 | I34: =IFERROR(6.56*(G34/H34),0) -> -0.025074597 | J34: =Data!J34 -> 6934793000000 | K34: =H34 -> 39131978000000 | L34: =IFERROR(3.26*(J34/K34),0) -> 0.57772253 | M34: =Data!M34 -> 1242464000000 | N34: =K34 -> 39131978000000 | O34: =IFERROR(6.72*(M34/N34),0) -> 0.21336407 | P34: =Data!K34 -> 7301939000000 | Q34: =Data!I34 -> 30372565000000 | R34: =IFERROR(1.05*(P34/Q34),0) -> 0.25243294 | S34: =IFERROR(I34+L34+O34+R34,0) -> 1.0184449
B35: 4 | C35: PT Asuransi Allianz Life Syariah Indonesia | D35: 2014 | E35: =Data!F35 -> 0 | F35: =Data!H35 -> 0 | G35: =E35-F35 -> 0 | H35: =Data!G35 -> 0 | I35: =IFERROR(6.56*(G35/H35),0) -> 0 | J35: =Data!J35 -> 0 | K35: =H35 -> 0 | L35: =IFERROR(3.26*(J35/K35),0) -> 0 | M35: =Data!M35 -> 0 | N35: =K35 -> 0 | O35: =IFERROR(6.72*(M35/N35),0) -> 0 | P35: =Data!K35 -> 0 | Q35: =Data!I35 -> 0 | R35: =IFERROR(1.05*(P35/Q35),0) -> 0 | S35: =IFERROR(I35+L35+O35+R35,0) -> 0
D36: 2015 | E36: =Data!F36 -> 0 | F36: =Data!H36 -> 0 | G36: =E36-F36 -> 0 | H36: =Data!G36 -> 0 | I36: =IFERROR(6.56*(G36/H36),0) -> 0 | J36: =Data!J36 -> 0 | K36: =H36 -> 0 | L36: =IFERROR(3.26*(J36/K36),0) -> 0 | M36: =Data!M36 -> 0 | N36: =K36 -> 0 | O36: =IFERROR(6.72*(M36/N36),0) -> 0 | P36: =Data!K36 -> 0 | Q36: =Data!I36 -> 0 | R36: =IFERROR(1.05*(P36/Q36),0) -> 0 | S36: =IFERROR(I36+L36+O36+R36,0) -> 0
D37: 2016 | E37: =Data!F37 -> 0 | F37: =Data!H37 -> 0 | G37: =E37-F37 -> 0 | H37: =Data!G37 -> 0 | I37: =IFERROR(6.56*(G37/H37),0) -> 0 | J37: =Data!J37 -> 0 | K37: =H37 -> 0 | L37: =IFERROR(3.26*(J37/K37),0) -> 0 | M37: =Data!M37 -> 0 | N37: =K37 -> 0 | O37: =IFERROR(6.72*(M37/N37),0) -> 0 | P37: =Data!K37 -> 0 | Q37: =Data!I37 -> 0 | R37: =IFERROR(1.05*(P37/Q37),0) -> 0 | S37: =IFERROR(I37+L37+O37+R37,0) -> 0
D38: 2017 | E38: =Data!F38 -> 0 | F38: =Data!H38 -> 0 | G38: =E38-F38 -> 0 | H38: =Data!G38 -> 0 | I38: =IFERROR(6.56*(G38/H38),0) -> 0 | J38: =Data!J38 -> 0 | K38: =H38 -> 0 | L38: =IFERROR(3.26*(J38/K38),0) -> 0 | M38: =Data!M38 -> 0 | N38: =K38 -> 0 | O38: =IFERROR(6.72*(M38/N38),0) -> 0 | P38: =Data!K38 -> 0 | Q38: =Data!I38 -> 0 | R38: =IFERROR(1.05*(P38/Q38),0) -> 0 | S38: =IFERROR(I38+L38+O38+R38,0) -> 0
D39: 2018 | E39: =Data!F39 -> 0 | F39: =Data!H39 -> 0 | G39: =E39-F39 -> 0 | H39: =Data!G39 -> 0 | I39: =IFERROR(6.56*(G39/H39),0) -> 0 | J39: =Data!J39 -> 0 | K39: =H39 -> 0 | L39: =IFERROR(3.26*(J39/K39),0) -> 0 | M39: =Data!M39 -> 0 | N39: =K39 -> 0 | O39: =IFERROR(6.72*(M39/N39),0) -> 0 | P39: =Data!K39 -> 0 | Q39: =Data!I39 -> 0 | R39: =IFERROR(1.05*(P39/Q39),0) -> 0 | S39: =IFERROR(I39+L39+O39+R39,0) -> 0
D40: 2019 | E40: =Data!F40 -> 0 | F40: =Data!H40 -> 0 | G40: =E40-F40 -> 0 | H40: =Data!G40 -> 0 | I40: =IFERROR(6.56*(G40/H40),0) -> 0 | J40: =Data!J40 -> 0 | K40: =H40 -> 0 | L40: =IFERROR(3.26*(J40/K40),0) -> 0 | M40: =Data!M40 -> 0 | N40: =K40 -> 0 | O40: =IFERROR(6.72*(M40/N40),0) -> 0 | P40: =Data!K40 -> 0 | Q40: =Data!I40 -> 0 | R40: =IFERROR(1.05*(P40/Q40),0) -> 0 | S40: =IFERROR(I40+L40+O40+R40,0) -> 0
D41: 2020 | E41: =Data!F41 -> 0 | F41: =Data!H41 -> 0 | G41: =E41-F41 -> 0 | H41: =Data!G41 -> 0 | I41: =IFERROR(6.56*(G41/H41),0) -> 0 | J41: =Data!J41 -> 0 | K41: =H41 -> 0 | L41: =IFERROR(3.26*(J41/K41),0) -> 0 | M41: =Data!M41 -> 0 | N41: =K41 -> 0 | O41: =IFERROR(6.72*(M41/N41),0) -> 0 | P41: =Data!K41 -> 0 | Q41: =Data!I41 -> 0 | R41: =IFERROR(1.05*(P41/Q41),0) -> 0 | S41: =IFERROR(I41+L41+O41+R41,0) -> 0
D42: 2021 | E42: =Data!F42 -> 0 | F42: =Data!H42 -> 0 | G42: =E42-F42 -> 0 | H42: =Data!G42 -> 0 | I42: =IFERROR(6.56*(G42/H42),0) -> 0 | J42: =Data!J42 -> 0 | K42: =H42 -> 0 | L42: =IFERROR(3.26*(J42/K42),0) -> 0 | M42: =Data!M42 -> 0 | N42: =K42 -> 0 | O42: =IFERROR(6.72*(M42/N42),0) -> 0 | P42: =Data!K42 -> 0 | Q42: =Data!I42 -> 0 | R42: =IFERROR(1.05*(P42/Q42),0) -> 0 | S42: =IFERROR(I42+L42+O42+R42,0) -> 0
D43: 2022 | E43: =Data!F43 -> 410708000000 | F43: =Data!H43 -> 516180000000 | G43: =E43-F43 -> -105472000000 | H43: =Data!G43 -> 4337827000000 | I43: =IFERROR(6.56*(G43/H43),0) -> -0.15950298 | J43: =Data!J43 -> -184000000 | K43: =H43 -> 4337827000000 | L43: =IFERROR(3.26*(J43/K43),0) -> -0.00013828122 | M43: =Data!M43 -> 382608000000 | N43: =K43 -> 4337827000000 | O43: =IFERROR(6.72*(M43/N43),0) -> 0.59272206 | P43: =Data!K43 -> 1497483000000 | Q43: =Data!I43 -> 891833000000 | R43: =IFERROR(1.05*(P43/Q43),0) -> 1.7630623 | S43: =IFERROR(I43+L43+O43+R43,0) -> 2.1961431
D44: 2023 | E44: =Data!F44 -> 612489000000 | F44: =Data!H44 -> 432783000000 | G44: =E44-F44 -> 179706000000 | H44: =Data!G44 -> 3620310000000 | I44: =IFERROR(6.56*(G44/H44),0) -> 0.32562719 | J44: =Data!J44 -> -22950000000 | K44: =H44 -> 3620310000000 | L44: =IFERROR(3.26*(J44/K44),0) -> -0.02066591 | M44: =Data!M44 -> 221160000000 | N44: =K44 -> 3620310000000 | O44: =IFERROR(6.72*(M44/N44),0) -> 0.41051601 | P44: =Data!K44 -> 958124000000 | Q44: =Data!I44 -> 867595000000 | R44: =IFERROR(1.05*(P44/Q44),0) -> 1.159562 | S44: =IFERROR(I44+L44+O44+R44,0) -> 1.8750393
D45: 2024 | E45: =Data!F45 -> 292352000000 | F45: =Data!H45 -> 370778000000 | G45: =E45-F45 -> -78426000000 | H45: =Data!G45 -> 3339322000000 | I45: =IFERROR(6.56*(G45/H45),0) -> -0.15406557 | J45: =Data!J45 -> 65665000000 | K45: =H45 -> 3339322000000 | L45: =IFERROR(3.26*(J45/K45),0) -> 0.064105199 | M45: =Data!M45 -> 69939000000 | N45: =K45 -> 3339322000000 | O45: =IFERROR(6.72*(M45/N45),0) -> 0.14074416 | P45: =Data!K45 -> 968188000000 | Q45: =Data!I45 -> 913660000000 | R45: =IFERROR(1.05*(P45/Q45),0) -> 1.1126649 | S45: =IFERROR(I45+L45+O45+R45,0) -> 1.1634487
B46: 5 | C46: PT Asuransi BRI Life | D46: 2014 | E46: =Data!F46 -> 0 | F46: =Data!H46 -> 0 | G46: =E46-F46 -> 0 | H46: =Data!G46 -> 0 | I46: =IFERROR(6.56*(G46/H46),0) -> 0 | J46: =Data!J46 -> 0 | K46: =H46 -> 0 | L46: =IFERROR(3.26*(J46/K46),0) -> 0 | M46: =Data!M46 -> 0 | N46: =K46 -> 0 | O46: =IFERROR(6.72*(M46/N46),0) -> 0 | P46: =Data!K46 -> 0 | Q46: =Data!I46 -> 0 | R46: =IFERROR(1.05*(P46/Q46),0) -> 0 | S46: =IFERROR(I46+L46+O46+R46,0) -> 0
D47: 2015 | E47: =Data!F47 -> 468361790000 | F47: =Data!H47 -> 212592184000 | G47: =E47-F47 -> 255769606000 | H47: =Data!G47 -> 4933308738000 | I47: =IFERROR(6.56*(G47/H47),0) -> 0.34010614 | J47: =Data!J47 -> 1179711349000 | K47: =H47 -> 4933308738000 | L47: =IFERROR(3.26*(J47/K47),0) -> 0.7795699 | M47: =Data!M47 -> 0 | N47: =K47 -> 4933308738000 | O47: =IFERROR(6.72*(M47/N47),0) -> 0 | P47: =Data!K47 -> 4933308738000 | Q47: =Data!I47 -> 3608103108000 | R47: =IFERROR(1.05*(P47/Q47),0) -> 1.4356503 | S47: =IFERROR(I47+L47+O47+R47,0) -> 2.5553263
D48: 2016 | E48: =Data!F48 -> 391460041000 | F48: =Data!H48 -> 132766311000 | G48: =E48-F48 -> 258693730000 | H48: =Data!G48 -> 6176329027000 | I48: =IFERROR(6.56*(G48/H48),0) -> 0.27476368 | J48: =Data!J48 -> 1393732890000 | K48: =H48 -> 6176329027000 | L48: =IFERROR(3.26*(J48/K48),0) -> 0.73564235 | M48: =Data!M48 -> 205478355000 | N48: =K48 -> 6176329027000 | O48: =IFERROR(6.72*(M48/N48),0) -> 0.22356557 | P48: =Data!K48 -> 6176329027000 | Q48: =Data!I48 -> 4512591084000 | R48: =IFERROR(1.05*(P48/Q48),0) -> 1.4371223 | S48: =IFERROR(I48+L48+O48+R48,0) -> 2.6710939
D49: 2017 | E49: =Data!F49 -> 483705909000 | F49: =Data!H49 -> 170181075000 | G49: =E49-F49 -> 313524834000 | H49: =Data!G49 -> 8162691116000 | I49: =IFERROR(6.56*(G49/H49),0) -> 0.25196628 | J49: =Data!J49 -> 1685534438000 | K49: =H49 -> 8162691116000 | L49: =IFERROR(3.26*(J49/K49),0) -> 0.67316553 | M49: =Data!M49 -> 355529117000 | N49: =K49 -> 8162691116000 | O49: =IFERROR(6.72*(M49/N49),0) -> 0.29269216 | P49: =Data!K49 -> 2104006591000 | Q49: =Data!I49 -> 5984418466000 | R49: =IFERROR(1.05*(P49/Q49),0) -> 0.36915983 | S49: =IFERROR(I49+L49+O49+R49,0) -> 1.5869838
D50: 2018 | E50: =Data!F50 -> 564045684000 | F50: =Data!H50 -> 362779204000 | G50: =E50-F50 -> 201266480000 | H50: =Data!G50 -> 9356504263000 | I50: =IFERROR(6.56*(G50/H50),0) -> 0.14111126 | J50: =Data!J50 -> 2121822247000 | K50: =H50 -> 9356504263000 | L50: =IFERROR(3.26*(J50/K50),0) -> 0.73928685 | M50: =Data!M50 -> 784108783000 | N50: =K50 -> 9356504263000 | O50: =IFERROR(6.72*(M50/N50),0) -> 0.56316022 | P50: =Data!K50 -> 2231804990000 | Q50: =Data!I50 -> 7033564683000 | R50: =IFERROR(1.05*(P50/Q50),0) -> 0.3331732 | S50: =IFERROR(I50+L50+O50+R50,0) -> 1.7767315
D51: 2019 | E51: =Data!F51 -> 506706000000 | F51: =Data!H51 -> 322081000000 | G51: =E51-F51 -> 184625000000 | H51: =Data!G51 -> 11084971000000 | I51: =IFERROR(6.56*(G51/H51),0) -> 0.10925965 | J51: =Data!J51 -> 2325009000000 | K51: =H51 -> 11084971000000 | L51: =IFERROR(3.26*(J51/K51),0) -> 0.68376628 | M51: =Data!M51 -> 336198000000 | N51: =K51 -> 11084971000000 | O51: =IFERROR(6.72*(M51/N51),0) -> 0.20381204 | P51: =Data!K51 -> 2563929000000 | Q51: =Data!I51 -> 8407279000000 | R51: =IFERROR(1.05*(P51/Q51),0) -> 0.32021364 | S51: =IFERROR(I51+L51+O51+R51,0) -> 1.3170516
D52: 2020 | E52: =Data!F52 -> 723140000000 | F52: =Data!H52 -> 255342000000 | G52: =E52-F52 -> 467798000000 | H52: =Data!G52 -> 13044264000000 | I52: =IFERROR(6.56*(G52/H52),0) -> 0.23525704 | J52: =Data!J52 -> 2387399000000 | K52: =H52 -> 13044264000000 | L52: =IFERROR(3.26*(J52/K52),0) -> 0.59665465 | M52: =Data!M52 -> 53150000000 | N52: =K52 -> 13044264000000 | O52: =IFERROR(6.72*(M52/N52),0) -> 0.027381231 | P52: =Data!K52 -> 2794003000000 | Q52: =Data!I52 -> 10081934000000 | R52: =IFERROR(1.05*(P52/Q52),0) -> 0.29098615 | S52: =IFERROR(I52+L52+O52+R52,0) -> 1.1502791
D53: 2021 | E53: =Data!F53 -> 848461000000 | F53: =Data!H53 -> 946159000000 | G53: =E53-F53 -> -97698000000 | H53: =Data!G53 -> 18260736000000 | I53: =IFERROR(6.56*(G53/H53),0) -> -0.0350971 | J53: =Data!J53 -> 2537438000000 | K53: =H53 -> 18260736000000 | L53: =IFERROR(3.26*(J53/K53),0) -> 0.45299641 | M53: =Data!M53 -> 130173000000 | N53: =K53 -> 18260736000000 | O53: =IFERROR(6.72*(M53/N53),0) -> 0.047904014 | P53: =Data!K53 -> 6683102000000 | Q53: =Data!I53 -> 11381796000000 | R53: =IFERROR(1.05*(P53/Q53),0) -> 0.61653337 | S53: =IFERROR(I53+L53+O53+R53,0) -> 1.0823367
D54: 2022 | E54: =Data!F54 -> 1239866000000 | F54: =Data!H54 -> 577879000000 | G54: =E54-F54 -> 661987000000 | H54: =Data!G54 -> 21494817000000 | I54: =IFERROR(6.56*(G54/H54),0) -> 0.20203171 | J54: =Data!J54 -> 2851684000000 | K54: =H54 -> 21494817000000 | L54: =IFERROR(3.26*(J54/K54),0) -> 0.43249914 | M54: =Data!M54 -> 385371000000 | N54: =K54 -> 21494817000000 | O54: =IFERROR(6.72*(M54/N54),0) -> 0.12047989 | P54: =Data!K54 -> 7706566000000 | Q54: =Data!I54 -> 13552263000000 | R54: =IFERROR(1.05*(P54/Q54),0) -> 0.59708805 | S54: =IFERROR(I54+L54+O54+R54,0) -> 1.3520988
D55: 2023 | E55: =Data!F55 -> 831272000000 | F55: =Data!H55 -> 318534000000 | G55: =E55-F55 -> 512738000000 | H55: =Data!G55 -> 23552167000000 | I55: =IFERROR(6.56*(G55/H55),0) -> 0.14281324 | J55: =Data!J55 -> 3386792000000 | K55: =H55 -> 23552167000000 | L55: =IFERROR(3.26*(J55/K55),0) -> 0.46878667 | M55: =Data!M55 -> 618387000000 | N55: =K55 -> 23552167000000 | O55: =IFERROR(6.72*(M55/N55),0) -> 0.17644069 | P55: =Data!K55 -> 9111525000000 | Q55: =Data!I55 -> 14172581000000 | R55: =IFERROR(1.05*(P55/Q55),0) -> 0.67504298 | S55: =IFERROR(I55+L55+O55+R55,0) -> 1.4630836
D56: 2024 | E56: =Data!F56 -> 0 | F56: =Data!H56 -> 0 | G56: =E56-F56 -> 0 | H56: =Data!G56 -> 0 | I56: =IFERROR(6.56*(G56/H56),0) -> 0 | J56: =Data!J56 -> 0 | K56: =H56 -> 0 | L56: =IFERROR(3.26*(J56/K56),0) -> 0 | M56: =Data!M56 -> 0 | N56: =K56 -> 0 | O56: =IFERROR(6.72*(M56/N56),0) -> 0 | P56: =Data!K56 -> 0 | Q56: =Data!I56 -> 0 | R56: =IFERROR(1.05*(P56/Q56),0) -> 0 | S56: =IFERROR(I56+L56+O56+R56,0) -> 0
B57: 6 | C57: PT Asuransi Ciputra Indonesia | D57: 2014 | E57: =Data!F57 -> 0 | F57: =Data!H57 -> 0 | G57: =E57-F57 -> 0 | H57: =Data!G57 -> 0 | I57: =IFERROR(6.56*(G57/H57),0) -> 0 | J57: =Data!J57 -> 0 | K57: =H57 -> 0 | L57: =IFERROR(3.26*(J57/K57),0) -> 0 | M57: =Data!M57 -> 0 | N57: =K57 -> 0 | O57: =IFERROR(6.72*(M57/N57),0) -> 0 | P57: =Data!K57 -> 0 | Q57: =Data!I57 -> 0 | R57: =IFERROR(1.05*(P57/Q57),0) -> 0 | S57: =IFERROR(I57+L57+O57+R57,0) -> 0
D58: 2015 | E58: =Data!F58 -> 0 | F58: =Data!H58 -> 0 | G58: =E58-F58 -> 0 | H58: =Data!G58 -> 0 | I58: =IFERROR(6.56*(G58/H58),0) -> 0 | J58: =Data!J58 -> 0 | K58: =H58 -> 0 | L58: =IFERROR(3.26*(J58/K58),0) -> 0 | M58: =Data!M58 -> 0 | N58: =K58 -> 0 | O58: =IFERROR(6.72*(M58/N58),0) -> 0 | P58: =Data!K58 -> 0 | Q58: =Data!I58 -> 0 | R58: =IFERROR(1.05*(P58/Q58),0) -> 0 | S58: =IFERROR(I58+L58+O58+R58,0) -> 0
D59: 2016 | E59: =Data!F59 -> 7116000000 | F59: =Data!H59 -> 3417000000 | G59: =E59-F59 -> 3699000000 | H59: =Data!G59 -> 98507000000 | I59: =IFERROR(6.56*(G59/H59),0) -> 0.24633214 | J59: =Data!J59 -> -4909000000 | K59: =H59 -> 98507000000 | L59: =IFERROR(3.26*(J59/K59),0) -> -0.16245891 | M59: =Data!M59 -> -4909000000 | N59: =K59 -> 98507000000 | O59: =IFERROR(6.72*(M59/N59),0) -> -0.33488463 | P59: =Data!K59 -> 95091000000 | Q59: =Data!I59 -> 3417000000 | R59: =IFERROR(1.05*(P59/Q59),0) -> 29.220237 | S59: =IFERROR(I59+L59+O59+R59,0) -> 28.969226
